Workbook

Sheet TOP 40
A1: Company Name | B1: PROVINCE | C1: Date of last inv | D1: CM
A2: ='route plans'!A64 -> RANJHA TRADERS HARDWARE & DIY STORE | B2: ='route plans'!D64 -> GAUTENG | C2: ='route plans'!P64 -> 0 | D2: ='route plans'!R64 -> N
A3: ='route plans'!A65 -> SINOVILLE FENCING | B3: ='route plans'!D65 -> GAUTENG | C3: ='route plans'!P65 -> 0 | D3: ='route plans'!R65 -> N
A4: ='route plans'!A66 -> TIMBERCITY ALLDAYS | B4: ='route plans'!D66 -> LIMPOPO | C4: ='route plans'!P66 -> 0 | D4: ='route plans'!R66 -> Y
A5: ='route plans'!A69 -> UNIVERSAL PAINTS MENLYN | B5: POLOKWANE | C5: ='route plans'!P69 -> 0 | D5: ='route plans'!R69 -> N
A6: ='route plans'!#REF! -> #REF! | B6: POLOKWANE | C6: ='route plans'!#REF! -> #REF! | D6: ='route plans'!#REF! -> #REF!
A7: ='route plans'!A70 -> AJ BOLTS & NUTS | B7: POLOKWANE | C7: ='route plans'!P70 -> 0 | D7: ='route plans'!R70 -> N
A8: ='route plans'!A71 -> SAZAR TILE AND HARDWARE | B8: GAUTENG | C8: ='route plans'!P71 -> 0 | D8: ='route plans'!R71 -> N
A9: ='route plans'!A12 -> RALF SUPPLIES | B9: ='route plans'!D72 -> GAUTENG | C9: ='route plans'!P72 -> 0 | D9: ='route plans'!R72 -> N
A10: ='route plans'!A73 -> MUHAMMADS HARDWARE | B10: GAUTENG | C10: ='route plans'!P73 -> 0 | D10: ='route plans'!R73 -> Y
A11: ='route plans'!A74 -> MACBUILD | B11: GAUTENG | C11: ='route plans'!P74 -> 44261 | D11: ='route plans'!R74 -> N
A12: ='route plans'!A75 -> BUCO ATHLONE | B12: ='route plans'!D75 -> WESTERN CAPE | C12: ='route plans'!P75 -> 44350 | D12: ='route plans'!R75 -> N
A13: ='route plans'!A76 -> JACKRITE MICA QUEESWOOD | B13: GAUTENG | C13: ='route plans'!P76 -> 0 | D13: ='route plans'!R76 -> N
A14: ='route plans'!A77 -> LIGHTHOUSE MICA HARDWARE | B14: GAUTENG | C14: ='route plans'!P77 -> 0 | D14: ='route plans'!R77 -> N
A15: ='route plans'!A78 -> DIY NORTHDALE | B15: ='route plans'!D78 -> GAUTENG | C15: ='route plans'!P78 -> 0 | D15: ='route plans'!R78 -> N
A16: ='route plans'!A80 -> AKSA BUILDERS SUPPLIERS | B16: GAUTENG | C16: ='route plans'!P80 -> 0 | D16: ='route plans'!R80 -> N
A17: ='route plans'!A81 -> KHAN'S HARDWARE & GENERAL DEALER | B17: ='route plans'!D81 -> GAUTENG | C17: ='route plans'!P81 -> 0 | D17: ='route plans'!R81 -> N
A18: ='route plans'!A82 -> DIY THE REEDS | B18: ='route plans'!D82 -> GAUTENG | C18: ='route plans'!P82 -> 0 | D18: ='route plans'!R82 -> N
A19: ='route plans'!A83 -> DIY LYTTLETON | B19: ='route plans'!D83 -> GAUTENG | C19: ='route plans'!P83 -> 0 | D19: ='route plans'!R83 -> N
A20: ='route plans'!A84 -> RAMODISE SUPERSTORE & WHOLESALES | B20: ='route plans'!D84 -> GAUTENG | C20: ='route plans'!P84 -> 0 | D20: ='route plans'!R84 -> N
A21: =#REF! -> #REF! | B21: =#REF! -> #REF! | C21: =#REF! -> #REF! | D21: =#REF! -> #REF!
A22: ='route plans'!A88 -> ALL PAINT & HARDWARE JEFFREY’S BAY (DAJEES ) | B22: ='route plans'!D88 -> EASTERN CAPE | C22: ='route plans'!P88 -> 0 | D22: ='route plans'!R88 -> N
A23: ='route plans'!A89 -> ALLIED BUILD (ADDITIONAL DELIVERY ADDRESS FOR INDALI) | B23: ='route plans'!D89 -> EASTERN CAPE | C23: ='route plans'!P89 -> 0 | D23: ='route plans'!R89 -> N
A24: ='route plans'!A90 -> STEEL & PIPES CENTURION | B24: ='route plans'!D90 -> GAUTENG | C24: ='route plans'!P90 -> 0 | D24: ='route plans'!R90 -> N
A25: ='route plans'!A91 -> ALLIED BUILDERS CLAYVILLE | B25: ='route plans'!D91 -> GAUTENG | C25: ='route plans'!P91 -> 0 | D25: ='route plans'!R91 -> N
A26: ='route plans'!A92 -> HAMMERKOP HARDWARE | B26: ='route plans'!D92 -> GAUTENG | C26: ='route plans'!P92 -> 0 | D26: ='route plans'!R92 -> N
A27: ='route plans'!A96 -> HUMPHRIES &JEWELL | B27: GAUTENG | C27: ='route plans'!P96 -> 0 | D27: ='route plans'!R96 -> Y
A28: ='route plans'!A97 -> NJR STEEL PTA EAST | B28: ='route plans'!D97 -> GAUTENG | C28: ='route plans'!P97 -> 0 | D28: ='route plans'!R97 -> N
A29: ='route plans'!A98 -> ALLIED BUILDERS HAMMANSKRAAL | B29: GAUTENG | C29: ='route plans'!P98 -> 0 | D29: ='route plans'!R98 -> N
A30: ='route plans'!A99 -> ALPHA BUILD HARDWARE | B30: GAUTENG | C30: ='route plans'!P99 -> 0 | D30: ='route plans'!R99 -> N
A31: =#REF! -> #REF! | B31: =#REF! -> #REF! | C31: =#REF! -> #REF! | D31: =#REF! -> #REF!
A32: ='route plans'!A100 -> WESLOU FLOOR COVERINGS | B32: ='route plans'!D100 -> LIMPOPO | C32: ='route plans'!P100 -> 0 | D32: ='route plans'!R100 -> N
A33: ='route plans'!A101 -> MILLENIUM PIPE & STEEL | B33: ='route plans'!D101 -> GAUTENG | C33: ='route plans'!P101 -> 0 | D33: ='route plans'!R101 -> N
A34: ='route plans'!A103 -> TIMBERCITY THOHOYANDOU | B34: GAUTENG | C34: ='route plans'!P103 -> 0 | D34: ='route plans'!R103 -> Y
A35: ='route plans'!A105 -> DADA'S WORLD OF HARWARE | B35: ='route plans'!D105 -> LIMPOPO | C35: ='route plans'!P105 -> 0 | D35: ='route plans'!R105 -> N
A36: ='route plans'!A106 -> ALPHA BUILDERS SUPPLY | B36: ='route plans'!D106 -> GAUTENG | C36: ='route plans'!P106 -> 0 | D36: ='route plans'!R106 -> Y
A37: ='route plans'!A108 -> VALHALLA GENERAL DEALERS | B37: GAUTENG | C37: ='route plans'!P108 -> 0 | D37: ='route plans'!R108 -> N
A38: ='route plans'!A109 -> CLUB SEVEN HARDWARE | B38: GAUTENG | C38: ='route plans'!P109 -> 0 | D38: ='route plans'!R109 -> N
A39: ='route plans'!A110 -> ALPHA BUILDERS SUPPLY | B39: ='route plans'!D110 -> GAUTENG | C39: ='route plans'!P110 -> 0 | D39: ='route plans'!R110 -> N
A40: ='route plans'!A111 -> EKAYA HARDWARE GAUTENG | B40: ='route plans'!D111 -> GAUTENG | C40: ='route plans'!P111 -> 0 | D40: ='route plans'!R111 -> Y
A41: ='route plans'!A112 -> ELITE BUILDING SUPPLIES | B41: ='route plans'!D112 -> WESTERN CAPE | C41: ='route plans'!P112 -> 0 | D41: ='route plans'!R112 -> N

Sheet route plans
A1: STORE NAME | B1: AREA | C1: CITY | D1: PROVINCE | E1: STREET ADDRESS | F1: EMAIL | G1: WHOLESALER | H1: GROUP | I1: ACTIVE/INACTIVE | J1: DATE VISITED | K1: Days since last visted | L1: NEXT VISIT DATE | M1: PRODUCT | N1: TYPE OF CLIENT | O1: CREDIT APP | P1: Last invoice sent date | Q1: Days from last order | R1: Cornice Maker | S1: CURRENT SUPPLIER | T1: CUSTOMER NAME | U1: CUSTOMER NUMBER | V1: REP NAME | W1: CUSTOMER COMMENTS | X1: LAST PHONED DATE | Y1: DAYS FROM LAST CALL | Z1: PHONED BY | AA1: EMAIL | AB1: LAST MAILED | AC1: DAYS FROM LAST MAIL | AD1: MAILED BY | AE1: WHAT WAS MAILED | AF1: CLIENT FEEDBACK | AG1: HAPPY/ANGRY
A2: Power Build MODIMOLLE | B2: MODIMOLE | C2: MODIMOLE | D2: LIMPOPO | E2: CORNER OF NELSON MANDELA AND ALLAN STREET, MODIMOLLE, 0150 | G2: NO | H2: POWER BUILD | I2: ACTIVE | J2: 44572 | K2: =ABS(IF(ISBLANK(J2),"",TODAY()-J2)) -> 735 | L2: =J2+14 -> 44586 | M2: CORNICE | N2: N/A | O2: NO | Q2: =ABS(IF(ISBLANK(P2),"",TODAY()-P2)) -> #VALUE! | R2: N | T2: VAN ZYL OBERHOLZER | U2: 084 417 2334 | V2: TYRONE | W2: CLIENT ACCEPTED QUOTE, WILL SEND DOCUMENTS FOR APPROVAL | X2: 44480 | Y2: 9 | Z2: YOLANDI | AA2: VANZYLOBE@GMAIL.COM | AB2: 44508 | AC2: =ABS(IF(ISBLANK(AB2),"",TODAY()-AB2)) -> 799 | AD2: YOLANDI | AE2: POWER BUILD BR PROMOTION | AF2: CLIENT WILL COMPLETE CREDIT APP
A3: Power Build THLABANE | B3: THLABANE | C3: RUSTENBURG | D3: NORTH WEST | E3: 219 BEYERS NAUDE, RUSTENBURG, NORTHWEST, 0299 | G3: NO | H3: POWER BUILD | I3: INACTIVE | J3: 44378 | K3: =ABS(IF(ISBLANK(J3),"",TODAY()-J3)) -> 929 | L3: =J3+14 -> 44392 | M3: CORNICE | N3: N/A | O3: NO | Q3: =ABS(IF(ISBLANK(P3),"",TODAY()-P3)) -> #VALUE! | R3: N | T3: JOHN | U3: 824801380 | V3: HEYNS | Y3: 44489 | AA3: MSIZI@RTINDUSTRIES.CO.ZA | AB3: 44480 | AC3: =ABS(IF(ISBLANK(AB3),"",TODAY()-AB3)) -> 827 | AD3: YOLANDI | AE3: POWER BUILD BR PROMOTION
A4: MAKRO CROWN MINES | B4: SELBY | C4: SELBY | D4: GAUTENG | E4: CORNER OF MAIN REEF ROAD & HANOVER STREET, SELBY, JHB | G4: NO | H4: MAKRO | I4: ACTIVE | J4: 44585 | K4: =ABS(IF(ISBLANK(J4),"",TODAY()-J4)) -> 722 | L4: =J4+14 -> 44599 | M4: GRASS/PEBBLES/POTS | N4: N/A | O4: NO | R4: N | S4: FLINSTONE | V4: ELSA
A5: HDS CUT & EDGE | B5: BENONI | C5: BENONI | D5: GAUTENG | E5: 28 Liverpool Road, Benoni | G5: NO | H5: CUT & EDGE | I5: NEW | J5: 44579 | K5: =ABS(IF(ISBLANK(J5),"",TODAY()-J5)) -> 728 | L5: =J5+14 -> 44593 | M5: CORNICE | N5: N/A | O5: NO | Q5: =ABS(IF(ISBLANK(P5),"",TODAY()-P5)) -> #VALUE! | R5: N | T5: Zack | U5: 011 422 4839 | V5: REINHARDT | W5: Appointment to be scheduled for the 1st week of September | X5: 44473 | Y5: 16 | Z5: YOLANDI | AA5: SALES@HDSVANDERBIJLPARK.CO.ZA | AB5: 44497 | AC5: =ABS(IF(ISBLANK(AB5),"",TODAY()-AB5)) -> 810 | AD5: YOLANDI | AE5: HOMEPACK BR PROMOTION
A6: TLT INDUSTRIAL HARDWARE SUPPLIES | B6: KEMPTON PARK | C6: KEMPTON PARK | D6: GAUTENG | E6: 49 rRIGGER ROAD, SPARTAN, KEMPTON | G6: NO | H6: ESSENTIAL | I6: NEW | J6: 44588 | K6: =ABS(IF(ISBLANK(J6),"",TODAY()-J6)) -> 719 | L6: =J6+14 -> 44602 | M6: CORNICE | N6: N/A | O6: NO | R6: N | T6: Leigh-Anne | U6: 011 394 9689 | V6: REINHARDT | W6: Callback after 13:00
A7: MAKRO ALBERTON | B7: ALBERTON | C7: ALBERTON | D7: GAUTENG | E7: CORNER OF HEIDELBERG ROAD & ASCOT ROAD, NEWMARKET, ALBERTON | G7: NO | H7: MAKRO | I7: ACTIVE | J7: 12/10/0221 | K7: =ABS(IF(ISBLANK(J7),"",TODAY()-J7)) -> #VALUE! | L7: =J7+14 -> #VALUE! | M7: GRASS/PEBBLES/POTS
A8: DIE HOUT FABRIEK | B8: VAN DER BIJL | C8: VAN DER BIJL | D8: GAUTENG | E8: 3 WEBBER STR | G8: NO | H8: NONE | I8: INACTIVE | J8: 44420 | K8: =ABS(IF(ISBLANK(J8),"",TODAY()-J8)) -> 887 | L8: =J8+14 -> 44434 | M8: CORNICE | N8: N/A | O8: NO | P8: 44376 | Q8: =ABS(IF(ISBLANK(P8),"",TODAY()-P8)) -> 931 | R8: N | U8: 0169337712 | V8: HEYNS | X8: 44473 | Y8: 16 | Z8: YOLANDI | AA8: DIEHOUTFABRIEK@VODAMAIL.CO.ZA | AB8: 44497 | AC8: =ABS(IF(ISBLANK(AB8),"",TODAY()-AB8)) -> 810 | AD8: YOLANDI | AE8: HOMEPACK BR PROMOTION
A9: STYLISH CEILINGS SPRINGS | B9: SPRINGS | C9: SPRINGS | D9: GAUTENG | E9: 208 NIGEL ROAD, SPRINGS | G9: NO | H9: NONE | I9: NEW | J9: 44579 | K9: =ABS(IF(ISBLANK(J9),"",TODAY()-J9)) -> 728 | L9: =J9+14 -> 44593 | M9: CORNICE | N9: N/A | O9: N | R9: N | T9: COLE KUKKARD/JP | U9: 064 843 9138 | V9: REINHARDT | W9: Callback after 14:00
A10: MAKRO CARNIVAL | B10: BOKSBURG | C10: BOKSBURG | D10: GAUTENG | E10: 16 BEECHWOOD STREET, BRAKPAN | G10: NO | H10: MAKRO | I10: ACTIVE | J10: 44585 | K10: =ABS(IF(ISBLANK(J10),"",TODAY()-J10)) -> 722 | L10: =J10+14 -> 44599 | M10: GRASS/PEBBLES/POTS | N10: N/A | O10: N | Q10: =ABS(IF(ISBLANK(P10),"",TODAY()-P10)) -> #VALUE! | R10: N | S10: FLINSTONE | V10: ELSA
A11: MAKRO GERMISTON | B11: GERMISTON | C11: GERMISTON | D11: GAUTENG | E11: 16 HERMAN STREET, MEADOWDALE, GERMISTON | G11: NO | H11: MAKRO | I11: ACTIVE | J11: 44585 | K11: =ABS(IF(ISBLANK(J11),"",TODAY()-J11)) -> 722 | L11: =J11+14 -> 44599 | M11: GRASS/PEBBLES/POTS | N11: N/A | O11: N | Q11: =ABS(IF(ISBLANK(P11),"",TODAY()-P11)) -> #VALUE! | R11: N | S11: FLINSTONE | V11: ELSA | W11: NEEDS STANDS
A12: RALF SUPPLIES | B12: VAN DER BIJL | C12: VAN DER BIJL | D12: GAUTENG | E12: 10 NORTH ST | G12: NO | H12: NONE | I12: INACTIVE | J12: 44417 | K12: =ABS(IF(ISBLANK(J12),"",TODAY()-J12)) -> 890 | L12: =J12+14 -> 44431 | M12: CORNICE | N12: N/A | O12: NO | Q12: =ABS(IF(ISBLANK(P12),"",TODAY()-P12)) -> #VALUE! | R12: N | U12: 0169324060 | V12: HEYNS | X12: 44473 | Y12: 16 | Z12: YOLANDI | AA12: RALF@ADMIN@LANTIC.NET | AB12: 44497 | AC12: =ABS(IF(ISBLANK(AB12),"",TODAY()-AB12)) -> 810 | AD12: YOLANDI | AE12: HOMEPACK BR PROMOTION
A13: AK'S DISTRIBUTORS T/A DAWSONS HARDWARE | B13: LYDENBURG | C13: LYDENBURG | D13: MPUMALANGA | E13: 38 JOUBERT STREET, LYDENBURG | G13: NO | H13: NONE | I13: NEW | J13: 44599 | K13: =ABS(IF(ISBLANK(J13),"",TODAY()-J13)) -> 708 | L13: =J13+14 -> 44613 | M13: CORNICE | N13: N/A | O13: NO | Q13: =ABS(IF(ISBLANK(P13),"",TODAY()-P13)) -> #VALUE! | R13: N | T13: ABDUL | U13: 0728676302 | V13: REINHARDT | W13: ORDERED
A14: KLIPKOR | B14: VAN DER BIJL | C14: VAN DER BIJL | D14: GAUTENG | E14: EASTMAN STREET | G14: NO | H14: NONE | I14: INACTIVE | J14: 44414 | K14: =ABS(IF(ISBLANK(J14),"",TODAY()-J14)) -> 893 | L14: =J14+14 -> 44428 | M14: CORNICE | N14: N/A | O14: NO | Q14: =ABS(IF(ISBLANK(P14),"",TODAY()-P14)) -> #VALUE! | R14: N | U14: 0169861441 | V14: HEYNS | X14: 44473 | Y14: 16 | Z14: YOLANDI | AA14: KLIPKOR@ABSAMAIL.CO.ZA | AB14: 44497 | AC14: =ABS(IF(ISBLANK(AB14),"",TODAY()-AB14)) -> 810 | AD14: YOLANDI | AE14: HOMEPACK BR PROMOTION
A15: BUILDERS CORNER | B15: BENONI | C15: BENONI | D15: GAUTENG | E15: 36 SWAN STREET, BENONI | G15: NO | H15: NONE | I15: NEW | J15: 44585 | K15: =ABS(IF(ISBLANK(J15),"",TODAY()-J15)) -> 722 | L15: =J15+14 -> 44599 | M15: CORNICE | N15: N/A | O15: N | Q15: =ABS(IF(ISBLANK(P15),"",TODAY()-P15)) -> #VALUE! | R15: N | S15: ELEGANT | T15: NAHEEM | U15: 011 421 0011/065 320 6505 | V15: REINHARDT | W15: Catalogue sent, to follow-up tomorrow
A16: IMPACT | B16: VAN DER BIJL | C16: VAN DER BIJL | D16: GAUTENG | E16: GOLDEN HIGH WAY | G16: NO | H16: NONE | I16: INACTIVE | J16: 44409 | K16: =ABS(IF(ISBLANK(J16),"",TODAY()-J16)) -> 898 | L16: =J16+14 -> 44423 | M16: CORNICE | N16: N/A | O16: NO | Q16: =ABS(IF(ISBLANK(P16),"",TODAY()-P16)) -> #VALUE! | R16: N | U16: 0795007917 | V16: HEYNS | X16: 44473 | Y16: 16 | Z16: YOLANDI | AA16: BUYER@BOLTANDNUT.CO.ZA | AB16: 44497 | AC16: =ABS(IF(ISBLANK(AB16),"",TODAY()-AB16)) -> 810 | AD16: YOLANDI | AE16: HOMEPACK BR PROMOTION
A17: OLYMPIC MICA | B17: VAN DER BIJL | C17: VAN DER BIJL | D17: GAUTENG | E17: 2 PETTER ST | G17: NO | H17: MICA | I17: INACTIVE | J17: 44405 | K17: =ABS(IF(ISBLANK(J17),"",TODAY()-J17)) -> 902 | L17: =J17+14 -> 44419 | M17: CORNICE | N17: N/A | O17: NO | Q17: =ABS(IF(ISBLANK(P17),"",TODAY()-P17)) -> #VALUE! | R17: N | U17: 0169819135 | V17: HEYNS | X17: 44473 | Y17: 16 | Z17: YOLANDI | AA17: INFO@OLYMPICMICA.CO.ZA | AB17: 44497 | AC17: =ABS(IF(ISBLANK(AB17),"",TODAY()-AB17)) -> 810 | AD17: YOLANDI | AE17: HOMEPACK BR PROMOTION
A18: CONSTRUCTA | B18: VAN DER BIJL | C18: VAN DER BIJL | D18: GAUTENG | E18: CNR RAUTENBACH,GOLDEN | G18: NO | H18: NONE | I18: NEW | J18: 44578 | K18: =ABS(IF(ISBLANK(J18),"",TODAY()-J18)) -> 729 | L18: =J18+14 -> 44592 | M18: CORNICE | N18: N/A | O18: NO | Q18: =ABS(IF(ISBLANK(P18),"",TODAY()-P18)) -> #VALUE! | R18: N | T18: WEAN | U18: 0161100181 | V18: ELSA | W18: SPOKE TO DEAN, STARTING A HOUSING DEVELOPMENT IN FEB, MUST SEE HIM AGAIN IN FEB | X18: 44473 | Y18: 16 | Z18: YOLANDI | AA18: WEAN@CONSTRUCTA.COM | AB18: 44497 | AC18: =ABS(IF(ISBLANK(AB18),"",TODAY()-AB18)) -> 810 | AD18: YOLANDI | AE18: HOMEPACK BR PROMOTION
A19: CARRIGTON HARDWARE ATHLONE | B19: ATHLONE | C19: ATHLONE | D19: WESTERN CAPE | E19: ATHLONE | G19: NO | H19: NONE | I19: ACTIVE | J19: 44434 | K19: =ABS(IF(ISBLANK(J19),"",TODAY()-J19)) -> 873 | L19: =J19+14 -> 44448 | M19: CORNICE | N19: COD | O19: N | Q19: =ABS(IF(ISBLANK(P19),"",TODAY()-P19)) -> #VALUE! | R19: N | X19: 44487 | Y19: 2 | Z19: YOLANDI | AA19: FOXBOUERS@TELKOMSA.NET | AB19: 44497 | AC19: =ABS(IF(ISBLANK(AB19),"",TODAY()-AB19)) -> 810 | AD19: YOLANDI | AE19: HOMEPACK BR PROMOTION
A20: JACKS | B20: VAN DER BIJL | C20: VAN DER BIJL | D20: GAUTENG | E20: 2 PETTER ST VAN DER BIJL | G20: NO | H20: NONE | I20: INACTIVE | J20: 44397 | K20: =ABS(IF(ISBLANK(J20),"",TODAY()-J20)) -> 910 | L20: =J20+14 -> 44411 | M20: CORNICE | N20: N/A | O20: NO | Q20: =ABS(IF(ISBLANK(P20),"",TODAY()-P20)) -> #VALUE! | R20: N | U20: 0169819135 | V20: HEYNS | X20: 44473 | Y20: 16 | Z20: YOLANDI | AA20: INFO@OLYMPICMICA.CO.ZA | AB20: 44497 | AC20: =ABS(IF(ISBLANK(AB20),"",TODAY()-AB20)) -> 810 | AD20: YOLANDI | AE20: HOMEPACK BR PROMOTION
A21: TUGELA | B21: VAN DER BIJL | C21: VAN DER BIJL | D21: GAUTENG | E21: 134 HANS STRYDOM | G21: NO | H21: NONE | I21: INACTIVE | J21: 44582 | K21: =ABS(IF(ISBLANK(J21),"",TODAY()-J21)) -> 725 | L21: =J21+14 -> 44596 | M21: CORNICE | N21: N/A | O21: NO | Q21: =ABS(IF(ISBLANK(P21),"",TODAY()-P21)) -> #VALUE! | R21: N | S21: ELEGANT | T21: NITA | U21: 0169816900 | V21: REINHARDT | W21: WILL COMPARE PRICE | X21: 44473 | Y21: 16 | Z21: YOLANDI | AA21: TUGELA.ORDERS@CYBERSERVE.CO.ZA | AB21: 44497 | AC21: =ABS(IF(ISBLANK(AB21),"",TODAY()-AB21)) -> 810 | AD21: YOLANDI | AE21: HOMEPACK BR PROMOTION
A22: MAKRO CENTURION | B22: CENTURION | C22: CENTURION | D22: GAUTENG | E22: 2 BLOUKRANS ROAD, CENTURION | G22: NO | H22: MAKRO | I22: ACTIVE | J22: 44582 | K22: =ABS(IF(ISBLANK(J22),"",TODAY()-J22)) -> 725 | L22: =J22+14 -> 44596 | M22: GRASS | N22: N/A | O22: N | Q22: =ABS(IF(ISBLANK(P22),"",TODAY()-P22)) -> #VALUE! | R22: N | S22: FLINSTONE | V22: ELSA | W22: HAPPY
A23: 3 STAR HARDWARE BUILDING MATERIAL | B23: RELETO SECTION | C23: SILVERKRANS | D23: NORTH WEST | E23: 1435 RALETO SECTION, SILVERKRANS, NORTH WEST | G23: NO | H23: EST | I23: NEW | J23: 44386 | K23: =ABS(IF(ISBLANK(J23),"",TODAY()-J23)) -> 921 | L23: =J23+14 -> 44400 | M23: CORNICE | N23: N/A | O23: NO | Q23: =ABS(IF(ISBLANK(P23),"",TODAY()-P23)) -> #VALUE! | R23: N | T23: M.W. ARSHAD | U23: 074 518 2972 | W23: No Answer, call keeps cutting | AA23: ALI.KHATANA07@GMAIL.COM | AB23: 44497 | AC23: =ABS(IF(ISBLANK(AB23),"",TODAY()-AB23)) -> 810 | AD23: YOLANDI | AE23: HOMEPACK BR PROMOTION
A24: BUCO ATHLONE | B24: ATHLONE | C24: ATHLONE | D24: WESTERN CAPE | E24: 57 BELGRAVIA ROAD, ATHLONE, 7764 | H24: BUCO | I24: NEW | J24: 44386 | K24: =ABS(IF(ISBLANK(J24),"",TODAY()-J24)) -> 921 | L24: =J24+14 -> 44400 | M24: CORNICE | N24: N/A | O24: NO | Q24: =ABS(IF(ISBLANK(P24),"",TODAY()-P24)) -> #VALUE! | R24: N | T24: ANEESA VAN DER FORT AVANDERFORT@BUCO.CO.ZA 083 381 2597 | X24: 44487 | Y24: 2 | Z24: YOLANDI | AA24: JANNIE@AHM.CO.ZA | AB24: 44497 | AC24: =ABS(IF(ISBLANK(AB24),"",TODAY()-AB24)) -> 810 | AD24: YOLANDI | AE24: HOMEPACK BR PROMOTION | AG24: HAPPY
A25: HOT POT | B25: VEREENIGING | C25: VEREENIGING | D25: GAUTENG | E25: 108A Houtkop Road, Duncanville, Vereeniging | G25: NO | H25: NONE | I25: INACTIVE | J25: 44592 | K25: =ABS(IF(ISBLANK(J25),"",TODAY()-J25)) -> 715 | L25: =J25+14 -> 44606 | M25: CORNICE | N25: N/A | O25: NO | Q25: =ABS(IF(ISBLANK(P25),"",TODAY()-P25)) -> #VALUE! | R25: N | T25: CORLIA | U25: 0164281113 | V25: REINHARDT | W25: Requested catalogue and appointment for the week of 18th or 25th July | X25: 44473 | Y25: 16 | Z25: YOLANDI | AA25: CORLIA@HOTPOTPAINT.COM | AB25: 44497 | AC25: =ABS(IF(ISBLANK(AB25),"",TODAY()-AB25)) -> 810 | AD25: YOLANDI | AE25: HOMEPACK BR PROMOTION
A26: HARDWARE INC | B26: VEREENIGING | C26: VEREENIGING | D26: GAUTENG | E26: 1 UNION ST | G26: NO | H26: ESSENTIAL | I26: INACTIVE | J26: 44582 | K26: =ABS(IF(ISBLANK(J26),"",TODAY()-J26)) -> 725 | L26: =J26+14 -> 44596 | M26: CORNICE | N26: N/A | O26: NO | P26: 44021 | Q26: =ABS(IF(ISBLANK(P26),"",TODAY()-P26)) -> 1286 | R26: N | S26: UPPER EDGE | T26: KEVIN | U26: 0663334324 | V26: REINHARDT | W26: Callback later | X26: 44473 | Y26: 16 | Z26: YOLANDI | AA26: INAM@HARDWAREINC.CO.ZA | AB26: 44497 | AC26: =ABS(IF(ISBLANK(AB26),"",TODAY()-AB26)) -> 810 | AD26: YOLANDI | AE26: HOMEPACK BR PROMOTION
A27: A.A BUILDING MATERIAL LESOTHO | B27: LERIBE | C27: LERIBE | D27: LESOTHO | E27: AIRPORT ROAD LERIBE LESOTHO | G27: NO | H27: EST | I27: NEW | J27: 44387 | K27: =ABS(IF(ISBLANK(J27),"",TODAY()-J27)) -> 920 | L27: =J27+14 -> 44401 | M27: CORNICE | N27: N/A | O27: NO | Q27: =ABS(IF(ISBLANK(P27),"",TODAY()-P27)) -> #VALUE! | R27: N | T27: HASSEN NOORMOHAMED | U27: 266 22400795 | W27: Invalid contact details | AA27: IRSHU7860@HOTMAIL.COM | AB27: 44497 | AC27: =ABS(IF(ISBLANK(AB27),"",TODAY()-AB27)) -> 810 | AD27: YOLANDI | AE27: HOMEPACK BR PROMOTION
A28: MUNAZA TRADERS CC T/A RAJA WHOLESALERS | B28: ACORNHOEK | C28: ACORNHOEK | D28: MPUMALANGA | E28: R40 NORTH | G28: YES | H28: NONE | I28: INACTIVE | J28: 44595 | K28: =ABS(IF(ISBLANK(J28),"",TODAY()-J28)) -> 712 | L28: =J28+14 -> 44609 | M28: CORNICE | N28: 30DAYS | O28: NO | P28: 44188 | Q28: =ABS(IF(ISBLANK(P28),"",TODAY()-P28)) -> 1119 | R28: Y | T28: FIAYAZ | U28: 013 795 5297/081 248 0393 | V28: REINHARDT | W28: No Answer | AA28: ACTIONBUILD@LIVE.CO.ZA | AB28: 44497 | AC28: =ABS(IF(ISBLANK(AB28),"",TODAY()-AB28)) -> 810 | AD28: YOLANDI | AE28: HOMEPACK BR PROMOTION
A29: ACTIVE BUILD AND DÉCOR | B29: THOHOYANDOU | C29: THOHOYANDOU | D29: LIMPOPO | E29: SHOP D1B, SABINA PLAZA, THOHOYANDOU | G29: NO | H29: EST | I29: NEW | J29: 44373 | K29: =ABS(IF(ISBLANK(J29),"",TODAY()-J29)) -> 934 | L29: =J29+14 -> 44387 | M29: CORNICE | N29: N/A | O29: NO | Q29: =ABS(IF(ISBLANK(P29),"",TODAY()-P29)) -> #VALUE! | R29: N | T29: MUAAZ SAGIR | U29: 015 962 5654/072 952 4091 | W29: No Answer | AA29: ACTIVEBUILD1931@GMAIL.COM; BRIDGEMOTORS@TISCALI.CO.ZA | AB29: 44497 | AC29: =ABS(IF(ISBLANK(AB29),"",TODAY()-AB29)) -> 810 | AD29: YOLANDI | AE29: HOMEPACK BR PROMOTION
A30: BUILD IT DTM | B30: BENONI | C30: BENONI | D30: GAUTENG | E30: 19 LIVERPOOL ROAD, BENONI | G30: NO | H30: BUILD IT | I30: NEW | J30: 44579 | K30: =ABS(IF(ISBLANK(J30),"",TODAY()-J30)) -> 728 | L30: =J30+14 -> 44593 | M30: CORNICE | N30: N/A | O30: N | R30: N | S30: ELEGANT | T30: Aqeefah | U30: 011 421 7659/067 747 6933 | V30: REINHARD | W30: Requested updated catalogue via whatsapp
A31: CARRINGTON HARDWARE | B31: CAPE TOWN | C31: CAPE TOWN | D31: WESTERN CAPE | E31: 4 HAJDI CRES | G31: NO | H31: NONE | I31: ACTIVE | J31: 44603 | K31: =ABS(IF(ISBLANK(J31),"",TODAY()-J31)) -> 704 | L31: =J31+14 -> 44617 | M31: CORNICE | N31: N/A | O31: N | R31: N | V31: ASH | W31: ORDER PLACED
A32: THE FX GROUP | B32: BENONI | C32: BENONI | D32: GAUTENG | E32: 28 LIVERPOOL ROAD | G32: YES | H32: NONE | I32: NEW | J32: 44579 | K32: =ABS(IF(ISBLANK(J32),"",TODAY()-J32)) -> 728 | L32: =J32+14 -> 44593 | M32: CORNICE | N32: N/A | O32: N | R32: N | T32: ZACK | V32: REINHARD | W32: NEED TO MAKE APOINTMENT TO SEE THE BUYER
A33: ACTIVE BUILD HARDWARE | B33: OBERHOLZER | C33: CARLTONVILLE | D33: GAUTENG | E33: 44 VAN ZYL STREET, OBERHOLZER, CARLTONVILLE | G33: NO | H33: EST | I33: NEW | J33: 44372 | K33: =ABS(IF(ISBLANK(J33),"",TODAY()-J33)) -> 935 | L33: =J33+14 -> 44386 | M33: CORNICE | N33: N/A | O33: NO | Q33: =ABS(IF(ISBLANK(P33),"",TODAY()-P33)) -> #VALUE! | R33: N | T33: ZAAKIR ESSOOP | U33: 018 788 2275 | AA33: ACTIVEBUILD@GMAIL.COM | AB33: 44497 | AC33: =ABS(IF(ISBLANK(AB33),"",TODAY()-AB33)) -> 810 | AD33: YOLANDI | AE33: HOMEPACK BR PROMOTION
A34: TIMBERCITY LOUIS TRICHARDT | B34: TRICHARDT | C34: TRICHARDT | D34: LIMPOPO | E34: 93 GROBLER ST | G34: NO | H34: EST | I34: ACTIVE | J34: 44526 | K34: =ABS(IF(ISBLANK(J34),"",TODAY()-J34)) -> 781 | L34: =J34+14 -> 44540 | M34: CORNICE | N34: 30DAYS | O34: NO | Q34: =ABS(IF(ISBLANK(P34),"",TODAY()-P34)) -> #VALUE! | R34: Y | T34: MAZHAR | U34: 0820441200 | V34: TYRONE | W34: HAS ENOUGH CORNICE AND BUYS GARAGEDOORS AT THE SAME SUPPLIER AS US | X34: 44433 | Y34: 56 | AA34: BUYER@JURIHARDWARE.CO.ZA | AB34: 44497 | AC34: =ABS(IF(ISBLANK(AB34),"",TODAY()-AB34)) -> 810 | AD34: YOLANDI | AE34: HOMEPACK BR PROMOTION | AG34: HAPPY
A35: BUCO ACORNHOEK | B35: ACORNHOEK | C35: ACORNHOEK | D35: MPUMALANGA | E35: CNR R40 & GREENVALLEY TURN-OFF, GREENVALLEY TRUST FARM 473, ACORNHOEK, 1380 | G35: NO | H35: BUCO | I35: NEW | J35: 44384 | K35: =ABS(IF(ISBLANK(J35),"",TODAY()-J35)) -> 923 | L35: =J35+14 -> 44398 | M35: CORNICE | N35: N/A | O35: NO | P35: 44211 | Q35: =ABS(IF(ISBLANK(P35),"",TODAY()-P35)) -> 1096 | R35: N | T35: DEBBY GUNN-HENDERSON DGUNN-HENDERSON@BUCO.CO.ZA 073 335 7706 | X35: 44543 | Y35: 44489 | Z35: GERHARD | AA35: DWH51214@GMAIL.COM | AB35: 44497 | AC35: =ABS(IF(ISBLANK(AB35),"",TODAY()-AB35)) -> 810 | AD35: YOLANDI | AE35: HOMEPACK BR PROMOTION | AG35: HAPPY
A36: AFRI BUILD | B36: MATATIELE | C36: MATATIELE | D36: EASTERN CAPE | E36: 40 WEST ST | G36: NO | H36: NONE | I36: ACTIVE | J36: 44391 | K36: =ABS(IF(ISBLANK(J36),"",TODAY()-J36)) -> 916 | L36: =J36+14 -> 44405 | M36: CORNICE PREMIX | N36: 30DAYS | O36: NO | Q36: =ABS(IF(ISBLANK(P36),"",TODAY()-P36)) -> #VALUE! | R36: Y | S36: C/M | T36: Jolene | U36: 039 737 3163 | V36: GERHARD | Y36: 44489 | AA36: SALES@AFRIBUILD.CO.ZA | AB36: 44497 | AC36: =ABS(IF(ISBLANK(AB36),"",TODAY()-AB36)) -> 810 | AD36: YOLANDI | AE36: HOMEPACK BR PROMOTION | AG36: HAPPY
A37: AFRICAN HARDWARE BERLIN | B37: BERLIN | C37: BERLIN | D37: EASTERN CAPE | E37: 1800 LEGION STREET, BERLIN, EAST LONDON, EASTERN CAPE | G37: NO | H37: POWER BUILD | I37: INACTIVE | J37: 44387 | K37: =ABS(IF(ISBLANK(J37),"",TODAY()-J37)) -> 920 | L37: =J37+14 -> 44401 | M37: CORNICE | N37: N/A | O37: NO | P37: 44084 | Q37: =ABS(IF(ISBLANK(P37),"",TODAY()-P37)) -> 1223 | R37: N | T37: MEHDI HASSAN | U37: 081 387 6993/043 685 2019 | V37: HEYNS | Y37: 44489 | AA37: MEHDIHASSAN136@GMAIL.COM | AB37: 44480 | AC37: =ABS(IF(ISBLANK(AB37),"",TODAY()-AB37)) -> 827 | AD37: YOLANDI | AE37: POWER BUILD BR PROMOTION
A38: HONEST ELECTRICAL AND PLUMBING PTY LTD | B38: MALAMULELE | C38: MALAMULELE | D38: POLOKWANE | E38: R81 MALAMULELE | G38: NO | H38: NONE | I38: ACTIVE | J38: 44551 | K38: =ABS(IF(ISBLANK(J38),"",TODAY()-J38)) -> 756 | L38: =J38+14 -> 44565 | M38: CORNICE | N38: 30DAYS | O38: NO | P38: 44064 | Q38: =ABS(IF(ISBLANK(P38),"",TODAY()-P38)) -> 1243 | R38: N | T38: HONEST | U38: 0747912495 | V38: TYRONE | W38: BUING FROM MR BUILD, NEEDS PRICING FOR B24 & B22, & DADO FLOWER SOFT | X38: 44434 | Y38: 55 | AA38: HONESTFACTORYPRISE@GMAIL.COM | AB38: 44497 | AC38: =ABS(IF(ISBLANK(AB38),"",TODAY()-AB38)) -> 810 | AD38: YOLANDI | AE38: HOMEPACK BR PROMOTION
A39: SI HARDWARE | B39: THOHOYANDOU | C39: THOHOYANDOU | D39: LIMPOPO | E39: 2010 GARDEN STREET | G39: NO | H39: NONE | I39: ACTIVE | J39: 44550 | K39: =ABS(IF(ISBLANK(J39),"",TODAY()-J39)) -> 757 | L39: =J39+14 -> 44564 | M39: CORNICE | N39: 30DAYS | O39: NO | P39: 44400 | Q39: =ABS(IF(ISBLANK(P39),"",TODAY()-P39)) -> 907 | R39: Y | T39: NAEEM | U39: 0155900497 | V39: TYRONE | W39: WAITED FOR HES ORDER BUT GOT IT | X39: 44433 | Y39: 56 | AA39: ORDERS@SIHARDWARE.CO.ZA | AB39: 44497 | AC39: =ABS(IF(ISBLANK(AB39),"",TODAY()-AB39)) -> 810 | AD39: YOLANDI | AE39: HOMEPACK BR PROMOTION
A40: MIDRAND HYPER HARDWARE (PTY) LTD | B40: MIDRAND | C40: JOHANNESBURG | D40: GAUTENG | E40: 89 DALE RD, GLEN AUSTIN AH | G40: NO | H40: EST | I40: ACTIVE | J40: 44588 | K40: =ABS(IF(ISBLANK(J40),"",TODAY()-J40)) -> 719 | L40: =J40+14 -> 44602 | M40: PREMIX | N40: 30DAYS | O40: NO | P40: 44306 | Q40: =ABS(IF(ISBLANK(P40),"",TODAY()-P40)) -> 1001 | R40: N | T40: SALMAN | U40: 0114864000 | V40: REINHARDT | W40: WAITING FOR STANDS | X40: 44383 | Y40: 106 | AA40: SBV@SBVGROUP.CO.ZA | AB40: 44497 | AC40: =ABS(IF(ISBLANK(AB40),"",TODAY()-AB40)) -> 810 | AD40: YOLANDI | AE40: HOMEPACK BR PROMOTION
A41: AGRA HARDAP BRANCH 143 | B41: MARIENTAL | C41: NAMIBIA | D41: NAMIBIA | E41: PLOT NARIS 111 MARIENTAL NAMIBIA | G41: NO | H41: EST | I41: NEW | J41: 44379 | K41: =ABS(IF(ISBLANK(J41),"",TODAY()-J41)) -> 928 | L41: =J41+14 -> 44393 | M41: CORNICE | N41: N/A | O41: NO | Q41: =ABS(IF(ISBLANK(P41),"",TODAY()-P41)) -> #VALUE! | R41: N | T41: GRAEME SCHAEFER | U41: +063 241 501 | AA41: GRAEME@AGRA.COM.NA | AB41: 44497 | AC41: =ABS(IF(ISBLANK(AB41),"",TODAY()-AB41)) -> 810 | AD41: YOLANDI | AE41: HOMEPACK BR PROMOTION
A42: PETRONELLA HARDWARE | B42: GROOTVLEI | C42: PRETORIA | D42: GAUTENG | E42: 319 OLD WARMBATHS ROAD GROOTVLEI, PETRONELLA, 012 | G42: NO | H42: NONE | I42: INACTIVE | J42: 44466 | K42: =ABS(IF(ISBLANK(J42),"",TODAY()-J42)) -> 841 | L42: =J42+14 -> 44480 | M42: CORNICE | N42: N/A | O42: NO | P42: 44438 | Q42: =ABS(IF(ISBLANK(P42),"",TODAY()-P42)) -> 869 | R42: Y | S42: C/M | U42: 125450411 | V42: TYRONE | W42: CORNICE NOT A BIG MOVER | Y42: 44489 | AA42: PETRONELLAHARDWARE@GMAIL.COM | AB42: 44497 | AC42: =ABS(IF(ISBLANK(AB42),"",TODAY()-AB42)) -> 810 | AD42: YOLANDI | AE42: HOMEPACK BR PROMOTION | AF42: CORNICE NOT MOVER
A43: AGRA HYPER BRANCH 114 | B43: LAFRENZ | C43: WINDHOEK | D43: NAMIBIA | E43: 232 INDUSTRIAL LAFRENZ INDUSTRIAL AREA WINDHOEK | G43: NO | H43: EST | I43: NEW | J43: 44380 | K43: =ABS(IF(ISBLANK(J43),"",TODAY()-J43)) -> 927 | L43: =J43+14 -> 44394 | M43: CORNICE | N43: N/A | O43: NO | Q43: =ABS(IF(ISBLANK(P43),"",TODAY()-P43)) -> #VALUE! | R43: N | T43: GRAEME SCHAEFER | U43: +061 290 9605 | AA43: GRAEME@AGRA.COM.NA | AB43: 44497 | AC43: =ABS(IF(ISBLANK(AB43),"",TODAY()-AB43)) -> 810 | AD43: YOLANDI | AE43: HOMEPACK BR PROMOTION
A44: AGRIFEED BOTSWANA | B44: BOTSWANA | C44: BOTSWANA | D44: BOTSWANA | E44: PLOT 1253 HALLESALASSI ROAD OLD INDUSTRIAL GABORONE | G44: NO | H44: EST | I44: NEW | J44: 44377 | K44: =ABS(IF(ISBLANK(J44),"",TODAY()-J44)) -> 930 | L44: =J44+14 -> 44391 | M44: CORNICE | N44: N/A | O44: NO | P44: 44412 | Q44: =ABS(IF(ISBLANK(P44),"",TODAY()-P44)) -> 895 | R44: N | T44: SANCHIN BAROT | U44: +267 397 2348 | AA44: SACHIN_BAROT2000@YAHOO.COM | AB44: 44497 | AC44: =ABS(IF(ISBLANK(AB44),"",TODAY()-AB44)) -> 810 | AD44: YOLANDI | AE44: HOMEPACK BR PROMOTION
A45: WOOD CORNER | B45: POLOKWANE | C45: POLOKWANE | D45: LIMPOPO | E45: BOK STREET | G45: NO | H45: NONE | I45: ACTIVE | J45: 44572 | K45: =ABS(IF(ISBLANK(J45),"",TODAY()-J45)) -> 735 | L45: =J45+14 -> 44586 | M45: CORNICE | N45: COD | O45: NO | Q45: =ABS(IF(ISBLANK(P45),"",TODAY()-P45)) -> #VALUE! | R45: N | T45: MOHAMMED | U45: 0152973144 | V45: TYRONE | W45: WILL PLACE ORDER BEFORE END JANUARY | Y45: 44489 | AA45: WOODCORNER@TELKOMSA.NET | AB45: 44497 | AC45: =ABS(IF(ISBLANK(AB45),"",TODAY()-AB45)) -> 810 | AD45: YOLANDI | AE45: HOMEPACK BR PROMOTION | AF45: ENOUGH STOCK
A46: NJR STEEL PTA WEST | B46: PRETORIA WEST | C46: PRETORIA | D46: GAUTENG | E46: 1668 MALIE ST | G46: NO | H46: NONE | I46: ACTIVE | J46: 44460 | K46: =ABS(IF(ISBLANK(J46),"",TODAY()-J46)) -> 847 | L46: =J46+14 -> 44474 | M46: PREMIX | N46: 30DAYS | O46: NO | Q46: =ABS(IF(ISBLANK(P46),"",TODAY()-P46)) -> #VALUE! | R46: N | U46: 123720760 | V46: GERHARD | W46: BUYER BUSY WILL CALL LATER | X46: 44443 | Y46: 46 | AA46: CNAUDE@NJRSTEEL.CO.ZA | AB46: 44497 | AC46: =ABS(IF(ISBLANK(AB46),"",TODAY()-AB46)) -> 810 | AD46: YOLANDI | AE46: HOMEPACK BR PROMOTION | AF46: FOLLOW UP
A47: Power Build THLABANE | B47: THLABANE | C47: RUSTENBURG | D47: NORTH WEST | E47: 219 BEYERS NAUDE, RUSTENBURG, NORTHWEST, 0299 | G47: NO | H47: POWER BUILD | I47: INACTIVE | J47: 44378 | K47: =ABS(IF(ISBLANK(J47),"",TODAY()-J47)) -> 929 | L47: =J47+14 -> 44392 | M47: CORNICE | N47: N/A | O47: NO | Q47: =ABS(IF(ISBLANK(P47),"",TODAY()-P47)) -> #VALUE! | R47: N | T47: JOHN | U47: 824801380 | V47: HEYNS | Y47: 44489 | AA47: MSIZI@RTINDUSTRIES.CO.ZA | AB47: 44480 | AC47: =ABS(IF(ISBLANK(AB47),"",TODAY()-AB47)) -> 827 | AD47: YOLANDI | AE47: POWER BUILD BR PROMOTION
A48: HDS CUT & EDGE | B48: VAN DER BIJL | C48: VAN DER BIJL | D48: GAUTENG | E48: 8 AHRBECK STR, VAN DER BIJL | G48: NO | H48: CUT & EDGE | I48: INACTIVE | J48: 44421 | K48: =ABS(IF(ISBLANK(J48),"",TODAY()-J48)) -> 886 | L48: =J48+14 -> 44435 | M48: CORNICE | N48: N/A | O48: NO | P48: 44232 | Q48: =ABS(IF(ISBLANK(P48),"",TODAY()-P48)) -> 1075 | R48: N | U48: 016 933 5279 | V48: HEYNS | X48: 44473 | Y48: 16 | Z48: YOLANDI | AA48: SALES@HDSVANDERBIJLPARK.CO.ZA | AB48: 44497 | AC48: =ABS(IF(ISBLANK(AB48),"",TODAY()-AB48)) -> 810 | AD48: YOLANDI | AE48: HOMEPACK BR PROMOTION
A49: DIE HOUT FABRIEK | B49: VAN DER BIJL | C49: VAN DER BIJL | D49: GAUTENG | E49: 3 WEBBER STR | G49: NO | H49: NONE | I49: INACTIVE | J49: 44420 | K49: =ABS(IF(ISBLANK(J49),"",TODAY()-J49)) -> 887 | L49: =J49+14 -> 44434 | M49: CORNICE | N49: N/A | O49: NO | P49: 44148 | Q49: =ABS(IF(ISBLANK(P49),"",TODAY()-P49)) -> 1159 | R49: N | U49: 0169337712 | V49: HEYNS | X49: 44473 | Y49: 16 | Z49: YOLANDI | AA49: DIEHOUTFABRIEK@VODAMAIL.CO.ZA | AB49: 44497 | AC49: =ABS(IF(ISBLANK(AB49),"",TODAY()-AB49)) -> 810 | AD49: YOLANDI | AE49: HOMEPACK BR PROMOTION
A50: RALF SUPPLIES | B50: VAN DER BIJL | C50: VAN DER BIJL | D50: GAUTENG | E50: 10 NORTH ST | G50: NO | H50: NONE | I50: INACTIVE | J50: 44417 | K50: =ABS(IF(ISBLANK(J50),"",TODAY()-J50)) -> 890 | L50: =J50+14 -> 44431 | M50: CORNICE | N50: N/A | O50: NO | P50: 44119 | Q50: =ABS(IF(ISBLANK(P50),"",TODAY()-P50)) -> 1188 | R50: N | U50: 0169324060 | V50: HEYNS | X50: 44473 | Y50: 16 | Z50: YOLANDI | AA50: RALF@ADMIN@LANTIC.NET | AB50: 44497 | AC50: =ABS(IF(ISBLANK(AB50),"",TODAY()-AB50)) -> 810 | AD50: YOLANDI | AE50: HOMEPACK BR PROMOTION
A51: KLIPKOR | B51: VAN DER BIJL | C51: VAN DER BIJL | D51: GAUTENG | E51: EASTMAN STREET | G51: NO | H51: NONE | I51: INACTIVE | J51: 44414 | K51: =ABS(IF(ISBLANK(J51),"",TODAY()-J51)) -> 893 | L51: =J51+14 -> 44428 | M51: CORNICE | N51: N/A | O51: NO | Q51: =ABS(IF(ISBLANK(P51),"",TODAY()-P51)) -> #VALUE! | R51: N | U51: 0169861441 | V51: HEYNS | X51: 44473 | Y51: 16 | Z51: YOLANDI | AA51: KLIPKOR@ABSAMAIL.CO.ZA | AB51: 44497 | AC51: =ABS(IF(ISBLANK(AB51),"",TODAY()-AB51)) -> 810 | AD51: YOLANDI | AE51: HOMEPACK BR PROMOTION
A52: IMPACT | B52: VAN DER BIJL | C52: VAN DER BIJL | D52: GAUTENG | E52: GOLDEN HIGH WAY | G52: NO | H52: NONE | I52: INACTIVE | J52: 44409 | K52: =ABS(IF(ISBLANK(J52),"",TODAY()-J52)) -> 898 | L52: =J52+14 -> 44423 | M52: CORNICE | N52: N/A | O52: NO | Q52: =ABS(IF(ISBLANK(P52),"",TODAY()-P52)) -> #VALUE! | R52: N | U52: 0795007917 | V52: HEYNS | X52: 44473 | Y52: 16 | Z52: YOLANDI | AA52: BUYER@BOLTANDNUT.CO.ZA | AB52: 44497 | AC52: =ABS(IF(ISBLANK(AB52),"",TODAY()-AB52)) -> 810 | AD52: YOLANDI | AE52: HOMEPACK BR PROMOTION
A53: OLYMPIC MICA | B53: VAN DER BIJL | C53: VAN DER BIJL | D53: GAUTENG | E53: 2 PETTER ST | G53: NO | H53: MICA | I53: INACTIVE | J53: 44405 | K53: =ABS(IF(ISBLANK(J53),"",TODAY()-J53)) -> 902 | L53: =J53+14 -> 44419 | M53: CORNICE | N53: N/A | O53: NO | P53: 44400 | Q53: =ABS(IF(ISBLANK(P53),"",TODAY()-P53)) -> 907 | R53: N | U53: 0169819135 | V53: HEYNS | X53: 44473 | Y53: 16 | Z53: YOLANDI | AA53: INFO@OLYMPICMICA.CO.ZA | AB53: 44497 | AC53: =ABS(IF(ISBLANK(AB53),"",TODAY()-AB53)) -> 810 | AD53: YOLANDI | AE53: HOMEPACK BR PROMOTION
A54: CONSTRUCTA | B54: VAN DER BIJL | C54: VAN DER BIJL | D54: GAUTENG | E54: CNR RAUTENBACH,GOLDEN | G54: NO | H54: NONE | I54: INACTIVE | J54: 44404 | K54: =ABS(IF(ISBLANK(J54),"",TODAY()-J54)) -> 903 | L54: =J54+14 -> 44418 | M54: CORNICE | N54: N/A | O54: NO | Q54: =ABS(IF(ISBLANK(P54),"",TODAY()-P54)) -> #VALUE! | R54: N | T54: WEAN | U54: 0161100181 | V54: HEYNS | X54: 44473 | Y54: 16 | Z54: YOLANDI | AA54: WEAN@CONSTRUCTA.COM | AB54: 44497 | AC54: =ABS(IF(ISBLANK(AB54),"",TODAY()-AB54)) -> 810 | AD54: YOLANDI | AE54: HOMEPACK BR PROMOTION
A55: JACKS | B55: VAN DER BIJL | C55: VAN DER BIJL | D55: GAUTENG | E55: 2 PETTER ST | G55: NO | H55: NONE | I55: INACTIVE | J55: 44397 | K55: =ABS(IF(ISBLANK(J55),"",TODAY()-J55)) -> 910 | L55: =J55+14 -> 44411 | M55: CORNICE | N55: N/A | O55: NO | P55: 44147 | Q55: =ABS(IF(ISBLANK(P55),"",TODAY()-P55)) -> 1160 | R55: N | U55: 0169819135 | V55: HEYNS | X55: 44473 | Y55: 16 | Z55: YOLANDI | AA55: INFO@OLYMPICMICA.CO.ZA | AB55: 44497 | AC55: =ABS(IF(ISBLANK(AB55),"",TODAY()-AB55)) -> 810 | AD55: YOLANDI | AE55: HOMEPACK BR PROMOTION
A56: TUGELA | B56: VAN DER BIJL | C56: VAN DER BIJL | D56: GAUTENG | E56: 134 HANS STRYDOM | G56: NO | H56: NONE | I56: INACTIVE | J56: 44393 | K56: =ABS(IF(ISBLANK(J56),"",TODAY()-J56)) -> 914 | L56: =J56+14 -> 44407 | M56: CORNICE | N56: N/A | O56: NO | Q56: =ABS(IF(ISBLANK(P56),"",TODAY()-P56)) -> #VALUE! | R56: N | U56: 0169816900 | V56: HEYNS | X56: 44473 | Y56: 16 | Z56: YOLANDI | AA56: TUGELA.ORDERS@CYBERSERVE.CO.ZA | AB56: 44497 | AC56: =ABS(IF(ISBLANK(AB56),"",TODAY()-AB56)) -> 810 | AD56: YOLANDI | AE56: HOMEPACK BR PROMOTION
A57: 3 STAR HARDWARE BUILDING MATERIAL | B57: RELETO SECTION | C57: SILVERKRANS | D57: NORTH WEST | E57: 1435 RALETO SECTION, SILVERKRANS, NORTH WEST | G57: NO | H57: EST | I57: NEW | J57: 44386 | K57: =ABS(IF(ISBLANK(J57),"",TODAY()-J57)) -> 921 | L57: =J57+14 -> 44400 | M57: CORNICE | N57: N/A | O57: NO | P57: 44354 | Q57: =ABS(IF(ISBLANK(P57),"",TODAY()-P57)) -> 953 | R57: N | T57: M.W. ARSHAD | U57: 074 518 2972 | AA57: ALI.KHATANA07@GMAIL.COM | AB57: 44497 | AC57: =ABS(IF(ISBLANK(AB57),"",TODAY()-AB57)) -> 810 | AD57: YOLANDI | AE57: HOMEPACK BR PROMOTION
A58: SPHINX | B58: VEREENIGING | C58: VEREENIGING | D58: GAUTENG | E58: 68 VOORTREKKER | G58: NO | H58: NONE | I58: INACTIVE | J58: 44387 | K58: =ABS(IF(ISBLANK(J58),"",TODAY()-J58)) -> 920 | L58: =J58+14 -> 44401 | M58: CORNICE | N58: N/A | O58: NO | Q58: =ABS(IF(ISBLANK(P58),"",TODAY()-P58)) -> #VALUE! | R58: N | U58: 0745665555 | V58: HEYNS | X58: 44473 | Y58: 16 | Z58: YOLANDI | AA58: SPINXMANAGEMENTS@GMAIL.COM | AB58: 44497 | AC58: =ABS(IF(ISBLANK(AB58),"",TODAY()-AB58)) -> 810 | AD58: YOLANDI | AE58: HOMEPACK BR PROMOTION
A59: A.A BUILDING MATERIAL LESOTHO | B59: LERIBE | C59: LERIBE | D59: LESOTHO | E59: AIRPORT ROAD LERIBE LESOTHO | G59: NO | H59: EST | I59: NEW | J59: 44387 | K59: =ABS(IF(ISBLANK(J59),"",TODAY()-J59)) -> 920 | L59: =J59+14 -> 44401 | M59: CORNICE | N59: N/A | O59: NO | Q59: =ABS(IF(ISBLANK(P59),"",TODAY()-P59)) -> #VALUE! | R59: N | T59: HASSEN NOORMOHAMED | U59: 266 22400795 | AA59: IRSHU7860@HOTMAIL.COM | AB59: 44497 | AC59: =ABS(IF(ISBLANK(AB59),"",TODAY()-AB59)) -> 810 | AD59: YOLANDI | AE59: HOMEPACK BR PROMOTION
A60: ACTIVE BUILD HARDWARE | B60: OBERHOLZER | C60: CARLTONVILLE | D60: GAUTENG | E60: 44 VAN ZYL STREET, OBERHOLZER, CARLTONVILLE | G60: NO | H60: EST | I60: NEW | J60: 44372 | K60: =ABS(IF(ISBLANK(J60),"",TODAY()-J60)) -> 935 | L60: =J60+14 -> 44386 | M60: CORNICE | N60: N/A | O60: NO | Q60: =ABS(IF(ISBLANK(P60),"",TODAY()-P60)) -> #VALUE! | R60: N | T60: ZAAKIR ESSOOP | U60: 018 788 2275 | AA60: ACTIVEBUILD@GMAIL.COM | AB60: 44497 | AC60: =ABS(IF(ISBLANK(AB60),"",TODAY()-AB60)) -> 810 | AD60: YOLANDI | AE60: HOMEPACK BR PROMOTION
A61: AGRA HARDAP BRANCH 143 | B61: MARIENTAL | C61: NAMIBIA | D61: NAMIBIA | E61: PLOT NARIS 111 MARIENTAL NAMIBIA | G61: NO | H61: EST | I61: NEW | J61: 44379 | K61: =ABS(IF(ISBLANK(J61),"",TODAY()-J61)) -> 928 | L61: =J61+14 -> 44393 | M61: CORNICE | N61: N/A | O61: NO | Q61: =ABS(IF(ISBLANK(P61),"",TODAY()-P61)) -> #VALUE! | R61: N | T61: GRAEME SCHAEFER | U61: +063 241 501 | AA61: GRAEME@AGRA.COM.NA | AB61: 44497 | AC61: =ABS(IF(ISBLANK(AB61),"",TODAY()-AB61)) -> 810 | AD61: YOLANDI | AE61: HOMEPACK BR PROMOTION
A62: PETRONELLA HARDWARE | B62: GROOTVLEI | C62: PRETORIA | D62: GAUTENG | E62: 319 OLD WARMBATHS ROAD GROOTVLEI, PETRONELLA, 012 | G62: NO | H62: NONE | I62: INACTIVE | J62: 44466 | K62: =ABS(IF(ISBLANK(J62),"",TODAY()-J62)) -> 841 | L62: =J62+14 -> 44480 | M62: CORNICE | N62: N/A | O62: NO | Q62: =ABS(IF(ISBLANK(P62),"",TODAY()-P62)) -> #VALUE! | R62: Y | S62: C/M | U62: 125450411 | V62: TYRONE | W62: CORNICE NOT A BIG MOVER | Y62: 44489 | AA62: PETRONELLAHARDWARE@GMAIL.COM | AB62: 44497 | AC62: =ABS(IF(ISBLANK(AB62),"",TODAY()-AB62)) -> 810 | AD62: YOLANDI | AE62: HOMEPACK BR PROMOTION | AF62: CORNICE NOT MOVER
A63: AGRA HYPER BRANCH 114 | B63: LAFRENZ | C63: WINDHOEK | D63: NAMIBIA | E63: 232 INDUSTRIAL LAFRENZ INDUSTRIAL AREA WINDHOEK | G63: NO | H63: EST | I63: NEW | J63: 44380 | K63: =ABS(IF(ISBLANK(J63),"",TODAY()-J63)) -> 927 | L63: =J63+14 -> 44394 | M63: CORNICE | N63: N/A | O63: NO | Q63: =ABS(IF(ISBLANK(P63),"",TODAY()-P63)) -> #VALUE! | R63: N | T63: GRAEME SCHAEFER | U63: +061 290 9605 | AA63: GRAEME@AGRA.COM.NA | AB63: 44497 | AC63: =ABS(IF(ISBLANK(AB63),"",TODAY()-AB63)) -> 810 | AD63: YOLANDI | AE63: HOMEPACK BR PROMOTION
A64: RANJHA TRADERS HARDWARE & DIY STORE | B64: AKASIA | C64: PRETORIA | D64: GAUTENG | E64: C/O DOREEN & GARDEN ROAD ORCHARDS | G64: NO | H64: NONE | I64: INACTIVE | J64: 44603 | K64: =ABS(IF(ISBLANK(J64),"",TODAY()-J64)) -> 704 | L64: =J64+14 -> 44617 | M64: CORNICE PREMIX | N64: 30DAYS | O64: NO | Q64: =ABS(IF(ISBLANK(P64),"",TODAY()-P64)) -> #VALUE! | R64: N | T64: ZAMID | U64: 0848588455 | V64: TYRONE | W64: ORDERED | X64: 44439 | Y64: 50 | AA64: RANJHATRADERS.SA@GMAIL.COM | AB64: 44497 | AC64: =ABS(IF(ISBLANK(AB64),"",TODAY()-AB64)) -> 810 | AD64: YOLANDI | AE64: HOMEPACK BR PROMOTION | AF64: ENOUGH STOCK
A65: SINOVILLE FENCING | B65: AKASIA | C65: PRETORIA | D65: GAUTENG | E65: 81 WILLEM CRUYWAGEN | G65: NO | H65: NONE | I65: ACTIVE | J65: 44550 | K65: =ABS(IF(ISBLANK(J65),"",TODAY()-J65)) -> 757 | L65: =J65+14 -> 44564 | M65: PREMIX | N65: 30DAYS | O65: NO | Q65: =ABS(IF(ISBLANK(P65),"",TODAY()-P65)) -> #VALUE! | R65: N | T65: JOHAN | U65: 0861336237 | V65: GERHARD | W65: JOHAN NOT IN | X65: 44425 | Y65: 64 | AA65: JOHANG@SINOVILLEFENCING.CO.ZA | AB65: 44497 | AC65: =ABS(IF(ISBLANK(AB65),"",TODAY()-AB65)) -> 810 | AD65: YOLANDI | AE65: HOMEPACK BR PROMOTION | AF65: ORDER PLACED
A66: TIMBERCITY ALLDAYS | B66: ALLDAYS | C66: ALLDAYS | D66: LIMPOPO | E66: MAIN ROAD | G66: YES | H66: NONE | I66: ACTIVE | J66: 44386 | K66: =ABS(IF(ISBLANK(J66),"",TODAY()-J66)) -> 921 | L66: =J66+14 -> 44400 | M66: CORNICE PREMIX | N66: 30DAYS | O66: N | Q66: =ABS(IF(ISBLANK(P66),"",TODAY()-P66)) -> #VALUE! | R66: Y | U66: 0820441200 | Y66: 44489 | AA66: BUYER@JURIHARDWARE.CO.ZA | AB66: 44497 | AC66: =ABS(IF(ISBLANK(AB66),"",TODAY()-AB66)) -> 810 | AD66: YOLANDI | AE66: HOMEPACK BR PROMOTION
A67: UNIVERSAL PAINTS SILVER LAKES | B67: SILVERLAKES | C67: PRETORIA | D67: GAUTENG | E67: 5 GRAHAM ROAD, SILVER LAKES | G67: NO | H67: NONE | I67: INACTIVE | J67: 44459 | K67: =ABS(IF(ISBLANK(J67),"",TODAY()-J67)) -> 848 | L67: =J67+14 -> 44473 | M67: CORNICE | N67: COD | O67: NO | Q67: =ABS(IF(ISBLANK(P67),"",TODAY()-P67)) -> #VALUE! | R67: N | T67: HERBIE | U67: 0832698801 | V67: GERHARD | X67: 44431 | Y67: 58 | AA67: UNIVERSALSL@MWEB.CO.ZA | AB67: 44497 | AC67: =ABS(IF(ISBLANK(AB67),"",TODAY()-AB67)) -> 810 | AD67: YOLANDI | AE67: HOMEPACK BR PROMOTION
A68: DIY DEPOT GRASKOP | B68: GRASKOP | C68: GRASKOP | D68: MPUMALANGA | E68: 16 RICHARDSON STREET, GRASKOP | G68: NO | H68: DIY | I68: NEW | J68: 44599 | K68: =ABS(IF(ISBLANK(J68),"",TODAY()-J68)) -> 708 | L68: =J68+14 -> 44613 | M68: CORNICE | N68: N/A | O68: NO | Q68: =ABS(IF(ISBLANK(P68),"",TODAY()-P68)) -> #VALUE! | R68: N | T68: RASHAD | U68: 0621719496 | V68: REINHARDT | W68: ORDER PLACED
A69: UNIVERSAL PAINTS MENLYN | B69: MENLYN | C69: PRETORIA | D69: GAUTENG | E69: GARSFONTEIN DRIVE & LOUIS AVENUE | G69: NO | H69: NONE | I69: INACTIVE | J69: 44455 | K69: =ABS(IF(ISBLANK(J69),"",TODAY()-J69)) -> 852 | L69: =J69+14 -> 44469 | M69: CORNICE | N69: COD | O69: NO | Q69: =ABS(IF(ISBLANK(P69),"",TODAY()-P69)) -> #VALUE! | R69: N | T69: JACQUES | U69: 129412267 | V69: TYRONE | Y69: 44489 | AA69: UNIVERSALSL@MWEB.CO.ZA | AB69: 44497 | AC69: =ABS(IF(ISBLANK(AB69),"",TODAY()-AB69)) -> 810 | AD69: YOLANDI | AE69: HOMEPACK BR PROMOTION
A70: AJ BOLTS & NUTS | B70: BRITS | C70: BRITS | D70: NORTH WEST | E70: 71 RAILWAY STREET, BRITS, 0250 | G70: NO | H70: EST | I70: NEW | J70: 44388 | K70: =ABS(IF(ISBLANK(J70),"",TODAY()-J70)) -> 919 | L70: =J70+14 -> 44402 | M70: CORNICE | N70: N/A | O70: NO | Q70: =ABS(IF(ISBLANK(P70),"",TODAY()-P70)) -> #VALUE! | R70: N | T70: ZELDAMIEN BOSHOFF | U70: 012 252 7300 | AA70: AJBOLTS@MWEB.CO.ZA; ZELDARIEN@GMAIL.COM | AB70: 44497 | AC70: =ABS(IF(ISBLANK(AB70),"",TODAY()-AB70)) -> 810 | AD70: YOLANDI | AE70: HOMEPACK BR PROMOTION
A71: SAZAR TILE AND HARDWARE | B71: BRONKHORSTSPRUIT | C71: BRONKHORSTSPRUIT | D71: GAUTENG | E71: 3 CHURCH STREET, BRONKHORSTSPRUIT | G71: NO | H71: NONE | I71: ACTIVE | J71: 44452 | K71: =ABS(IF(ISBLANK(J71),"",TODAY()-J71)) -> 855 | L71: =J71+14 -> 44466 | M71: CORNICE | N71: COD | O71: NO | Q71: =ABS(IF(ISBLANK(P71),"",TODAY()-P71)) -> #VALUE! | R71: N | U71: 0139323201 | V71: HEYNS | X71: 44449 | Y71: 40 | AA71: SAZAR@TELKOMSA.NET | AB71: 44497 | AC71: =ABS(IF(ISBLANK(AB71),"",TODAY()-AB71)) -> 810 | AD71: YOLANDI | AE71: HOMEPACK BR PROMOTION
A72: MUNAFS HARDWARE | B72: LAUDIUM | C72: PRETORIA | D72: GAUTENG | E72: 221 2ND DRIVE, LAUDIUM, PRETORIA | G72: NO | H72: FBS | I72: ACTIVE | J72: 44580 | K72: =ABS(IF(ISBLANK(J72),"",TODAY()-J72)) -> 727 | L72: =J72+14 -> 44594 | M72: CORNICE PREMIX | N72: COD | O72: NO | Q72: =ABS(IF(ISBLANK(P72),"",TODAY()-P72)) -> #VALUE! | R72: N | S72: H/P | T72: MUNAF | U72: 0794914786 | V72: GERHARD/ASH | W72: ENOUGH STOCK | X72: 44484 | Y72: 5 | Z72: YOLANDI | AA72: MUNAFSHARDWARE@GMAIL.CO.ZA | AB72: 44497 | AC72: =ABS(IF(ISBLANK(AB72),"",TODAY()-AB72)) -> 810 | AD72: YOLANDI | AE72: HOMEPACK BR PROMOTION | AF72: ORDER PLACED FOR PREMIX | AG72: HAPPY
A73: MUHAMMADS HARDWARE | B73: CENTURION | C73: PRETORIA | D73: GAUTENG | E73: 370 2ND AVE | G73: NO | H73: NONE | I73: INACTIVE | J73: 44550 | K73: =ABS(IF(ISBLANK(J73),"",TODAY()-J73)) -> 757 | L73: =J73+14 -> 44564 | M73: CORNICE PREMIX | N73: 30DAYS | O73: NO | Q73: =ABS(IF(ISBLANK(P73),"",TODAY()-P73)) -> #VALUE! | R73: Y | S73: C/M | T73: MUHAMMAD | U73: 0123743378 | V73: GERHARD | W73: ENOUGH STOCK | X73: 44445 | Y73: 44 | AA73: MUHAMMADSHARDWARE@GMAIL.COM | AB73: 44497 | AC73: =ABS(IF(ISBLANK(AB73),"",TODAY()-AB73)) -> 810 | AD73: YOLANDI | AE73: HOMEPACK BR PROMOTION
A74: MACBUILD | B74: CLUBVIEW | C74: CENTURION | D74: GAUTENG | E74: CNR LYTTELTON & RIVERVIEW ROAD, CLUBVIEW CENTRE, SHOP NO. 5 & 6, CLUBVIEW, CENTURION, 0157 | G74: NO | H74: NONE | I74: NEW | J74: 44589 | K74: =ABS(IF(ISBLANK(J74),"",TODAY()-J74)) -> 718 | L74: =J74+14 -> 44603 | M74: CORNICE | N74: N/A | O74: NO | P74: 44261 | Q74: =ABS(IF(ISBLANK(P74),"",TODAY()-P74)) -> 1046 | R74: N | T74: MOHAMMED | U74: 0126667866 | V74: REINHARDT | W74: GAVE CATALOQUE AND SAMPLES, OWNER WILL LOOK AT IT | X74: 44434 | Y74: 55 | AA74: RASLOUW@MACBUILD.CO.ZA | AB74: 44497 | AC74: =ABS(IF(ISBLANK(AB74),"",TODAY()-AB74)) -> 810 | AD74: YOLANDI | AE74: HOMEPACK BR PROMOTION
A75: BUCO ATHLONE | B75: ATHLONE | C75: ATHLONE | D75: WESTERN CAPE | E75: 57 BELGRAVIA ROAD, ATHLONE, 7764 | H75: BUCO | I75: NEW | J75: 44386 | K75: =ABS(IF(ISBLANK(J75),"",TODAY()-J75)) -> 921 | L75: =J75+14 -> 44400 | M75: CORNICE | N75: N/A | O75: NO | P75: 44350 | Q75: =ABS(IF(ISBLANK(P75),"",TODAY()-P75)) -> 957 | R75: N | T75: ANEESA VAN DER FORT AVANDERFORT@BUCO.CO.ZA 083 381 2597 | X75: 44487 | Y75: 2 | Z75: YOLANDI | AA75: ACCOUNT@GLOBALHARDWARE.CO.ZA | AB75: 44497 | AC75: =ABS(IF(ISBLANK(AB75),"",TODAY()-AB75)) -> 810 | AD75: YOLANDI | AE75: HOMEPACK BR PROMOTION
A76: JACKRITE MICA QUEESWOOD | B76: QUEESWOOD | C76: PRETORIA | D76: GAUTENG | E76: 1175 COBHAM ST | G76: NO | H76: NONE | I76: ACTIVE | J76: 44550 | K76: =ABS(IF(ISBLANK(J76),"",TODAY()-J76)) -> 757 | L76: =J76+14 -> 44564 | M76: PREMIX | N76: 30DAYS | O76: NO | Q76: =ABS(IF(ISBLANK(P76),"",TODAY()-P76)) -> #VALUE! | R76: N | T76: ELSE | U76: 0828314526 | V76: GERHARD | W76: WAITING FOR STOCK | X76: 44428 | Y76: 61 | AA76: LIZE@JACKRITE.CO.ZA | AB76: 44497 | AC76: =ABS(IF(ISBLANK(AB76),"",TODAY()-AB76)) -> 810 | AD76: YOLANDI | AE76: HOMEPACK BR PROMOTION
A77: LIGHTHOUSE MICA HARDWARE | B77: POLOKWANE | C77: POLOKWANE | D77: LIMPOPO | E77: 16 JORISSEN STREET, POLOKWANE, 0700 | G77: NO | H77: NONE | I77: ACTIVE | J77: 44601 | K77: =ABS(IF(ISBLANK(J77),"",TODAY()-J77)) -> 706 | L77: =J77+14 -> 44615 | M77: CORNICE | N77: COD | O77: NO | Q77: =ABS(IF(ISBLANK(P77),"",TODAY()-P77)) -> #VALUE! | R77: N | S77: CORNICE | T77: ROWAAN HOETS | U77: 0152959901 | V77: TYRONE | W77: WILL PLACE NEW ORDER NEXT WEEK | X77: 44428 | Y77: 61 | AA77: MICAORDERS@NADAIR.CO.ZA | AB77: 44497 | AC77: =ABS(IF(ISBLANK(AB77),"",TODAY()-AB77)) -> 810 | AD77: YOLANDI | AE77: HOMEPACK BR PROMOTION
A78: DIY NORTHDALE | B78: NORTHDALE | C78: JOHANNESBURG | D78: GAUTENG | E78: SHOP 23, NORTHDALE SHOPPING CENTRE, GRAFENHEIM STREET, NINAPARK | G78: NO | H78: DIY | I78: INACTIVE | J78: 44382 | K78: =ABS(IF(ISBLANK(J78),"",TODAY()-J78)) -> 925 | L78: =J78+14 -> 44396 | M78: PREMIX | O78: NO | Q78: =ABS(IF(ISBLANK(P78),"",TODAY()-P78)) -> #VALUE! | R78: N | T78: WILLEM | U78: 0746194606 | Y78: 44489 | AA78: ACCOUNTS.AKARINA@DIYDEPOT.CO.ZA | AB78: 44497 | AC78: =ABS(IF(ISBLANK(AB78),"",TODAY()-AB78)) -> 810 | AD78: YOLANDI | AE78: HOMEPACK BR PROMOTION
A79: ELITE BUILDING SUPPLIES | B79: ATHLONE | C79: ATHLONE | D79: WESTERN CAPE | E79: 15 CARRICK ROAD | H79: NONE | I79: INACTIVE | J79: 44430 | K79: =ABS(IF(ISBLANK(J79),"",TODAY()-J79)) -> 877 | L79: =J79+14 -> 44444 | M79: CORNICE | N79: 30 DAYS | O79: N | Q79: =ABS(IF(ISBLANK(P79),"",TODAY()-P79)) -> #VALUE! | R79: N | U79: 0216330005
A80: AKSA BUILDERS SUPPLIERS | B80: OVERPORT | C80: OVERPORT | D80: KWAZULU-NATAL | E80: 107 BRICKFIELD RD OVERPORT KWAZULU-NATAL | G80: NO | H80: EST | I80: NEW | J80: 44389 | K80: =ABS(IF(ISBLANK(J80),"",TODAY()-J80)) -> 918 | L80: =J80+14 -> 44403 | M80: CORNICE | N80: N/A | O80: NO | Q80: =ABS(IF(ISBLANK(P80),"",TODAY()-P80)) -> #VALUE! | R80: N | T80: SHABEER | U80: 031 208 6795 | AA80: AKSADBN@YMAIL.COM | AB80: 44497 | AC80: =ABS(IF(ISBLANK(AB80),"",TODAY()-AB80)) -> 810 | AD80: YOLANDI | AE80: HOMEPACK BR PROMOTION
A81: KHAN'S HARDWARE & GENERAL DEALER | B81: LAUDIUM | C81: PRETORIA | D81: GAUTENG | E81: SHOP NR 12, CARIMS ARCADE, TANGERINE STREET, LAUDIUM | G81: NO | H81: NONE | I81: INACTIVE | J81: 44380 | K81: =ABS(IF(ISBLANK(J81),"",TODAY()-J81)) -> 927 | L81: =J81+14 -> 44394 | N81: N/A | O81: NO | Q81: =ABS(IF(ISBLANK(P81),"",TODAY()-P81)) -> #VALUE! | R81: N | T81: KHAN | U81: 0123742996 | Y81: 44489 | AA81: KHANMMOOSA@GMAIL.COM | AB81: 44497 | AC81: =ABS(IF(ISBLANK(AB81),"",TODAY()-AB81)) -> 810 | AD81: YOLANDI | AE81: HOMEPACK BR PROMOTION
A82: DIY THE REEDS | B82: CENTURION | C82: PRETORIA | D82: GAUTENG | E82: SHOP 35A BLU VALLEY MALL, ROOIHUISKRAAL ROAD | G82: NO | H82: DIY | I82: INACTIVE | J82: 44550 | K82: =ABS(IF(ISBLANK(J82),"",TODAY()-J82)) -> 757 | L82: =J82+14 -> 44564 | M82: PREMIX | N82: 30 DAYS | O82: NO | Q82: =ABS(IF(ISBLANK(P82),"",TODAY()-P82)) -> #VALUE! | R82: N | T82: MARIANA HERBST | U82: 0613682495 | V82: GERHARD | W82: CLOSED | Y82: 44489 | AA82: ACCOUNTS.AKARINA@DIYDEPOT.CO.ZA | AB82: 44497 | AC82: =ABS(IF(ISBLANK(AB82),"",TODAY()-AB82)) -> 810 | AD82: YOLANDI | AE82: HOMEPACK BR PROMOTION
A83: DIY LYTTLETON | B83: CENTURION | C83: PRETORIA | D83: GAUTENG | E83: SHOP 24, THE HIGHLANDS SHOPPING CENTRE, LYTTLETON MANOR | G83: NO | H83: DIY | I83: INACTIVE | J83: 44550 | K83: =ABS(IF(ISBLANK(J83),"",TODAY()-J83)) -> 757 | L83: =J83+14 -> 44564 | M83: PREMIX | N83: 30 DAYS | O83: NO | Q83: =ABS(IF(ISBLANK(P83),"",TODAY()-P83)) -> #VALUE! | R83: N | T83: MARIANA HERBST | U83: 0795249135 | V83: GERHARD | W83: CLOSED | Y83: 44489 | AA83: ACCOUNTS.AKARINA@DIYDEPOT.CO.ZA | AB83: 44497 | AC83: =ABS(IF(ISBLANK(AB83),"",TODAY()-AB83)) -> 810 | AD83: YOLANDI | AE83: HOMEPACK BR PROMOTION
A84: RAMODISE SUPERSTORE & WHOLESALES | B84: HAMMANSKRAAL | C84: PRETORIA | D84: GAUTENG | E84: 3675 NEW EERSTERUST BLOCK C | G84: YES | H84: NONE | I84: INACTIVE | J84: 44347 | K84: =ABS(IF(ISBLANK(J84),"",TODAY()-J84)) -> 960 | L84: =J84+14 -> 44361 | M84: CORNICE PREMIX | N84: 30DAYS | O84: NO | Q84: =ABS(IF(ISBLANK(P84),"",TODAY()-P84)) -> #VALUE! | R84: N | T84: ZAHIDIQ | U84: 0826784058 | W84: ZAHID - SEND CATALOQUE AND REP NEEDS TO VISIT. ZAHIDIQ765@GMAIL.COM | X84: 44447 | Y84: 42 | Z84: YOLANDI | AA84: ZAHIDIQ765@GMAIL.COM | AB84: 44497 | AC84: =ABS(IF(ISBLANK(AB84),"",TODAY()-AB84)) -> 810 | AD84: YOLANDI | AE84: HOMEPACK BR PROMOTION
A85: PETIT MICA | B85: BOKSBURG | C85: JOHANNESBURG | D85: GAUTENG | E85: 6B EVA RD | G85: NO | H85: MICA | I85: INACTIVE | J85: 44603 | K85: =ABS(IF(ISBLANK(J85),"",TODAY()-J85)) -> 704 | L85: =J85+14 -> 44617 | M85: PREMIX | N85: 30DAYS | O85: NO | Q85: =ABS(IF(ISBLANK(P85),"",TODAY()-P85)) -> #VALUE! | R85: Y | S85: ELEGANT | T85: HERMAN | U85: 0105913990 | V85: REINHARDT | W85: NEED TO MAKE AN APPOINTMENT | X85: 44367 | Y85: 122 | AA85: HERMAN@PETITMICA.CO.ZA | AB85: 44497 | AC85: =ABS(IF(ISBLANK(AB85),"",TODAY()-AB85)) -> 810 | AD85: YOLANDI | AE85: HOMEPACK BR PROMOTION
A86: SAFRINTA ROOFING NELSPRUIT | B86: NELSPRUIT | C86: NELSPRUIT | D86: MPUMALANGA | E86: 10 WATER LILY STREET | G86: NO | H86: NONE | I86: NEW | J86: 44601 | K86: =ABS(IF(ISBLANK(J86),"",TODAY()-J86)) -> 706 | L86: =J86+14 -> 44615 | M86: CORNICE | N86: N/A | O86: NO | Q86: =ABS(IF(ISBLANK(P86),"",TODAY()-P86)) -> #VALUE! | R86: N | T86: ADRIAN PILLAY | U86: 0113236300 | V86: REINHARDT | W86: NEEDS TO SET UP A MEETING
A87: ALI'S HARDWARE (ADDITIONAL DELIVERY ADDRESS FOR BUILDFAST) | B87: MT AYLIFF | C87: MT AYLIFF | D87: EASTERN CAPE | E87: 6 NTSIZWA STREET, MT AYLIFF, EASTERN CAPE, 4735 | G87: NO | H87: POWER BUILD | I87: INACTIVE | J87: 44375 | K87: =ABS(IF(ISBLANK(J87),"",TODAY()-J87)) -> 932 | L87: =J87+14 -> 44389 | M87: CORNICE | N87: N/A | O87: NO | Q87: =ABS(IF(ISBLANK(P87),"",TODAY()-P87)) -> #VALUE! | R87: N | T87: MONICA | U87: 083 756 3221 | V87: HEYNS | Y87: 44489 | AA87: BUILDFAST902@GMAIL.COM | AB87: 44480 | AC87: =ABS(IF(ISBLANK(AB87),"",TODAY()-AB87)) -> 827 | AD87: YOLANDI | AE87: POWER BUILD BR PROMOTION
A88: ALL PAINT & HARDWARE JEFFREY’S BAY (DAJEES ) | B88: JEFFREYS BAY | C88: JEFFREYS BAY | D88: EASTERN CAPE | E88: 11 DA GAMA ROAD JEFFREYS BAY | G88: NO | H88: EST | I88: NEW | J88: 44378 | K88: =ABS(IF(ISBLANK(J88),"",TODAY()-J88)) -> 929 | L88: =J88+14 -> 44392 | M88: CORNICE | N88: N/A | O88: NO | Q88: =ABS(IF(ISBLANK(P88),"",TODAY()-P88)) -> #VALUE! | R88: N | T88: FRANSIE/RONEL | U88: 041 995 8331 | AA88: ALLPAINTHARDWARE@GMAIL.COM;ACCOUNTS@DAJEES.CO.ZA | AB88: 44497 | AC88: =ABS(IF(ISBLANK(AB88),"",TODAY()-AB88)) -> 810 | AD88: YOLANDI | AE88: HOMEPACK BR PROMOTION
A89: ALLIED BUILD (ADDITIONAL DELIVERY ADDRESS FOR INDALI) | B89: MTHATHA | C89: MTHATA | D89: EASTERN CAPE | E89: 15 ERROL SPRING AVENUE, VULINDLELA HEIGHTS, MTHATHA, 5099 | G89: NO | H89: POWER BUILD | I89: INACTIVE | J89: 44395 | K89: =ABS(IF(ISBLANK(J89),"",TODAY()-J89)) -> 912 | L89: =J89+14 -> 44409 | M89: CORNICE | N89: N/A | O89: NO | Q89: =ABS(IF(ISBLANK(P89),"",TODAY()-P89)) -> #VALUE! | R89: N | T89: ANSAR SADIQ CHEEMA | U89: 083 289 0744 | V89: HEYNS | Y89: 44489 | AA89: INDALI.CHEEMA@GMAIL.COM | AB89: 44480 | AC89: =ABS(IF(ISBLANK(AB89),"",TODAY()-AB89)) -> 827 | AD89: YOLANDI | AE89: POWER BUILD BR PROMOTION
A90: STEEL & PIPES CENTURION | B90: CENTURION | C90: PRETORIA | D90: GAUTENG | E90: 143 SAREL BAARD CRES,ROOIHUISKRAAL | G90: NO | H90: NONE | I90: INACTIVE | J90: 44346 | K90: =ABS(IF(ISBLANK(J90),"",TODAY()-J90)) -> 961 | L90: =J90+14 -> 44360 | M90: PREMIX | N90: 30DAYS | O90: NO | Q90: =ABS(IF(ISBLANK(P90),"",TODAY()-P90)) -> #VALUE! | R90: N | T90: STEVE | U90: 0126550580 | V90: HEYNS | X90: 44395 | Y90: 94 | AA90: STEVE@SPAWEST.CO.ZA | AB90: 44497 | AC90: =ABS(IF(ISBLANK(AB90),"",TODAY()-AB90)) -> 810 | AD90: YOLANDI | AE90: HOMEPACK BR PROMOTION
A91: ALLIED BUILDERS CLAYVILLE | B91: CLAYVILLE | C91: PRETORIA | D91: GAUTENG | E91: CNR OLIFANTSFONTEIN & SOUTHWARD R, CLAYVILLE, TEMBISA, MIDRAND | G91: YES | H91: EST | I91: ACTIVE | J91: 44580 | K91: =ABS(IF(ISBLANK(J91),"",TODAY()-J91)) -> 727 | L91: =J91+14 -> 44594 | M91: CORNICE | N91: 30 DAYS | O91: NO | Q91: =ABS(IF(ISBLANK(P91),"",TODAY()-P91)) -> #VALUE! | R91: N | S91: H/P | T91: SUHAIL | U91: 0714373621 | V91: TYRONE | W91: ORDER PLACED | Y91: 44489 | AA91: m.omarjee@alliedbuildex.co.za | AB91: 44497 | AC91: =ABS(IF(ISBLANK(AB91),"",TODAY()-AB91)) -> 810 | AD91: YOLANDI | AE91: HOMEPACK BR PROMOTION
A92: HAMMERKOP HARDWARE | B92: RIETFONTEIN | C92: PRETORIA | D92: GAUTENG | E92: HERTZOG STREET | G92: NO | H92: NONE | I92: ACTIVE | J92: 44346 | K92: =ABS(IF(ISBLANK(J92),"",TODAY()-J92)) -> 961 | L92: =J92+14 -> 44360 | M92: CORNICE | N92: COD | O92: NO | Q92: =ABS(IF(ISBLANK(P92),"",TODAY()-P92)) -> #VALUE! | R92: N | X92: 44368 | Y92: 121 | AA92: HAMMERKOP901@GMAIL.COM | AB92: 44497 | AC92: =ABS(IF(ISBLANK(AB92),"",TODAY()-AB92)) -> 810 | AD92: YOLANDI | AE92: HOMEPACK BR PROMOTION
A93: BUILD IT NELSPRUIT | B93: NELSPRUIT | C93: NELSPRUIT | D93: MPUMALANGA | E93: NELSPRUIT | G93: NO | H93: NONE | I93: NEW | J93: 44601 | K93: =ABS(IF(ISBLANK(J93),"",TODAY()-J93)) -> 706 | L93: =J93+14 -> 44615 | M93: CORNICE | N93: N/A | O93: NO | Q93: =ABS(IF(ISBLANK(P93),"",TODAY()-P93)) -> #VALUE! | R93: N | T93: SHANE | V93: REINHARDT | W93: HO IN PINETOWN
A94: JADA'S HARDWARE MIDWAY | B94: SOWETO | C94: JOHANNESBURG | D94: GAUTENG | E94: 11 GATEWAY ST | G94: NO | H94: EST | I94: INACTIVE | J94: 44346 | K94: =ABS(IF(ISBLANK(J94),"",TODAY()-J94)) -> 961 | L94: =J94+14 -> 44360 | M94: PREMIX | N94: 30DAYS | O94: NO | P94: 44261 | Q94: =ABS(IF(ISBLANK(P94),"",TODAY()-P94)) -> 1046 | R94: N | T94: JADA MOOSA | U94: 0119800035 | W94: ON ORDER SCHEDULE AS STATED PREVIOUS | X94: 44428 | Y94: 61 | AA94: JADAMOOSA@GMAIL.COM | AB94: 44497 | AC94: =ABS(IF(ISBLANK(AB94),"",TODAY()-AB94)) -> 810 | AD94: YOLANDI | AE94: HOMEPACK BR PROMOTION
A95: ALLIED BUILDERS HAMMANSKRAAL | B95: HAMMANSKRAAL | C95: PRETORIA | D95: GAUTENG | E95: DOUGLAS RENS RD | G95: YES | H95: EST | I95: ACTIVE | J95: 44595 | K95: =ABS(IF(ISBLANK(J95),"",TODAY()-J95)) -> 712 | L95: =J95+14 -> 44609 | M95: CORNICE | N95: 30DAYS | O95: NO | P95: 44158 | Q95: =ABS(IF(ISBLANK(P95),"",TODAY()-P95)) -> 1149 | R95: Y | S95: CORNICE | T95: SUHAIL | U95: #N/A | V95: TYRONE | W95: ORDER PLACED | Y95: 44489 | AA95: m.omarjee@alliedbuildex.co.za | AB95: 44497 | AC95: =ABS(IF(ISBLANK(AB95),"",TODAY()-AB95)) -> 810 | AD95: YOLANDI | AE95: HOMEPACK BR PROMOTION
A96: HUMPHRIES &JEWELL | B96: PRETORIA WEST | C96: PRETORIA | D96: GAUTENG | E96: SOUTTER ST | G96: NO | H96: NONE | I96: INACTIVE | J96: 44603 | K96: =ABS(IF(ISBLANK(J96),"",TODAY()-J96)) -> 704 | L96: =J96+14 -> 44617 | M96: CORNICE PREMIX | N96: 30DAYS | O96: NO | Q96: =ABS(IF(ISBLANK(P96),"",TODAY()-P96)) -> #VALUE! | R96: Y | S96: C/M | T96: BARRY | U96: 0123270673 | V96: REINHARDT | W96: BUYERS NOT IN | X96: 44429 | Y96: 60 | AA96: SALES@HJ.CO.ZA | AB96: 44497 | AC96: =ABS(IF(ISBLANK(AB96),"",TODAY()-AB96)) -> 810 | AD96: YOLANDI | AE96: HOMEPACK BR PROMOTION
A97: NJR STEEL PTA EAST | B97: PRETORIA EAST | C97: PRETORIA | D97: GAUTENG | E97: 184 VONKPROP ST | G97: NO | H97: NONE | I97: INACTIVE | J97: 44461 | K97: =ABS(IF(ISBLANK(J97),"",TODAY()-J97)) -> 846 | L97: =J97+14 -> 44475 | M97: PREMIX | N97: 30DAYS | O97: NO | Q97: =ABS(IF(ISBLANK(P97),"",TODAY()-P97)) -> #VALUE! | R97: N | T97: MELISSA | U97: 0128037162 | V97: GERHARD | W97: WANTS BETER PRICE AND SERVICE | X97: 44386 | Y97: 103 | AA97: BVANHEERDEN@NJRSTEEL.CO.ZA | AB97: 44497 | AC97: =ABS(IF(ISBLANK(AB97),"",TODAY()-AB97)) -> 810 | AD97: YOLANDI | AE97: HOMEPACK BR PROMOTION | AG97: HAPPY
A98: ALLIED BUILDERS HAMMANSKRAAL | B98: HAMMANSKRAAL | C98: HAMMANSKRAAL | D98: GAUTENG | E98: SHOP 7A, HAMMANSKRAAL SHOPPING CENTRE, HAMMANSKRAAL, GAUTENG | G98: NO | H98: EST | I98: NEW | J98: 44393 | K98: =ABS(IF(ISBLANK(J98),"",TODAY()-J98)) -> 914 | L98: =J98+14 -> 44407 | M98: CORNICE | N98: N/A | O98: NO | Q98: =ABS(IF(ISBLANK(P98),"",TODAY()-P98)) -> #VALUE! | R98: N | T98: SUHAIL ENGAR | U98: 012 942 8862 | AA98: S.ENGAR@ALLIEDBUILDEX.CO.ZA | AB98: 44497 | AC98: =ABS(IF(ISBLANK(AB98),"",TODAY()-AB98)) -> 810 | AD98: YOLANDI | AE98: HOMEPACK BR PROMOTION
A99: ALPHA BUILD HARDWARE | B99: MTATHA | C99: MTATHA | D99: EASTERN CAPE | E99: NO 7 SPRIGG STREET, MTATHA, EC, 5099 | G99: NO | H99: EST | I99: NEW | J99: 44396 | K99: =ABS(IF(ISBLANK(J99),"",TODAY()-J99)) -> 911 | L99: =J99+14 -> 44410 | M99: CORNICE | N99: N/A | O99: NO | Q99: =ABS(IF(ISBLANK(P99),"",TODAY()-P99)) -> #VALUE! | R99: N | T99: NASEERA BASHIR | U99: 047 531 0179 | AA99: ALPHABUILDHARDWARE@GMAIL.COM | AB99: 44497 | AC99: =ABS(IF(ISBLANK(AB99),"",TODAY()-AB99)) -> 810 | AD99: YOLANDI | AE99: HOMEPACK BR PROMOTION
A100: WESLOU FLOOR COVERINGS | B100: MODIMOLE | C100: MODIMOLE | D100: LIMPOPO | E100: 49 JOE SLOVO STREET, NYLSTROOM | G100: NO | H100: NONE | I100: INACTIVE | J100: 44460 | K100: =ABS(IF(ISBLANK(J100),"",TODAY()-J100)) -> 847 | L100: =J100+14 -> 44474 | M100: GRASS | N100: N/A | O100: NO | Q100: =ABS(IF(ISBLANK(P100),"",TODAY()-P100)) -> #VALUE! | R100: N | T100: LINKY | U100: 0762748653 | V100: TYRONE | W100: REQUESTED QUOTE | Y100: 44489 | AA100: ADMIN@WESLOUFLOORCOVERINGSS.CO.ZA | AB100: 44497 | AC100: =ABS(IF(ISBLANK(AB100),"",TODAY()-AB100)) -> 810 | AD100: YOLANDI | AE100: HOMEPACK BR PROMOTION | AF100: QUOTE SEND
...

Sheet Complete sheet
A1: STORE NAME | B1: AREA | C1: CITY | D1: PROVINCE | E1: STREET ADDRESS | F1: WHOLESALER | G1: GROUP | H1: ACTIVE/INACTIVE | I1: DATE VISITED | J1: Days since last visted | K1: NEXT VISIT DATE | L1: Product | M1: TYPE OF CLIENT | N1: CREDIT APP | O1: Last invoice sent date | P1: Days from last order | Q1: Cornice Maker | R1: CURRENT SUPPLIER | S1: CUSTOMER NAME | T1: CUSTOMER NUMBER | U1: REP NAME | V1: CUSTOMER COMMENTS | W1: LAST PHONED DATE | X1: DAYS FROM LAST CALL | Y1: PHONED BY | Z1: EMAIL | AA1: LAST MAILED | AB1: DAYS FROM LAST MAIL | AC1: MAILED BY | AD1: WHAT WAS MAILED | AE1: CLIENT FEEDBACK | AF1: HAPPY/ANGRY | AG1: LAST MAIL DATE
A2: More Plus Paints | B2: Bloemfontein | C2: Bloemfontein | D2: Free State | E2: 3 Oranje Street Hilton Bloemfontein | G2: EST | L2: HARDWARE | S2: Johanna | T2: 051 447 5050 | Z2: megapaints@live.co.ca;boodskapvirjou@hotmail.com
A3: =UPPER('route plans'!A1419) -> 2 ACRE HARDWARE / FOX BOUERS | B3: =UPPER('route plans'!B1419) -> PIKETBERG | C3: =UPPER('route plans'!C1419) -> PIKETBERG | D3: =UPPER('route plans'!D1419) -> WESTERN CAPE | E3: =UPPER('route plans'!E1419) -> 53 LANE STREET PIKETBERG 7320 | F3: =UPPER('route plans'!G1419) -> NO | G3: =UPPER('route plans'!H1419) -> EST | L3: HARDWARE | M3: =UPPER('route plans'!N1419) -> N/A | N3: =UPPER('route plans'!O1419) -> NO | S3: =UPPER('route plans'!T1419) -> CARLO HENDRIKS | T3: ='route plans'!U1419 -> 022 91 33940 | W3: ='route plans'!X1419 -> 0 | X3: ='route plans'!Y1419 -> 0 | Y3: =UPPER('route plans'!Z1419) | Z3: =UPPER('route plans'!AA1419) -> FLOUW@TAGRI.CO.ZA | AB3: ='route plans'!AC1419 -> #VALUE!
A4: =UPPER('route plans'!A23) -> 3 STAR HARDWARE BUILDING MATERIAL | B4: =UPPER('route plans'!B23) -> RELETO SECTION | C4: =UPPER('route plans'!C23) -> SILVERKRANS | D4: =UPPER('route plans'!D23) -> NORTH WEST | E4: =UPPER('route plans'!E23) -> 1435 RALETO SECTION, SILVERKRANS, NORTH WEST | F4: =UPPER('route plans'!G23) -> NO | G4: =UPPER('route plans'!H23) -> EST | L4: HARDWARE | M4: =UPPER('route plans'!N23) -> N/A | N4: =UPPER('route plans'!O23) -> NO | S4: =UPPER('route plans'!T23) -> M.W. ARSHAD | T4: ='route plans'!U23 -> 074 518 2972 | W4: ='route plans'!X23 -> 0 | X4: ='route plans'!Y23 -> 0 | Y4: =UPPER('route plans'!Z23) | Z4: =UPPER('route plans'!AA23) -> ALI.KHATANA07@GMAIL.COM | AB4: ='route plans'!AC23 -> 810
A5: =UPPER('route plans'!A57) -> 3 STAR HARDWARE BUILDING MATERIAL | B5: =UPPER('route plans'!B57) -> RELETO SECTION | C5: =UPPER('route plans'!C57) -> SILVERKRANS | D5: =UPPER('route plans'!D57) -> NORTH WEST | E5: =UPPER('route plans'!E57) -> 1435 RALETO SECTION, SILVERKRANS, NORTH WEST | F5: =UPPER('route plans'!G57) -> NO | G5: =UPPER('route plans'!H57) -> EST | L5: HARDWARE | M5: =UPPER('route plans'!N57) -> N/A | N5: =UPPER('route plans'!O57) -> NO | S5: =UPPER('route plans'!T57) -> M.W. ARSHAD | T5: ='route plans'!U57 -> 074 518 2972 | W5: ='route plans'!X57 -> 0 | X5: ='route plans'!Y57 -> 0 | Y5: =UPPER('route plans'!Z57) | Z5: =UPPER('route plans'!AA57) -> ALI.KHATANA07@GMAIL.COM | AB5: ='route plans'!AC57 -> 810
A6: =UPPER('route plans'!A535) -> 31 HARDWARE (PTY) LTD | B6: =UPPER('route plans'!B535) -> GEORGE | C6: =UPPER('route plans'!C535) -> GEORGE | D6: =UPPER('route plans'!D535) -> WESTERN CAPE | E6: =UPPER('route plans'!E535) -> DENNE OORD GEORGE 6529 | F6: =UPPER('route plans'!G535) -> NO | G6: =UPPER('route plans'!H535) -> EST | L6: HARDWARE | M6: =UPPER('route plans'!N535) -> N/A | N6: =UPPER('route plans'!O535) -> NO | S6: =UPPER('route plans'!T535) -> ELIZMA JOUBERT | T6: ='route plans'!U535 -> 044 050 3700 | W6: ='route plans'!X535 -> 0 | X6: ='route plans'!Y535 -> 0 | Y6: =UPPER('route plans'!Z535) | Z6: =UPPER('route plans'!AA535) | AB6: ='route plans'!AC535 -> #VALUE!
A7: =UPPER('route plans'!A732) -> 786 DIRECTION | B7: =UPPER('route plans'!B732) -> PALAPYE | C7: =UPPER('route plans'!C732) -> PALAPYE | D7: =UPPER('route plans'!D732) -> BOTSWANA | E7: =UPPER('route plans'!E732) -> BOPEDI WARD RAMOKGUNAMI VILLAGE CENTRAL DISTRICT BOTSWANA | F7: =UPPER('route plans'!G732) -> NO | G7: =UPPER('route plans'!H732) -> EST | L7: HARDWARE | M7: =UPPER('route plans'!N732) -> N/A | N7: =UPPER('route plans'!O732) -> NO | S7: =UPPER('route plans'!T732) -> FAROUK | T7: ='route plans'!U732 -> (267) 4922560 | W7: ='route plans'!X732 -> 0 | X7: ='route plans'!Y732 -> 0 | Y7: =UPPER('route plans'!Z732) | Z7: =UPPER('route plans'!AA732) -> TAWAQAL_INVESTMENT@YAHOO.COM;KHALIDPATEL37@YAHOO.COM | AB7: ='route plans'!AC732 -> #VALUE!
A8: =UPPER('route plans'!A2214) -> A H MARAIS SEUNS (EDMS) BPK | B8: =UPPER('route plans'!B2214) -> WORCESTER | C8: =UPPER('route plans'!C2214) -> WORCESTER | D8: =UPPER('route plans'!D2214) -> WESTERN CAPE | E8: =UPPER('route plans'!E2214) -> 12 FIELD ST | F8: =UPPER('route plans'!G2214) -> NO | G8: =UPPER('route plans'!H2214) -> NONE | L8: HARDWARE | M8: =UPPER('route plans'!N2214) -> 30DAYS | N8: =UPPER('route plans'!O2214) -> NO | S8: =UPPER('route plans'!T2214) -> JANNIE | T8: ='route plans'!U2214 -> 0236263071 | W8: ='route plans'!X2214 -> 0 | X8: ='route plans'!Y2214 -> 0 | Y8: =UPPER('route plans'!Z2214) | Z8: =UPPER('route plans'!AA2214) -> CTERBLANCHE@TAGRI.CO.ZA | AB8: ='route plans'!AC2214 -> 823
A9: =UPPER('route plans'!A711) -> A HARDWARE ZANDSPRUIT | B9: =UPPER('route plans'!B711) -> ZANDSPRUIT | C9: =UPPER('route plans'!C711) -> ROODEPOORT | D9: =UPPER('route plans'!D711) -> GAUTENG | E9: =UPPER('route plans'!E711) -> 187 MARINA ROAD ZANDSPRUIT ROODEPOORT 2169 | F9: =UPPER('route plans'!G711) -> NO | G9: =UPPER('route plans'!H711) -> EST | L9: HARDWARE | M9: =UPPER('route plans'!N711) -> N/A | N9: =UPPER('route plans'!O711) -> NO | S9: =UPPER('route plans'!T711) -> HAMZA/ZYED/MOHAMED | T9: ='route plans'!U711 -> 011 419 3019 | W9: ='route plans'!X711 -> 0 | X9: ='route plans'!Y711 -> 0 | Y9: =UPPER('route plans'!Z711) | Z9: =UPPER('route plans'!AA711) -> AHARDWAREMOKALE@GMAIL.COM;ADMIN@AHARDWARE.CO.ZA | AB9: ='route plans'!AC711 -> #VALUE!
A10: A Hardware Zandspruit | B10: Roodepoort | C10: Roodepoort | D10: Gauteng | E10: 187 Marina Road Zandspruit Roodepoort 2169 | G10: EST | L10: HARDWARE | S10: Hamza/Zyed/Mohamed | T10: 011 419 3019 | Z10: ahardwaremokale@gmail.com;admin@ahardware.co.za
A11: =UPPER('route plans'!A710) -> A HARDWARE KAGISO | B11: =UPPER('route plans'!B710) -> KAGISO | C11: =UPPER('route plans'!C710) -> KRUGERSDORP | D11: =UPPER('route plans'!D710) -> GAUTENG | E11: =UPPER('route plans'!E710) -> 1997 THEMBA DRIVE KAGISO CENTRAL | F11: =UPPER('route plans'!G710) -> NO | G11: =UPPER('route plans'!H710) -> EST | L11: HARDWARE | M11: =UPPER('route plans'!N710) -> N/A | N11: =UPPER('route plans'!O710) -> NO | S11: =UPPER('route plans'!T710) -> HAMZA/ZYED/MOHAMED | T11: ='route plans'!U710 -> 011 419 3019 | W11: ='route plans'!X710 -> 0 | X11: ='route plans'!Y710 -> 0 | Y11: =UPPER('route plans'!Z710) | Z11: =UPPER('route plans'!AA710) -> AHARDWAREMOKALE@GMAIL.COM;ADMIN@AHARDWARE.CO.ZA | AB11: ='route plans'!AC710 -> #VALUE!
A12: A Hardware Kagiso | B12: Krugersdorp | C12: Krugersdorp | D12: Gauteng | E12: 1997 Themba Drive Kagiso Central | G12: EST | L12: HARDWARE | S12: Hamza/Zyed/Mohamed | T12: 011 419 3019 | Z12: ahardwaremokale@gmail.com;admin@ahardware.co.za
A13: =UPPER('route plans'!A709) -> A HARDWARE MOKALE | B13: =UPPER('route plans'!B709) -> MOKALE | C13: =UPPER('route plans'!C709) -> KRUGERSDORP | D13: =UPPER('route plans'!D709) -> GAUTENG | E13: =UPPER('route plans'!E709) -> 14611 MASEDI STR RIVERSIDE KAGISO KURGERSDORP | F13: =UPPER('route plans'!G709) -> NO | G13: =UPPER('route plans'!H709) -> EST | L13: HARDWARE | M13: =UPPER('route plans'!N709) -> N/A | N13: =UPPER('route plans'!O709) -> NO | S13: =UPPER('route plans'!T709) -> HAMZA/ZYED/MOHAMED | T13: ='route plans'!U709 -> 011 419 3019 | W13: ='route plans'!X709 -> 0 | X13: ='route plans'!Y709 -> 0 | Y13: =UPPER('route plans'!Z709) | Z13: =UPPER('route plans'!AA709) -> AHARDWAREMOKALE@GMAIL.COM;ADMIN@AHARDWARE.CO.ZA | AB13: ='route plans'!AC709 -> #VALUE!
A14: A Hardware Mokale | B14: Krugersdorp | C14: Krugersdorp | D14: Gauteng | E14: 14611 Masedi Str Riverside Kagiso Kurgersdorp | G14: EST | L14: HARDWARE | S14: Hamza/Zyed/Mohamed | T14: 011 419 3019 | Z14: ahardwaremokale@gmail.com;admin@ahardware.co.za
A15: =UPPER('route plans'!A1943) -> A HARDWARE ZANDSPRUIT | B15: =UPPER('route plans'!B1943) -> ROODEPOORT | C15: =UPPER('route plans'!C1943) -> ROODEPOORT | D15: =UPPER('route plans'!D1943) -> GAUTENG | E15: =UPPER('route plans'!E1943) -> 187 MARINA ROAD ZANDSPRUIT ROODEPOORT 2169 | F15: =UPPER('route plans'!G1943) -> NO | G15: =UPPER('route plans'!H1943) -> BUILD IT | L15: HARDWARE | M15: =UPPER('route plans'!N1943) -> N/A | N15: =UPPER('route plans'!O1943) -> N | S15: =UPPER('route plans'!T1943) -> HAMZA/ZYED/MOHAMED | T15: ='route plans'!U1943 -> 011 419 3019 | W15: ='route plans'!X1943 -> 0 | X15: ='route plans'!Y1943 -> 0 | Y15: =UPPER('route plans'!Z1943) | Z15: =UPPER('route plans'!AA1943) -> AHARDWAREMOKALE@GMAIL.COM;ADMIN@AHARDWARE.CO.ZA | AB15: ='route plans'!AC1943 -> 823
A16: =UPPER('route plans'!A651) -> A ONE HARDWARE STORE | B16: =UPPER('route plans'!B651) -> GRABOUW | C16: =UPPER('route plans'!C651) -> GRABOUW | D16: =UPPER('route plans'!D651) -> WESTERN CAPE | E16: =UPPER('route plans'!E651) -> 1507 VIOLA STREET | F16: =UPPER('route plans'!G651) -> NO | G16: =UPPER('route plans'!H651) -> NONE | L16: HARDWARE | M16: =UPPER('route plans'!N651) -> 30DAYS | N16: =UPPER('route plans'!O651) -> NO | S16: =UPPER('route plans'!T651) -> INAM | T16: ='route plans'!U651 -> 0670124496 | W16: ='route plans'!X651 -> 44434 | X16: ='route plans'!Y651 -> 55 | Y16: =UPPER('route plans'!Z651) | Z16: =UPPER('route plans'!AA651) | AB16: ='route plans'!AC651 -> 832
A17: =UPPER('route plans'!A139) -> A PLUS MARKETING PTY LTD T/A MICA LENASIA | B17: =UPPER('route plans'!B139) -> LENASIA | C17: =UPPER('route plans'!C139) -> LENASIA | D17: =UPPER('route plans'!D139) -> GAUTENG | E17: =UPPER('route plans'!E139) -> 4 MAIN LAWLET RD | F17: =UPPER('route plans'!G139) -> NO | G17: =UPPER('route plans'!H139) -> FBS | L17: HARDWARE | M17: =UPPER('route plans'!N139) -> 30DAYS | N17: =UPPER('route plans'!O139) -> YES | S17: =UPPER('route plans'!T139) -> CERWIN | T17: ='route plans'!U139 -> 0118520797 | W17: ='route plans'!X139 -> 44484 | X17: ='route plans'!Y139 -> 5 | Y17: =UPPER('route plans'!Z139) -> TYRONE | Z17: =UPPER('route plans'!AA139) -> CERWINM@MICARETAIL.CO.ZA | AB17: ='route plans'!AC139 -> 810
A18: =UPPER('route plans'!A27) -> A.A BUILDING MATERIAL LESOTHO | B18: =UPPER('route plans'!B27) -> LERIBE | C18: =UPPER('route plans'!C27) -> LERIBE | D18: =UPPER('route plans'!D27) -> LESOTHO | E18: =UPPER('route plans'!E27) -> AIRPORT ROAD LERIBE LESOTHO | F18: =UPPER('route plans'!G27) -> NO | G18: =UPPER('route plans'!H27) -> EST | L18: HARDWARE | M18: =UPPER('route plans'!N27) -> N/A | N18: =UPPER('route plans'!O27) -> NO | S18: =UPPER('route plans'!T27) -> HASSEN NOORMOHAMED | T18: ='route plans'!U27 -> 266 22400795 | W18: ='route plans'!X27 -> 0 | X18: ='route plans'!Y27 -> 0 | Y18: =UPPER('route plans'!Z27) | Z18: =UPPER('route plans'!AA27) -> IRSHU7860@HOTMAIL.COM | AB18: ='route plans'!AC27 -> 810
A19: =UPPER('route plans'!A59) -> A.A BUILDING MATERIAL LESOTHO | B19: =UPPER('route plans'!B59) -> LERIBE | C19: =UPPER('route plans'!C59) -> LERIBE | D19: =UPPER('route plans'!D59) -> LESOTHO | E19: =UPPER('route plans'!E59) -> AIRPORT ROAD LERIBE LESOTHO | F19: =UPPER('route plans'!G59) -> NO | G19: =UPPER('route plans'!H59) -> EST | L19: HARDWARE | M19: =UPPER('route plans'!N59) -> N/A | N19: =UPPER('route plans'!O59) -> NO | S19: =UPPER('route plans'!T59) -> HASSEN NOORMOHAMED | T19: ='route plans'!U59 -> 266 22400795 | W19: ='route plans'!X59 -> 0 | X19: ='route plans'!Y59 -> 0 | Y19: =UPPER('route plans'!Z59) | Z19: =UPPER('route plans'!AA59) -> IRSHU7860@HOTMAIL.COM | AB19: ='route plans'!AC59 -> 810
A20: =UPPER('route plans'!A2140) -> A.A BUILDING MATERIAL LESOTHO | B20: =UPPER('route plans'!B2140) -> LERIBE | C20: =UPPER('route plans'!C2140) -> LERIBE | D20: =UPPER('route plans'!D2140) -> LESOTHO | E20: =UPPER('route plans'!E2140) -> AIRPORT ROAD LERIBE LESOTHO | F20: =UPPER('route plans'!G2140) -> NO | G20: =UPPER('route plans'!H2140) -> BUILD IT | L20: HARDWARE | M20: =UPPER('route plans'!N2140) -> N/A | N20: =UPPER('route plans'!O2140) -> N | S20: =UPPER('route plans'!T2140) -> HASSEN NOORMOHAMED | T20: ='route plans'!U2140 -> 266 22400795 | W20: ='route plans'!X2140 -> 0 | X20: ='route plans'!Y2140 -> 0 | Y20: =UPPER('route plans'!Z2140) | Z20: =UPPER('route plans'!AA2140) -> IRSHU7860@HOTMAIL.COM | AB20: ='route plans'!AC2140 -> 823
A21: A.A Building Material LESOTHO | B21: Leribe | C21: Leribe | D21: Lesotho | E21: Airport Road Leribe Lesotho | G21: EST | L21: HARDWARE | S21: Hassen Noormohamed | T21: 266 22400795 | Z21: irshu7860@hotmail.com
A22: =UPPER('route plans'!A565) -> A.G. HARDWARE | B22: =UPPER('route plans'!B565) -> STANGER | C22: =UPPER('route plans'!C565) -> STANGER | D22: =UPPER('route plans'!D565) -> KWAZULU-NATAL | E22: =UPPER('route plans'!E565) -> SHOP 2, GROUND FLOOR, 22 KING SHAKA STREET, STANGER, KWAZULU-NATAL, 4450 | F22: =UPPER('route plans'!G565) -> NO | G22: =UPPER('route plans'!H565) -> POWER BUILD | L22: HARDWARE | M22: =UPPER('route plans'!N565) -> N/A | N22: =UPPER('route plans'!O565) -> NO | S22: =UPPER('route plans'!T565) -> RAWA BILAL | T22: ='route plans'!U565 -> 032 437 8194 | W22: ='route plans'!X565 -> 0 | X22: ='route plans'!Y565 -> 44489 | Y22: =UPPER('route plans'!Z565) | Z22: =UPPER('route plans'!AA565) -> ADMIN@ADILGENERALTRADERS.CO.ZA | AB22: ='route plans'!AC565 -> 827
A23: =UPPER('route plans'!A495) -> A.H MART | B23: =UPPER('route plans'!B495) -> QUMBU | C23: =UPPER('route plans'!C495) -> QUMBU | D23: =UPPER('route plans'!D495) -> EASTERN CAPE | E23: =UPPER('route plans'!E495) -> 146 OLD MAIN ROAD / STREET, QUMBU, EASTERN CAPE,5180 | F23: =UPPER('route plans'!G495) -> NO | G23: =UPPER('route plans'!H495) -> POWER BUILD | L23: HARDWARE | M23: =UPPER('route plans'!N495) -> N/A | N23: =UPPER('route plans'!O495) -> NO | S23: =UPPER('route plans'!T495) -> MUHAMMAD ASIF | T23: ='route plans'!U495 -> 073 993 9786 | W23: ='route plans'!X495 -> 0 | X23: ='route plans'!Y495 -> 44489 | Y23: =UPPER('route plans'!Z495) | Z23: =UPPER('route plans'!AA495) -> INFO@AHMART.CO.ZA | AB23: ='route plans'!AC495 -> 827
A24: =UPPER('route plans'!A496) -> A.H MART (ADDITIONAL DELIVERY ADDRESS MDANTSANE) | B24: =UPPER('route plans'!B496) -> MDANTSANE | C24: =UPPER('route plans'!C496) -> MDANTSANE | D24: =UPPER('route plans'!D496) -> EASTERN CAPE | E24: =UPPER('route plans'!E496) -> SHOP NO.8, SHOPRITE MALL, NU2 HIGHWAY, MDANTSANE, 5419 | F24: =UPPER('route plans'!G496) -> NO | G24: =UPPER('route plans'!H496) -> POWER BUILD | L24: HARDWARE | M24: =UPPER('route plans'!N496) -> N/A | N24: =UPPER('route plans'!O496) -> NO | S24: =UPPER('route plans'!T496) -> MUHAMMAD ASIF | T24: ='route plans'!U496 -> 073 993 9786 | W24: ='route plans'!X496 -> 0 | X24: ='route plans'!Y496 -> 44489 | Y24: =UPPER('route plans'!Z496) | Z24: =UPPER('route plans'!AA496) -> INFO@AHMART.CO.ZA | AB24: ='route plans'!AC496 -> 827
A25: =UPPER('route plans'!A497) -> A.H MART (ADDITIONAL DELIVERY ADDRESS QUEENSTOWN) | B25: =UPPER('route plans'!B497) -> QUEENSTOWN | C25: =UPPER('route plans'!C497) -> QUEENSTOWN | D25: =UPPER('route plans'!D497) -> EASTERN CAPE | E25: =UPPER('route plans'!E497) -> 6 SHEPSTONE STREET, QUEENSTOWN, EASTERN CAPE, 5320 | F25: =UPPER('route plans'!G497) -> NO | G25: =UPPER('route plans'!H497) -> POWER BUILD | L25: HARDWARE | M25: =UPPER('route plans'!N497) -> N/A | N25: =UPPER('route plans'!O497) -> NO | S25: =UPPER('route plans'!T497) -> MUHAMMAD ASIF | T25: ='route plans'!U497 -> 073 993 9786 | W25: ='route plans'!X497 -> 0 | X25: ='route plans'!Y497 -> 44489 | Y25: =UPPER('route plans'!Z497) | Z25: =UPPER('route plans'!AA497) -> INFO@AHMART.CO.ZA | AB25: ='route plans'!AC497 -> 827
A26: =UPPER('route plans'!A672) -> AB JAMIE TRADING | B26: =UPPER('route plans'!B672) -> COFIMVABA | C26: =UPPER('route plans'!C672) -> COFIMVABA | D26: =UPPER('route plans'!D672) -> EASTERN CAPE | E26: =UPPER('route plans'!E672) -> ERG 76 MAIN STREET COFIMVABA | F26: =UPPER('route plans'!G672) -> NO | G26: =UPPER('route plans'!H672) -> EST | L26: HARDWARE | M26: =UPPER('route plans'!N672) -> N/A | N26: =UPPER('route plans'!O672) -> NO | S26: =UPPER('route plans'!T672) -> ERF 76 MAIN STREET COFIMVABA | T26: ='route plans'!U672 -> 047 874 0810 | W26: ='route plans'!X672 -> 0 | X26: ='route plans'!Y672 -> 0 | Y26: =UPPER('route plans'!Z672) | Z26: =UPPER('route plans'!AA672) -> KINGHARDWARE003@GMAIL.COM | AB26: ='route plans'!AC672 -> #VALUE!
A27: =UPPER('route plans'!A564) -> ABBA MOOSA HARDWARE | B27: =UPPER('route plans'!B564) -> OVERPORT | C27: =UPPER('route plans'!C564) -> OVERPORT | D27: =UPPER('route plans'!D564) -> KWAZULU-NATAL | E27: =UPPER('route plans'!E564) -> 189 MOSES KOTANE ROAD, OVERPORT, 4091 | F27: =UPPER('route plans'!G564) -> NO | G27: =UPPER('route plans'!H564) -> POWER BUILD | L27: HARDWARE | M27: =UPPER('route plans'!N564) -> N/A | N27: =UPPER('route plans'!O564) -> NO | S27: =UPPER('route plans'!T564) -> ZAHEER ESSA | T27: ='route plans'!U564 -> 031 208 6511 | W27: ='route plans'!X564 -> 0 | X27: ='route plans'!Y564 -> 44489 | Y27: =UPPER('route plans'!Z564) | Z27: =UPPER('route plans'!AA564) -> ABBAMOOSAS@GMAIL.COM | AB27: ='route plans'!AC564 -> 827
A28: =UPPER('route plans'!A2124) -> ABERDARE HARDWARE | B28: =UPPER('route plans'!B2124) -> PHOENIX | C28: =UPPER('route plans'!C2124) -> PHOENIX | D28: =UPPER('route plans'!D2124) -> KWAZULU-NATAL | E28: =UPPER('route plans'!E2124) -> 261 ABERDARE DR PHOENIX INDUSTRIAL PARK 4068 | F28: =UPPER('route plans'!G2124) -> NO | G28: =UPPER('route plans'!H2124) -> BUILD IT | L28: HARDWARE | M28: =UPPER('route plans'!N2124) -> N/A | N28: =UPPER('route plans'!O2124) -> N | S28: =UPPER('route plans'!T2124) -> MR D MAHARAJ | T28: ='route plans'!U2124 -> 031 500 5306 | W28: ='route plans'!X2124 -> 0 | X28: ='route plans'!Y2124 -> 0 | Y28: =UPPER('route plans'!Z2124) | Z28: =UPPER('route plans'!AA2124) -> MAHOMED.HASSIM@PINETIMBERS.CO.ZA | AB28: ='route plans'!AC2124 -> 823
A29: =UPPER('route plans'!A671) -> ABERDARE HARDWARE | B29: =UPPER('route plans'!B671) -> PHOENIX | C29: =UPPER('route plans'!C671) -> PHOENIX | D29: =UPPER('route plans'!D671) -> KWAZULU-NATAL | E29: =UPPER('route plans'!E671) -> 261 ABERDARE DR PHOENIX INDUSTRIAL PARK 4068 | F29: =UPPER('route plans'!G671) -> NO | G29: =UPPER('route plans'!H671) -> EST | L29: HARDWARE | M29: =UPPER('route plans'!N671) -> N/A | N29: =UPPER('route plans'!O671) -> NO | S29: =UPPER('route plans'!T671) -> MR D MAHARAJ | T29: ='route plans'!U671 -> 031 500 5306 | W29: ='route plans'!X671 -> 0 | X29: ='route plans'!Y671 -> 0 | Y29: =UPPER('route plans'!Z671) | Z29: =UPPER('route plans'!AA671) -> ABEDARE@TELKOMSA.NET;LEAESH@ABERDARE.BIZ | AB29: ='route plans'!AC671 -> #VALUE!
A30: Aberdare Hardware | B30: Phoenix | C30: Phoenix | D30: KwaZulu-Natal | E30: 261 Aberdare Dr Phoenix Industrial Park 4068 | G30: EST | L30: HARDWARE | S30: Mr D Maharaj | T30: 031 500 5306 | Z30: abedare@telkomsa.net
A31: =UPPER('route plans'!A2224) -> ABM PLUMBING & ELECTRICAL | B31: =UPPER('route plans'!B2224) -> WYNBERG | C31: =UPPER('route plans'!C2224) -> WYNBERG | D31: =UPPER('route plans'!D2224) -> WESTERN CAPE | E31: =UPPER('route plans'!E2224) -> 1 OTTERY RD | F31: =UPPER('route plans'!G2224) -> NO | G31: =UPPER('route plans'!H2224) -> NONE | L31: HARDWARE | M31: =UPPER('route plans'!N2224) -> 30DAYS | N31: =UPPER('route plans'!O2224) -> NO | S31: =UPPER('route plans'!T2224) -> NYTAN | T31: ='route plans'!U2224 -> #N/A | W31: ='route plans'!X2224 -> 0 | X31: ='route plans'!Y2224 -> 0 | Y31: =UPPER('route plans'!Z2224) | Z31: =UPPER('route plans'!AA2224) -> SIEGFRIED@BENBEL.CO.ZA | AB31: ='route plans'!AC2224 -> 823
A32: =UPPER('route plans'!A673) -> ABOO HARDWARE STEILOOP | B32: =UPPER('route plans'!B673) -> STEILOOP | C32: =UPPER('route plans'!C673) -> MOKOPANE | D32: =UPPER('route plans'!D673) -> LIMPOPO | E32: =UPPER('route plans'!E673) -> NO 27 STEILOOP COMPLEX N11 | F32: =UPPER('route plans'!G673) -> NO | G32: =UPPER('route plans'!H673) -> EST | L32: HARDWARE | M32: =UPPER('route plans'!N673) -> N/A | N32: =UPPER('route plans'!O673) -> NO | S32: =UPPER('route plans'!T673) -> MOHAMED | T32: ='route plans'!U673 -> 078 237 8828 | W32: ='route plans'!X673 -> 0 | X32: ='route plans'!Y673 -> 0 | Y32: =UPPER('route plans'!Z673) | Z32: =UPPER('route plans'!AA673) -> ABOO@TAAHAA.CO.ZA | AB32: ='route plans'!AC673 -> #VALUE!
A33: Aboo Hardware Steiloop | B33: Mokopane | C33: Mokopane | D33: Limpopo | E33: No 27 Steiloop Complex N11 | G33: EST | L33: HARDWARE | S33: Mohamed | T33: 078 237 8828 | Z33: aboo@taahaa.co.za
A34: =UPPER('route plans'!A674) -> ACE HARDWARE | B34: =UPPER('route plans'!B674) -> BURGERSFORT | C34: =UPPER('route plans'!C674) -> BURGERSFORT | D34: =UPPER('route plans'!D674) -> LIMPOPO | E34: =UPPER('route plans'!E674) -> 8 TARFAN PLAZA, MAIN RD, BURGERSFORT | F34: =UPPER('route plans'!G674) -> NO | G34: =UPPER('route plans'!H674) -> EST | L34: HARDWARE | M34: =UPPER('route plans'!N674) -> N/A | N34: =UPPER('route plans'!O674) -> NO | S34: =UPPER('route plans'!T674) -> TAR MAHOMED | T34: ='route plans'!U674 -> 013 231 7861 | W34: ='route plans'!X674 -> 0 | X34: ='route plans'!Y674 -> 0 | Y34: =UPPER('route plans'!Z674) | Z34: =UPPER('route plans'!AA674) -> ABU@ACEHARDWARE.CO.ZA | AB34: ='route plans'!AC674 -> #VALUE!
A35: Ace Hardware | B35: Burgersfort | C35: Burgersfort | D35: Limpopo | E35: 8 Tarfan Plaza, Main Rd, Burgersfort | G35: EST | L35: HARDWARE | S35: Tar Mahomed | T35: 013 231 7861 | Z35: abu@acehardware.co.za
A36: Ace Hardware & Furnishers Standerton | B36: Standerton | C36: Standerton | D36: Mpumalanga | E36: Shop 44 Oriental Plaza Standerton 2430 | G36: EST | L36: HARDWARE | S36: Naeem Gani | T36: 017 712 5891 | Z36: hardewareace40@gmail.com
A37: =UPPER('route plans'!A2150) -> ACE TILE & PAINT HARDWARE | B37: =UPPER('route plans'!B2150) -> PHOENIX | C37: =UPPER('route plans'!C2150) -> PHOENIX | D37: =UPPER('route plans'!D2150) -> KWAZULU-NATAL | E37: =UPPER('route plans'!E2150) -> 273 ABERDARE DRIVE, PHOENIX | F37: =UPPER('route plans'!G2150) -> NO | G37: =UPPER('route plans'!H2150) -> BUILD IT | L37: HARDWARE | M37: =UPPER('route plans'!N2150) -> N/A | N37: =UPPER('route plans'!O2150) -> N | S37: =UPPER('route plans'!T2150) -> AMID AKONJEE | T37: ='route plans'!U2150 -> 031 507 1214 | W37: ='route plans'!X2150 -> 0 | X37: ='route plans'!Y2150 -> 0 | Y37: =UPPER('route plans'!Z2150) | Z37: =UPPER('route plans'!AA2150) -> ABEDARE@TELKOMSA.NET | AB37: ='route plans'!AC2150 -> 823
A38: =UPPER('route plans'!A676) -> ACE TILE & PAINT HARDWARE | B38: =UPPER('route plans'!B676) -> PHOENIX | C38: =UPPER('route plans'!C676) -> PHOENIX | D38: =UPPER('route plans'!D676) -> KWAZULU-NATAL | E38: =UPPER('route plans'!E676) -> 273 ABERDARE DRIVE, PHOENIX | F38: =UPPER('route plans'!G676) -> NO | G38: =UPPER('route plans'!H676) -> EST | L38: HARDWARE | M38: =UPPER('route plans'!N676) -> N/A | N38: =UPPER('route plans'!O676) -> NO | S38: =UPPER('route plans'!T676) -> AMID AKONJEE | T38: ='route plans'!U676 -> 031 507 1214 | W38: ='route plans'!X676 -> 0 | X38: ='route plans'!Y676 -> 0 | Y38: =UPPER('route plans'!Z676) | Z38: =UPPER('route plans'!AA676) -> ACETILES@TELKOMSA.NET | AB38: ='route plans'!AC676 -> #VALUE!
A39: Ace Tile & paint Hardware | B39: Phoenix | C39: Phoenix | D39: KwaZulu-Natal | E39: 273 Aberdare Drive, Phoenix | G39: EST | L39: HARDWARE | S39: Amid Akonjee | T39: 031 507 1214 | Z39: acetiles@telkomsa.net
A40: Acornhoek Hardware | B40: Acornhoek | C40: Acornhoek | D40: Mpumalanga | E40: Shop 8 Acornhoek Mega City Acornhoek 1360 | G40: EST | L40: HARDWARE | S40: Abdul Munaf Turk | T40: 013 795 5680 | Z40: mafio@hotmail.co.za
A41: =UPPER('route plans'!A166) -> ACORNHOEK PLAZA HARDWARE | B41: =UPPER('route plans'!B166) -> ACORNHOEK | C41: =UPPER('route plans'!C166) -> ACORNHOEK | D41: =UPPER('route plans'!D166) -> MPUMALANGA | E41: =UPPER('route plans'!E166) -> SHOP 8, ACORNHOEK, PLAZA MAIN ROAD, ACORNHOEK | F41: =UPPER('route plans'!G166) -> NO | G41: =UPPER('route plans'!H166) -> EST | L41: HARDWARE | M41: =UPPER('route plans'!N166) -> N/A | N41: =UPPER('route plans'!O166) -> N | S41: =UPPER('route plans'!T166) | T41: ='route plans'!U166 -> 013 795 5680 | W41: ='route plans'!X166 -> 0 | X41: ='route plans'!Y166 -> 0 | Y41: =UPPER('route plans'!Z166) | Z41: =UPPER('route plans'!AA166) -> IHOOSEN7869@GMAIL.COM | AB41: ='route plans'!AC166 -> 810
A42: =UPPER('route plans'!A214) -> ACTION BUILD | B42: =UPPER('route plans'!B214) -> BETHAL | C42: =UPPER('route plans'!C214) -> BETHAL | D42: =UPPER('route plans'!D214) -> MPUMALANGA | E42: =UPPER('route plans'!E214) -> DU PLOOY STREET 42, BETHAL | F42: =UPPER('route plans'!G214) -> NO | G42: =UPPER('route plans'!H214) -> EST | L42: HARDWARE | M42: =UPPER('route plans'!N214) -> N/A | N42: =UPPER('route plans'!O214) -> NO | S42: =UPPER('route plans'!T214) -> MUKESH DAYA VALLABH | T42: ='route plans'!U214 -> 082 564 5892 | W42: ='route plans'!X214 -> 44543 | X42: ='route plans'!Y214 -> 2 | Y42: =UPPER('route plans'!Z214) -> GERHARD | Z42: =UPPER('route plans'!AA214) -> SUNNYHARDWARE.904@GMAIL.COM | AB42: ='route plans'!AC214 -> 810
A43: =UPPER('route plans'!A387) -> ACTION MICA | B43: =UPPER('route plans'!B387) -> RANDBURG | C43: =UPPER('route plans'!C387) -> JOHANNESBURG | D43: =UPPER('route plans'!D387) -> GAUTENG | E43: =UPPER('route plans'!E387) -> 60 FRERE ST, KENSINGTON B, RANDBURG, 2194 | F43: =UPPER('route plans'!G387) -> NO | G43: =UPPER('route plans'!H387) -> MICA | L43: HARDWARE | M43: =UPPER('route plans'!N387) -> N/A | N43: =UPPER('route plans'!O387) -> NO | S43: =UPPER('route plans'!T387) | T43: ='route plans'!U387 -> 118863102 | W43: ='route plans'!X387 -> 0 | X43: ='route plans'!Y387 -> 44489 | Y43: =UPPER('route plans'!Z387) | Z43: =UPPER('route plans'!AA387) | AB43: ='route plans'!AC387 -> 827
A44: =UPPER('route plans'!A29) -> ACTIVE BUILD AND DÉCOR | B44: =UPPER('route plans'!B29) -> THOHOYANDOU | C44: =UPPER('route plans'!C29) -> THOHOYANDOU | D44: =UPPER('route plans'!D29) -> LIMPOPO | E44: =UPPER('route plans'!E29) -> SHOP D1B, SABINA PLAZA, THOHOYANDOU | F44: =UPPER('route plans'!G29) -> NO | G44: =UPPER('route plans'!H29) -> EST | L44: HARDWARE | M44: =UPPER('route plans'!N29) -> N/A | N44: =UPPER('route plans'!O29) -> NO | S44: =UPPER('route plans'!T29) -> MUAAZ SAGIR | T44: ='route plans'!U29 -> 015 962 5654/072 952 4091 | W44: ='route plans'!X29 -> 0 | X44: ='route plans'!Y29 -> 0 | Y44: =UPPER('route plans'!Z29) | Z44: =UPPER('route plans'!AA29) -> ACTIVEBUILD1931@GMAIL.COM; BRIDGEMOTORS@TISCALI.CO.ZA | AB44: ='route plans'!AC29 -> 810
A45: =UPPER('route plans'!A33) -> ACTIVE BUILD HARDWARE | B45: =UPPER('route plans'!B33) -> OBERHOLZER | C45: =UPPER('route plans'!C33) -> CARLTONVILLE | D45: =UPPER('route plans'!D33) -> GAUTENG | E45: =UPPER('route plans'!E33) -> 44 VAN ZYL STREET, OBERHOLZER, CARLTONVILLE | F45: =UPPER('route plans'!G33) -> NO | G45: =UPPER('route plans'!H33) -> EST | L45: HARDWARE | M45: =UPPER('route plans'!N33) -> N/A | N45: =UPPER('route plans'!O33) -> NO | S45: =UPPER('route plans'!T33) -> ZAAKIR ESSOOP | T45: ='route plans'!U33 -> 018 788 2275 | W45: ='route plans'!X33 -> 0 | X45: ='route plans'!Y33 -> 0 | Y45: =UPPER('route plans'!Z33) | Z45: =UPPER('route plans'!AA33) -> ACTIVEBUILD@GMAIL.COM | AB45: ='route plans'!AC33 -> 810
A46: =UPPER('route plans'!A60) -> ACTIVE BUILD HARDWARE | B46: =UPPER('route plans'!B60) -> OBERHOLZER | C46: =UPPER('route plans'!C60) -> CARLTONVILLE | D46: =UPPER('route plans'!D60) -> GAUTENG | E46: =UPPER('route plans'!E60) -> 44 VAN ZYL STREET, OBERHOLZER, CARLTONVILLE | F46: =UPPER('route plans'!G60) -> NO | G46: =UPPER('route plans'!H60) -> EST | L46: HARDWARE | M46: =UPPER('route plans'!N60) -> N/A | N46: =UPPER('route plans'!O60) -> NO | S46: =UPPER('route plans'!T60) -> ZAAKIR ESSOOP | T46: ='route plans'!U60 -> 018 788 2275 | W46: ='route plans'!X60 -> 0 | X46: ='route plans'!Y60 -> 0 | Y46: =UPPER('route plans'!Z60) | Z46: =UPPER('route plans'!AA60) -> ACTIVEBUILD@GMAIL.COM | AB46: ='route plans'!AC60 -> 810
A47: =UPPER('route plans'!A389) -> ACU CEILINGS AND PARTITIONS | B47: =UPPER('route plans'!B389) -> ROODEPOORT | C47: =UPPER('route plans'!C389) -> JOHANNESBURG | D47: =UPPER('route plans'!D389) -> GAUTENG | E47: =UPPER('route plans'!E389) -> ROODEPOORT | F47: =UPPER('route plans'!G389) -> NO | G47: =UPPER('route plans'!H389) -> NONE | L47: HARDWARE | M47: =UPPER('route plans'!N389) -> N/A | N47: =UPPER('route plans'!O389) -> NO | S47: =UPPER('route plans'!T389) | T47: ='route plans'!U389 -> 0116737064 | W47: ='route plans'!X389 -> 0 | X47: ='route plans'!Y389 -> 44489 | Y47: =UPPER('route plans'!Z389) | Z47: =UPPER('route plans'!AA389) | AB47: ='route plans'!AC389 -> 827
A48: =UPPER('route plans'!A390) -> ADEO SOUTH AFRICA PTY LTD T/A LEROY MERLIN | B48: =UPPER('route plans'!B390) -> EDENVALE | C48: =UPPER('route plans'!C390) -> JOHANNESBURG | D48: =UPPER('route plans'!D390) -> GAUTENG | E48: =UPPER('route plans'!E390) -> CORNER BLACKROCK STREET AND, STONERIDGE DR, EDENVALE, JOHANNESBURG, 1610 | F48: =UPPER('route plans'!G390) -> NO | G48: =UPPER('route plans'!H390) -> NONE | L48: HARDWARE | M48: =UPPER('route plans'!N390) -> 30DAYS | N48: =UPPER('route plans'!O390) -> NO | S48: =UPPER('route plans'!T390) | T48: ='route plans'!U390 -> #N/A | W48: ='route plans'!X390 -> 44385 | X48: ='route plans'!Y390 -> 104 | Y48: =UPPER('route plans'!Z390) | Z48: =UPPER('route plans'!AA390) | AB48: ='route plans'!AC390 -> 832
A49: =UPPER('route plans'!A36) -> AFRI BUILD | B49: =UPPER('route plans'!B36) -> MATATIELE | C49: =UPPER('route plans'!C36) -> MATATIELE | D49: =UPPER('route plans'!D36) -> EASTERN CAPE | E49: =UPPER('route plans'!E36) -> 40 WEST ST | F49: =UPPER('route plans'!G36) -> NO | G49: =UPPER('route plans'!H36) -> NONE | L49: HARDWARE | M49: =UPPER('route plans'!N36) -> 30DAYS | N49: =UPPER('route plans'!O36) -> NO | S49: =UPPER('route plans'!T36) -> JOLENE | T49: ='route plans'!U36 -> 039 737 3163 | W49: ='route plans'!X36 -> 0 | X49: ='route plans'!Y36 -> 44489 | Y49: =UPPER('route plans'!Z36) | Z49: =UPPER('route plans'!AA36) -> SALES@AFRIBUILD.CO.ZA | AB49: ='route plans'!AC36 -> 810
A50: =UPPER('route plans'!A681) -> AFRIBUILD | B50: =UPPER('route plans'!B681) -> MATATIELE | C50: =UPPER('route plans'!C681) -> MATATIELE | D50: =UPPER('route plans'!D681) -> KWAZULU-NATAL | E50: =UPPER('route plans'!E681) -> 68 LONG STREET , MATATIELE | F50: =UPPER('route plans'!G681) -> NO | G50: =UPPER('route plans'!H681) -> EST | L50: HARDWARE | M50: =UPPER('route plans'!N681) -> N/A | N50: =UPPER('route plans'!O681) -> NO | S50: =UPPER('route plans'!T681) -> AHMAD OSMAN | T50: ='route plans'!U681 -> 039 737 3163 | W50: ='route plans'!X681 -> 0 | X50: ='route plans'!Y681 -> 0 | Y50: =UPPER('route plans'!Z681) | Z50: =UPPER('route plans'!AA681) -> INFO@AFRI-BUILD.CO.ZA | AB50: ='route plans'!AC681 -> #VALUE!
A51: =UPPER('route plans'!A1999) -> AFRIBUILD | B51: =UPPER('route plans'!B1999) -> MATATIELE | C51: =UPPER('route plans'!C1999) -> MATATIELE | D51: =UPPER('route plans'!D1999) -> KWAZULU-NATAL | E51: =UPPER('route plans'!E1999) -> 68 LONG STREET , MATATIELE | F51: =UPPER('route plans'!G1999) -> NO | G51: =UPPER('route plans'!H1999) -> BUILD IT | L51: HARDWARE | M51: =UPPER('route plans'!N1999) -> N/A | N51: =UPPER('route plans'!O1999) -> N | S51: =UPPER('route plans'!T1999) -> AHMAD OSMAN | T51: ='route plans'!U1999 -> 039 737 3163 | W51: ='route plans'!X1999 -> 0 | X51: ='route plans'!Y1999 -> 0 | Y51: =UPPER('route plans'!Z1999) | Z51: =UPPER('route plans'!AA1999) -> MOORBEE@GMAIL.COM;PHOENIX.TILE.MARKET@GMAIL.COM;ACCOUNTS@HYPERTILE.CO.ZA | AB51: ='route plans'!AC1999 -> 823
A52: Afribuild | B52: Matatiele | C52: Matatiele | D52: Kwa-Zulu Natal | E52: 68 Long Street , Matatiele | G52: INDEPENDENT | L52: HARDWARE | S52: Ahmad Osman | T52: 039 737 3163 | Z52: info@afri-build.co.za
A53: Afribuild | B53: Matatiele | C53: Matatiele | D53: KwaZulu-Natal | E53: 68 Long Street , Matatiele | G53: EST | L53: HARDWARE | S53: Ahmad Osman | T53: 039 737 3163 | Z53: info@afri-build.co.za
A54: =UPPER('route plans'!A501) -> AFRICA HARDWARE | B54: =UPPER('route plans'!B501) -> MQANDULI | C54: =UPPER('route plans'!C501) -> MQANDULI | D54: =UPPER('route plans'!D501) -> EASTERN CAPE | E54: =UPPER('route plans'!E501) -> ERF 21, MAIN STREET, MQANDULI, 5080 | F54: =UPPER('route plans'!G501) -> NO | G54: =UPPER('route plans'!H501) -> POWER BUILD | L54: HARDWARE | M54: =UPPER('route plans'!N501) -> N/A | N54: =UPPER('route plans'!O501) -> NO | S54: =UPPER('route plans'!T501) -> NAVEED AKHTAR | T54: ='route plans'!U501 -> 078 425 2140 | W54: ='route plans'!X501 -> 0 | X54: ='route plans'!Y501 -> 44489 | Y54: =UPPER('route plans'!Z501) | Z54: =UPPER('route plans'!AA501) -> NAVEEDWARRAICH22@GMAIL.COM | AB54: ='route plans'!AC501 -> 827
A55: =UPPER('route plans'!A577) -> AFRICA HARDWARE FLAGSTAFF | B55: =UPPER('route plans'!B577) -> FLAGSTAFF | C55: =UPPER('route plans'!C577) -> FLAGSTAFF | D55: =UPPER('route plans'!D577) -> KWAZULU-NATAL | E55: =UPPER('route plans'!E577) -> ERF 50 MAIN STREET, FLAGSTAFF, KWAZULU-NATAL, 4810 | F55: =UPPER('route plans'!G577) -> NO | G55: =UPPER('route plans'!H577) -> POWER BUILD | L55: HARDWARE | M55: =UPPER('route plans'!N577) -> N/A | N55: =UPPER('route plans'!O577) -> NO | S55: =UPPER('route plans'!T577) -> MASOOD BAKHTIAR | T55: ='route plans'!U577 -> 061 175 4784 | W55: ='route plans'!X577 -> 0 | X55: ='route plans'!Y577 -> 44489 | Y55: =UPPER('route plans'!Z577) | Z55: =UPPER('route plans'!AA577) -> MASOODBAKHTIAR23@GMAIL.COM | AB55: ='route plans'!AC577 -> 827
A56: =UPPER('route plans'!A1464) -> AFRICA HARDWARE PHOLA MALL | B56: =UPPER('route plans'!B1464) -> KWAMHLANGA | C56: =UPPER('route plans'!C1464) -> KWAMHLANGA | D56: =UPPER('route plans'!D1464) -> MPUMALANGA | E56: =UPPER('route plans'!E1464) -> STAND NO 1221, CORNER SHELDIN & R573 ROAD, PHOLA MALL, KWAMHLANGA | F56: =UPPER('route plans'!G1464) -> NO | G56: =UPPER('route plans'!H1464) -> NONE | L56: HARDWARE | M56: =UPPER('route plans'!N1464) -> COD | N56: =UPPER('route plans'!O1464) -> NO | S56: =UPPER('route plans'!T1464) | T56: ='route plans'!U1464 -> 0 | W56: ='route plans'!X1464 -> 0 | X56: ='route plans'!Y1464 -> 0 | Y56: =UPPER('route plans'!Z1464) | Z56: =UPPER('route plans'!AA1464) -> KARELPIETER@TOTALLYGAS.CO.ZA | AB56: ='route plans'!AC1464 -> #VALUE!
A57: =UPPER('route plans'!A682) -> AFRICA SPAREZONE SHAYANDIMA | B57: =UPPER('route plans'!B682) -> SHAYANDIMA | C57: =UPPER('route plans'!C682) -> SHAYANDIMA | D57: =UPPER('route plans'!D682) -> LIMPOPO | E57: =UPPER('route plans'!E682) -> BUILDERZONE R524 MAIN ROAD SHAYANDIMA 0945 | F57: =UPPER('route plans'!G682) -> NO | G57: =UPPER('route plans'!H682) -> EST | L57: HARDWARE | M57: =UPPER('route plans'!N682) -> N/A | N57: =UPPER('route plans'!O682) -> NO | S57: =UPPER('route plans'!T682) -> IRFAN | T57: ='route plans'!U682 -> 015 962 3131 | W57: ='route plans'!X682 -> 0 | X57: ='route plans'!Y682 -> 0 | Y57: =UPPER('route plans'!Z682) | Z57: =UPPER('route plans'!AA682) -> BUILDERSZONE@GMAIL.COM | AB57: ='route plans'!AC682 -> #VALUE!
A58: =UPPER('route plans'!A683) -> AFRICA SPAREZONE THOHOYANDOU | B58: =UPPER('route plans'!B683) -> THOHOYANDOU | C58: =UPPER('route plans'!C683) -> THOHOYANDOU | D58: =UPPER('route plans'!D683) -> LIMPOPO | E58: =UPPER('route plans'!E683) -> P.O BOX 592 THOHOYANDOU 0950 | F58: =UPPER('route plans'!G683) -> NO | G58: =UPPER('route plans'!H683) -> EST | L58: HARDWARE | M58: =UPPER('route plans'!N683) -> N/A | N58: =UPPER('route plans'!O683) -> NO | S58: =UPPER('route plans'!T683) -> IRFAN | T58: ='route plans'!U683 -> 015 962 313 | W58: ='route plans'!X683 -> 0 | X58: ='route plans'!Y683 -> 0 | Y58: =UPPER('route plans'!Z683) | Z58: =UPPER('route plans'!AA683) -> 'BUILDERSZONE@EMAIL.COM' | AB58: ='route plans'!AC683 -> #VALUE!
A59: Africa Sparezone CC Builderzone | B59: Thohoyandou | C59: Thohoyandou | D59: Limpopo | E59: P.O Box 592 Thohoyandou 0950 | G59: EST | L59: HARDWARE | S59: Irfan | T59: 015 962 313 | Z59: 'builderszone@email.com'
A60: =UPPER('route plans'!A1408) -> AFRICA TIMBERS | B60: =UPPER('route plans'!B1408) -> PORTELIZABETH | C60: =UPPER('route plans'!C1408) -> PORTELIZABETH | D60: =UPPER('route plans'!D1408) -> EASTERN CAPE | E60: =UPPER('route plans'!E1408) -> 82 HAUPT STREET, SIDWELL, PORT ELIZABETH | F60: =UPPER('route plans'!G1408) -> NO | G60: =UPPER('route plans'!H1408) -> EST | L60: HARDWARE | M60: =UPPER('route plans'!N1408) -> N/A | N60: =UPPER('route plans'!O1408) -> NO | S60: =UPPER('route plans'!T1408) -> CRAIG | T60: ='route plans'!U1408 -> 041 453 4341 | W60: ='route plans'!X1408 -> 0 | X60: ='route plans'!Y1408 -> 0 | Y60: =UPPER('route plans'!Z1408) | Z60: =UPPER('route plans'!AA1408) -> JANET@AFRICATIMBERS.CO.ZA | AB60: ='route plans'!AC1408 -> #VALUE!
A61: =UPPER('route plans'!A2156) -> AFRICA TIMBERS | B61: =UPPER('route plans'!B2156) -> PORTELIZABETH | C61: =UPPER('route plans'!C2156) -> PORTELIZABETH | D61: =UPPER('route plans'!D2156) -> EASTERN CAPE | E61: =UPPER('route plans'!E2156) -> 82 HAUPT STREET, SIDWELL, PORT ELIZABETH | F61: =UPPER('route plans'!G2156) -> NO | G61: =UPPER('route plans'!H2156) -> BUILD IT | L61: HARDWARE | M61: =UPPER('route plans'!N2156) -> N/A | N61: =UPPER('route plans'!O2156) -> N | S61: =UPPER('route plans'!T2156) -> CRAIG | T61: ='route plans'!U2156 -> 041 453 4341 | W61: ='route plans'!X2156 -> 0 | X61: ='route plans'!Y2156 -> 0 | Y61: =UPPER('route plans'!Z2156) | Z61: =UPPER('route plans'!AA2156) -> CRAIG@AFRICATIMBERS.CO.ZA | AB61: ='route plans'!AC2156 -> 823
A62: Africa Timbers | B62: Portelizabeth | C62: Portelizabeth | D62: Eastern Cape | E62: 82 Haupt Street, Sidwell, Port Elizabeth | G62: EST | L62: HARDWARE | S62: Craig | T62: 041 453 4341 | Z62: craig@africatimbers.co.za
A63: =UPPER('route plans'!A574) -> AFRICAN HARDWARE | B63: =UPPER('route plans'!B574) -> BHAMSHELA | C63: =UPPER('route plans'!C574) -> BHAMSHELA | D63: =UPPER('route plans'!D574) -> KWAZULU-NATAL | E63: =UPPER('route plans'!E574) -> 1521 CHIBINI ROAD, OZWATHINI AREA, BHAMSHELA, 3242 | F63: =UPPER('route plans'!G574) -> NO | G63: =UPPER('route plans'!H574) -> POWER BUILD | L63: HARDWARE | M63: =UPPER('route plans'!N574) -> N/A | N63: =UPPER('route plans'!O574) -> NO | S63: =UPPER('route plans'!T574) -> DANIEL ERGITHO | T63: ='route plans'!U574 -> 076 645 6497 | W63: ='route plans'!X574 -> 0 | X63: ='route plans'!Y574 -> 44489 | Y63: =UPPER('route plans'!Z574) | Z63: =UPPER('route plans'!AA574) -> ERICHODANIEL@GMAIL.COM | AB63: ='route plans'!AC574 -> 827
A64: =UPPER('route plans'!A37) -> AFRICAN HARDWARE BERLIN | B64: =UPPER('route plans'!B37) -> BERLIN | C64: =UPPER('route plans'!C37) -> BERLIN | D64: =UPPER('route plans'!D37) -> EASTERN CAPE | E64: =UPPER('route plans'!E37) -> 1800 LEGION STREET, BERLIN, EAST LONDON, EASTERN CAPE | F64: =UPPER('route plans'!G37) -> NO | G64: =UPPER('route plans'!H37) -> POWER BUILD | L64: HARDWARE | M64: =UPPER('route plans'!N37) -> N/A | N64: =UPPER('route plans'!O37) -> NO | S64: =UPPER('route plans'!T37) -> MEHDI HASSAN | T64: ='route plans'!U37 -> 081 387 6993/043 685 2019 | W64: ='route plans'!X37 -> 0 | X64: ='route plans'!Y37 -> 44489 | Y64: =UPPER('route plans'!Z37) | Z64: =UPPER('route plans'!AA37) -> MEHDIHASSAN136@GMAIL.COM | AB64: ='route plans'!AC37 -> 827
A65: =UPPER('route plans'!A528) -> AFRICAN HARDWARE STORE KING WILLIAMS TOWN | B65: =UPPER('route plans'!B528) -> KING WILLIAMS TOWN | C65: =UPPER('route plans'!C528) -> KING WILLIAMS TOWN | D65: =UPPER('route plans'!D528) -> EASTERN CAPE | E65: =UPPER('route plans'!E528) -> 168 BUFFALO STREET, KING WILLIAMS TOWN, EASTERN CAPE | F65: =UPPER('route plans'!G528) -> NO | G65: =UPPER('route plans'!H528) -> POWER BUILD | L65: HARDWARE | M65: =UPPER('route plans'!N528) -> N/A | N65: =UPPER('route plans'!O528) -> NO | S65: =UPPER('route plans'!T528) -> MEHDI HASSAN | T65: ='route plans'!U528 -> '081 387 6993 | W65: ='route plans'!X528 -> 0 | X65: ='route plans'!Y528 -> 44489 | Y65: =UPPER('route plans'!Z528) | Z65: =UPPER('route plans'!AA528) -> MEHDIHASSAN136@GMAIL.COM | AB65: ='route plans'!AC528 -> 827
A66: =UPPER('route plans'!A41) -> AGRA HARDAP BRANCH 143 | B66: =UPPER('route plans'!B41) -> MARIENTAL | C66: =UPPER('route plans'!C41) -> NAMIBIA | D66: =UPPER('route plans'!D41) -> NAMIBIA | E66: =UPPER('route plans'!E41) -> PLOT NARIS 111 MARIENTAL NAMIBIA | F66: =UPPER('route plans'!G41) -> NO | G66: =UPPER('route plans'!H41) -> EST | L66: HARDWARE | M66: =UPPER('route plans'!N41) -> N/A | N66: =UPPER('route plans'!O41) -> NO | S66: =UPPER('route plans'!T41) -> GRAEME SCHAEFER | T66: ='route plans'!U41 -> +063 241 501 | W66: ='route plans'!X41 -> 0 | X66: ='route plans'!Y41 -> 0 | Y66: =UPPER('route plans'!Z41) | Z66: =UPPER('route plans'!AA41) -> GRAEME@AGRA.COM.NA | AB66: ='route plans'!AC41 -> 810
A67: =UPPER('route plans'!A61) -> AGRA HARDAP BRANCH 143 | B67: =UPPER('route plans'!B61) -> MARIENTAL | C67: =UPPER('route plans'!C61) -> NAMIBIA | D67: =UPPER('route plans'!D61) -> NAMIBIA | E67: =UPPER('route plans'!E61) -> PLOT NARIS 111 MARIENTAL NAMIBIA | F67: =UPPER('route plans'!G61) -> NO | G67: =UPPER('route plans'!H61) -> EST | L67: HARDWARE | M67: =UPPER('route plans'!N61) -> N/A | N67: =UPPER('route plans'!O61) -> NO | S67: =UPPER('route plans'!T61) -> GRAEME SCHAEFER | T67: ='route plans'!U61 -> +063 241 501 | W67: ='route plans'!X61 -> 0 | X67: ='route plans'!Y61 -> 0 | Y67: =UPPER('route plans'!Z61) | Z67: =UPPER('route plans'!AA61) -> GRAEME@AGRA.COM.NA | AB67: ='route plans'!AC61 -> 810
A68: =UPPER('route plans'!A1956) -> AGRA HARDAP BRANCH 143 | B68: =UPPER('route plans'!B1956) -> NAMIBIA | C68: =UPPER('route plans'!C1956) -> NAMIBIA | D68: =UPPER('route plans'!D1956) -> NAMIBIA | E68: =UPPER('route plans'!E1956) -> PLOT NARIS 111 MARIENTAL NAMIBIA | F68: =UPPER('route plans'!G1956) -> NO | G68: =UPPER('route plans'!H1956) -> BUILD IT | L68: HARDWARE | M68: =UPPER('route plans'!N1956) -> N/A | N68: =UPPER('route plans'!O1956) -> N | S68: =UPPER('route plans'!T1956) -> GRAEME SCHAEFER | T68: ='route plans'!U1956 -> #ERROR! | W68: ='route plans'!X1956 -> 0 | X68: ='route plans'!Y1956 -> 0 | Y68: =UPPER('route plans'!Z1956) | Z68: =UPPER('route plans'!AA1956) -> GRAEME@AGRA.COM.NA | AB68: ='route plans'!AC1956 -> 823
A69: Agra Hardap Branch 143 | B69: Namibia | C69: Namibia | D69: Namibia | E69: Plot Naris 111 Mariental Namibia | G69: EST | L69: HARDWARE | S69: Graeme Schaefer | T69: +063 241 501 | Z69: Graeme@agra.com.na
A70: =UPPER('route plans'!A1957) -> AGRA HYPER BRANCH 114 | B70: =UPPER('route plans'!B1957) -> NAMIBIA | C70: =UPPER('route plans'!C1957) -> NAMIBIA | D70: =UPPER('route plans'!D1957) -> NAMIBIA | E70: =UPPER('route plans'!E1957) -> 232 INDUSTRIAL LAFRENZ INDUSTRIAL AREA WINDHOEK | F70: =UPPER('route plans'!G1957) -> NO | G70: =UPPER('route plans'!H1957) -> BUILD IT | L70: HARDWARE | M70: =UPPER('route plans'!N1957) -> N/A | N70: =UPPER('route plans'!O1957) -> N | S70: =UPPER('route plans'!T1957) -> GRAEME SCHAEFER | T70: ='route plans'!U1957 -> #ERROR! | W70: ='route plans'!X1957 -> 0 | X70: ='route plans'!Y1957 -> 0 | Y70: =UPPER('route plans'!Z1957) | Z70: =UPPER('route plans'!AA1957) -> GRAEME@AGRA.COM.NA | AB70: ='route plans'!AC1957 -> 823
A71: =UPPER('route plans'!A43) -> AGRA HYPER BRANCH 114 | B71: =UPPER('route plans'!B43) -> LAFRENZ | C71: =UPPER('route plans'!C43) -> WINDHOEK | D71: =UPPER('route plans'!D43) -> NAMIBIA | E71: =UPPER('route plans'!E43) -> 232 INDUSTRIAL LAFRENZ INDUSTRIAL AREA WINDHOEK | F71: =UPPER('route plans'!G43) -> NO | G71: =UPPER('route plans'!H43) -> EST | L71: HARDWARE | M71: =UPPER('route plans'!N43) -> N/A | N71: =UPPER('route plans'!O43) -> NO | S71: =UPPER('route plans'!T43) -> GRAEME SCHAEFER | T71: ='route plans'!U43 -> +061 290 9605 | W71: ='route plans'!X43 -> 0 | X71: ='route plans'!Y43 -> 0 | Y71: =UPPER('route plans'!Z43) | Z71: =UPPER('route plans'!AA43) -> GRAEME@AGRA.COM.NA | AB71: ='route plans'!AC43 -> 810
A72: =UPPER('route plans'!A63) -> AGRA HYPER BRANCH 114 | B72: =UPPER('route plans'!B63) -> LAFRENZ | C72: =UPPER('route plans'!C63) -> WINDHOEK | D72: =UPPER('route plans'!D63) -> NAMIBIA | E72: =UPPER('route plans'!E63) -> 232 INDUSTRIAL LAFRENZ INDUSTRIAL AREA WINDHOEK | F72: =UPPER('route plans'!G63) -> NO | G72: =UPPER('route plans'!H63) -> EST | L72: HARDWARE | M72: =UPPER('route plans'!N63) -> N/A | N72: =UPPER('route plans'!O63) -> NO | S72: =UPPER('route plans'!T63) -> GRAEME SCHAEFER | T72: ='route plans'!U63 -> +061 290 9605 | W72: ='route plans'!X63 -> 0 | X72: ='route plans'!Y63 -> 0 | Y72: =UPPER('route plans'!Z63) | Z72: =UPPER('route plans'!AA63) -> GRAEME@AGRA.COM.NA | AB72: ='route plans'!AC63 -> 810
A73: Agra Hyper Branch 114 | B73: Namibia | C73: Namibia | D73: Namibia | E73: 232 Industrial Lafrenz Industrial Area Windhoek | G73: EST | L73: HARDWARE | S73: Graeme Schaefer | T73: +061 290 9605 | Z73: Graeme@agra.com.na
A74: =UPPER('route plans'!A684) -> AGRA LIMITED H/O | B74: =UPPER('route plans'!B684) -> SOUTHERN IND AREA | C74: =UPPER('route plans'!C684) -> WINDHOEK | D74: =UPPER('route plans'!D684) -> NAMIBIA | E74: =UPPER('route plans'!E684) -> 8 BESSEMER STREET SOUTHERN IND AREA WINDHOEK | F74: =UPPER('route plans'!G684) -> NO | G74: =UPPER('route plans'!H684) -> EST | L74: HARDWARE | M74: =UPPER('route plans'!N684) -> N/A | N74: =UPPER('route plans'!O684) -> NO | S74: =UPPER('route plans'!T684) -> JUNE ALEXANDER | T74: ='route plans'!U684 -> +290 9232 | W74: ='route plans'!X684 -> 0 | X74: ='route plans'!Y684 -> 0 | Y74: =UPPER('route plans'!Z684) | Z74: =UPPER('route plans'!AA684) -> GRAEME@AGRA.COM.NA | AB74: ='route plans'!AC684 -> #VALUE!
A75: =UPPER('route plans'!A1958) -> AGRA LIMITED H/O | B75: =UPPER('route plans'!B1958) -> NAMIBIA | C75: =UPPER('route plans'!C1958) -> NAMIBIA | D75: =UPPER('route plans'!D1958) -> NAMIBIA | E75: =UPPER('route plans'!E1958) -> 8 BESSEMER STREET SOUTHERN IND AREA WINDHOEK | F75: =UPPER('route plans'!G1958) -> NO | G75: =UPPER('route plans'!H1958) -> BUILD IT | L75: HARDWARE | M75: =UPPER('route plans'!N1958) -> N/A | N75: =UPPER('route plans'!O1958) -> N | S75: =UPPER('route plans'!T1958) -> JUNE ALEXANDER | T75: ='route plans'!U1958 -> #ERROR! | W75: ='route plans'!X1958 -> 0 | X75: ='route plans'!Y1958 -> 0 | Y75: =UPPER('route plans'!Z1958) | Z75: =UPPER('route plans'!AA1958) -> GRAEME@AGRA.COM.NA | AB75: ='route plans'!AC1958 -> 823
A76: Agra Limited H/O | B76: Namibia | C76: Namibia | D76: Namibia | E76: 8 Bessemer Street Southern Ind Area Windhoek | G76: EST | L76: HARDWARE | S76: June Alexander | T76: +290 9232 | Z76: Graeme@agra.com.na
A77: =UPPER('route plans'!A2025) -> AGRI LAND & LANDMARK (HEAD OFFICE) | B77: =UPPER('route plans'!B2025) -> SWELLENDAM | C77: =UPPER('route plans'!C2025) -> SWELLENDAM | D77: =UPPER('route plans'!D2025) -> WESTERN CAPE | E77: =UPPER('route plans'!E2025) -> 34 VOORTREKKER STR SWELLENDAM 740 | F77: =UPPER('route plans'!G2025) -> NO | G77: =UPPER('route plans'!H2025) -> EST | L77: HARDWARE | M77: =UPPER('route plans'!N2025) -> N/A | N77: =UPPER('route plans'!O2025) -> NO | S77: =UPPER('route plans'!T2025) -> A.BURGER | T77: ='route plans'!U2025 -> 028 514 8600 | W77: ='route plans'!X2025 -> 0 | X77: ='route plans'!Y2025 -> 0 | Y77: =UPPER('route plans'!Z2025) | Z77: =UPPER('route plans'!AA2025) -> SADICK@SOPATRADING.CO.ZA | AB77: ='route plans'!AC2025 -> 823
A78: =UPPER('route plans'!A2162) -> AGRI LAND & LANDMARK (HEAD OFFICE) | B78: =UPPER('route plans'!B2162) -> SWELLENDAM | C78: =UPPER('route plans'!C2162) -> SWELLENDAM | D78: =UPPER('route plans'!D2162) -> WESTERN CAPE | E78: =UPPER('route plans'!E2162) -> 34 VOORTREKKER STR SWELLENDAM 740 | F78: =UPPER('route plans'!G2162) -> NO | G78: =UPPER('route plans'!H2162) -> BUILD IT | L78: HARDWARE | M78: =UPPER('route plans'!N2162) -> N/A | N78: =UPPER('route plans'!O2162) -> N | S78: =UPPER('route plans'!T2162) -> A.BURGER | T78: ='route plans'!U2162 -> 028 514 8600 | W78: ='route plans'!X2162 -> 0 | X78: ='route plans'!Y2162 -> 0 | Y78: =UPPER('route plans'!Z2162) | Z78: =UPPER('route plans'!AA2162) -> TIM@RJAMES.CO.ZA | AB78: ='route plans'!AC2162 -> 823
A79: Agri Land & Landmark (Head Office) | B79: Swellendam | C79: Swellendam | D79: Western Cape | E79: 34 Voortrekker Str Swellendam 740 | G79: EST | L79: HARDWARE | S79: A.Burger | T79: 028 514 8600 | Z79: andre@ssk.co.za
A80: =UPPER('route plans'!A755) -> AGRI LAND LANDMARK HEIDELBERG (BRANCH) | B80: =UPPER('route plans'!B755) -> HEIDELBERG | C80: =UPPER('route plans'!C755) -> HEIDELBERG | D80: =UPPER('route plans'!D755) -> WESTERN CAPE | E80: =UPPER('route plans'!E755) -> VAN RIECBEECK STR, HEIDELBERG | F80: =UPPER('route plans'!G755) -> NO | G80: =UPPER('route plans'!H755) -> EST | L80: HARDWARE | M80: =UPPER('route plans'!N755) -> N/A | N80: =UPPER('route plans'!O755) -> NO | S80: =UPPER('route plans'!T755) -> MANAGER KAREN NEL | T80: ='route plans'!U755 -> 028 514 8705 | W80: ='route plans'!X755 -> 44432 | X80: ='route plans'!Y755 -> 57 | Y80: =UPPER('route plans'!Z755) | Z80: =UPPER('route plans'!AA755) | AB80: ='route plans'!AC755 -> #VALUE!
A81: Agri land Landmark Heidelberg (Branch) | B81: Heidelberg | C81: Heidelberg | D81: Western Cape | E81: Van Riecbeeck Str, Heidelberg | G81: EST | L81: HARDWARE | S81: Manager Karen Nel | T81: 028 514 8705 | Z81: karen@ssk.co.za
A82: =UPPER('route plans'!A1547) -> AGRI LAND ROBERTSON (BRANCH) | B82: =UPPER('route plans'!B1547) -> ROBERTSON | C82: =UPPER('route plans'!C1547) -> ROBERTSON | D82: =UPPER('route plans'!D1547) -> WESTERN CAPE | E82: =UPPER('route plans'!E1547) -> 62 ROUTE STR ROBERTSON | F82: =UPPER('route plans'!G1547) -> NO | G82: =UPPER('route plans'!H1547) -> EST | L82: HARDWARE | M82: =UPPER('route plans'!N1547) -> N/A | N82: =UPPER('route plans'!O1547) -> NO | S82: =UPPER('route plans'!T1547) -> MANAGER:LENOR OBERHOLSER | T82: ='route plans'!U1547 -> 028 514 8684 | W82: ='route plans'!X1547 -> 0 | X82: ='route plans'!Y1547 -> 0 | Y82: =UPPER('route plans'!Z1547) | Z82: =UPPER('route plans'!AA1547) -> INFO@WESTCOASTPAINTS.CO.ZA | AB82: ='route plans'!AC1547 -> #VALUE!
A83: Agri Land Robertson (Branch) | B83: Robertson | C83: Robertson | D83: Western Cape | E83: 62 Route str Robertson | G83: EST | L83: HARDWARE | S83: Manager:Lenor Oberholser | T83: 028 514 8684 | Z83: loberholster@ssk.co.za
A84: AGRI LAND SWELLENDAM (BRANCH) | B84: SWELLENDAM | C84: SWELLENDAM | D84: WESTERN CAPE | E84: 34 VOORTREKKER STR SWELLENDAM | F84: NO | G84: EST | H84: NEW | I84: 44386 | J84: =ABS(IF(ISBLANK(I84),"",TODAY()-I84)) -> 921 | K84: =I84+14 -> 44400 | L84: CORNICE | M84: N/A | N84: NO | P84: =ABS(IF(ISBLANK(O84),"",TODAY()-O84)) -> #VALUE! | Q84: N | S84: ANDRE V WYK | T84: 028 514 8672 | Z84: ADMIN@OMEGA.CO.ZA;KOBUS@ADMIN.CO.ZA | AA84: 44484 | AB84: =ABS(IF(ISBLANK(AA84),"",TODAY()-AA84)) -> 823 | AC84: YOLANDI | AD84: HOMEPACK BR PROMOTION
A85: =UPPER('route plans'!A2056) -> AGRI LAND SWELLENDAM (BRANCH) | B85: =UPPER('route plans'!B2056) -> SWELLENDAM | C85: =UPPER('route plans'!C2056) -> SWELLENDAM | D85: =UPPER('route plans'!D2056) -> WESTERN CAPE | E85: =UPPER('route plans'!E2056) -> 34 VOORTREKKER STR SWELLENDAM | F85: =UPPER('route plans'!G2056) -> NO | G85: =UPPER('route plans'!H2056) -> EST | L85: HARDWARE | M85: =UPPER('route plans'!N2056) -> N/A | N85: =UPPER('route plans'!O2056) -> NO | S85: =UPPER('route plans'!T2056) -> ANDRE V WYK | T85: ='route plans'!U2056 -> 028 514 8672 | W85: ='route plans'!X2056 -> 0 | X85: ='route plans'!Y2056 -> 0 | Y85: =UPPER('route plans'!Z2056) | Z85: =UPPER('route plans'!AA2056) -> ADMIN@OMEGA.CO.ZA;KOBUS@ADMIN.CO.ZA | AB85: ='route plans'!AC2056 -> 823
A86: =UPPER('route plans'!A2165) -> AGRI LAND SWELLENDAM (BRANCH) | B86: =UPPER('route plans'!B2165) -> SWELLENDAM | C86: =UPPER('route plans'!C2165) -> SWELLENDAM | D86: =UPPER('route plans'!D2165) -> WESTERN CAPE | E86: =UPPER('route plans'!E2165) -> 34 VOORTREKKER STR SWELLENDAM | F86: =UPPER('route plans'!G2165) -> NO | G86: =UPPER('route plans'!H2165) -> BUILD IT | L86: HARDWARE | M86: =UPPER('route plans'!N2165) -> N/A | N86: =UPPER('route plans'!O2165) -> N | S86: =UPPER('route plans'!T2165) -> ANDRE V WYK | T86: ='route plans'!U2165 -> 028 514 8672 | W86: ='route plans'!X2165 -> 0 | X86: ='route plans'!Y2165 -> 0 | Y86: =UPPER('route plans'!Z2165) | Z86: =UPPER('route plans'!AA2165) -> HEINDRIE@AHM.CO.ZA | AB86: ='route plans'!AC2165 -> 823
A87: Agri Land Swellendam (Branch) | B87: Swellendam | C87: Swellendam | D87: Western Cape | E87: 34 Voortrekker Str Swellendam | G87: EST | L87: HARDWARE | S87: Andre V Wyk | T87: 028 514 8672 | Z87: avwyk@ssk.co.za
A88: =UPPER('route plans'!A44) -> AGRIFEED BOTSWANA | B88: =UPPER('route plans'!B44) -> BOTSWANA | C88: =UPPER('route plans'!C44) -> BOTSWANA | D88: =UPPER('route plans'!D44) -> BOTSWANA | E88: =UPPER('route plans'!E44) -> PLOT 1253 HALLESALASSI ROAD OLD INDUSTRIAL GABORONE | F88: =UPPER('route plans'!G44) -> NO | G88: =UPPER('route plans'!H44) -> EST | L88: HARDWARE | M88: =UPPER('route plans'!N44) -> N/A | N88: =UPPER('route plans'!O44) -> NO | S88: =UPPER('route plans'!T44) -> SANCHIN BAROT | T88: ='route plans'!U44 -> +267 397 2348 | W88: ='route plans'!X44 -> 0 | X88: ='route plans'!Y44 -> 0 | Y88: =UPPER('route plans'!Z44) | Z88: =UPPER('route plans'!AA44) -> SACHIN_BAROT2000@YAHOO.COM | AB88: ='route plans'!AC44 -> 810
A89: Agrifeed Botswana | B89: Botswana | C89: Botswana | D89: Botswana | E89: Plot 1253 Hallesalassi Road Old Industrial Gabarone | G89: EST | L89: HARDWARE | S89: Sanchin Barot | T89: +267 397 2348 | Z89: sachin_barot2000@yahoo.com
A90: =UPPER('route plans'!A352) -> AGRIMARK DARLING | B90: =UPPER('route plans'!B352) -> DARLING | C90: =UPPER('route plans'!C352) -> DARLING | D90: =UPPER('route plans'!D352) -> WESTERN CAPE | E90: =UPPER('route plans'!E352) -> CORNER OF VOORTREKKER AND R307 | F90: =UPPER('route plans'!G352) -> NO | G90: =UPPER('route plans'!H352) -> KAAP AGRI | L90: HARDWARE | M90: =UPPER('route plans'!N352) -> 30DAYS | N90: =UPPER('route plans'!O352) -> NO | S90: =UPPER('route plans'!T352) | T90: ='route plans'!U352 -> #N/A | W90: ='route plans'!X352 -> 0 | X90: ='route plans'!Y352 -> 0 | Y90: =UPPER('route plans'!Z352) | Z90: =UPPER('route plans'!AA352) -> SHAFIEK@BRIGHTS.CO.ZA;ASHLEIGH@BRIGHTS.CO.ZA | AB90: ='route plans'!AC352 -> #VALUE!
A91: =UPPER('route plans'!A359) -> AGRIMARK DURBANVILLE | B91: =UPPER('route plans'!B359) -> DURBANVILLE | C91: =UPPER('route plans'!C359) -> DURBANVILLE | D91: =UPPER('route plans'!D359) -> WESTERN CAPE | E91: =UPPER('route plans'!E359) -> STRAAT, 30 WELLINGTON RD | F91: =UPPER('route plans'!G359) -> NO | G91: =UPPER('route plans'!H359) -> KAAP AGRI | L91: HARDWARE | M91: =UPPER('route plans'!N359) -> 30DAYS | N91: =UPPER('route plans'!O359) -> NO | S91: =UPPER('route plans'!T359) -> LYNE/BYRON | T91: ='route plans'!U359 -> #N/A | W91: ='route plans'!X359 -> 0 | X91: ='route plans'!Y359 -> 44489 | Y91: =UPPER('route plans'!Z359) | Z91: =UPPER('route plans'!AA359) -> KENWORXMP@GMAIL.COM | AB91: ='route plans'!AC359 -> 832
A92: =UPPER('route plans'!A445) -> AGRIMARK FRANCHOEK | B92: =UPPER('route plans'!B445) -> FRANCHOEK | C92: =UPPER('route plans'!C445) -> FRANCHOEK | D92: =UPPER('route plans'!D445) -> WESTERN CAPE | E92: =UPPER('route plans'!E445) -> RESERVOIR ST | F92: =UPPER('route plans'!G445) -> NO | G92: =UPPER('route plans'!H445) -> KAAP AGRI | L92: HARDWARE | M92: =UPPER('route plans'!N445) -> 30DAYS | N92: =UPPER('route plans'!O445) -> NO | S92: =UPPER('route plans'!T445) -> LYLE | T92: ='route plans'!U445 -> #N/A | W92: ='route plans'!X445 -> 0 | X92: ='route plans'!Y445 -> 0 | Y92: =UPPER('route plans'!Z445) | Z92: =UPPER('route plans'!AA445) | AB92: ='route plans'!AC445 -> #VALUE!
A93: =UPPER('route plans'!A934) -> AGRIMARK KRAAIFONTEIN | B93: =UPPER('route plans'!B934) -> KRAAIFONTEIN | C93: =UPPER('route plans'!C934) -> KRAAIFONTEIN | D93: =UPPER('route plans'!D934) -> WESTERN CAPE | E93: =UPPER('route plans'!E934) -> 165 VOORTREKKER RD | F93: =UPPER('route plans'!G934) -> NO | G93: =UPPER('route plans'!H934) -> KAAP AGRI | L93: HARDWARE | M93: =UPPER('route plans'!N934) -> 30DAYS | N93: =UPPER('route plans'!O934) -> NO | S93: =UPPER('route plans'!T934) -> JP | T93: ='route plans'!U934 -> #N/A | W93: ='route plans'!X934 -> 0 | X93: ='route plans'!Y934 -> 0 | Y93: =UPPER('route plans'!Z934) | Z93: =UPPER('route plans'!AA934) -> ADMINLHH@EIGEVIS.COM; CREDITORS3@EIGEVIS.COM | AB93: ='route plans'!AC934 -> #VALUE!
A94: =UPPER('route plans'!A1105) -> AGRIMARK MALMESBURY | B94: =UPPER('route plans'!B1105) -> MALMESBURY | C94: =UPPER('route plans'!C1105) -> MALMESBURY | D94: =UPPER('route plans'!D1105) -> WESTERN CAPE | E94: =UPPER('route plans'!E1105) -> VOORTREKKER RD | F94: =UPPER('route plans'!G1105) -> NO | G94: =UPPER('route plans'!H1105) -> KAAP AGRI | L94: HARDWARE | M94: =UPPER('route plans'!N1105) -> 30DAYS | N94: =UPPER('route plans'!O1105) -> NO | S94: =UPPER('route plans'!T1105) -> PIETER | T94: ='route plans'!U1105 -> #N/A | W94: ='route plans'!X1105 -> 0 | X94: ='route plans'!Y1105 -> 0 | Y94: =UPPER('route plans'!Z1105) | Z94: =UPPER('route plans'!AA1105) -> RIAAN@KOUESTROOM.CO.ZA | AB94: ='route plans'!AC1105 -> #VALUE!
A95: =UPPER('route plans'!A1438) -> AGRIMARK RIEBEEK KASTEEL | B95: =UPPER('route plans'!B1438) -> RIEBEECK WEST | C95: =UPPER('route plans'!C1438) -> RIEBEECK WEST | D95: =UPPER('route plans'!D1438) -> WESTERN CAPE | E95: =UPPER('route plans'!E1438) -> VOORTREKKER RD | F95: =UPPER('route plans'!G1438) -> NO | G95: =UPPER('route plans'!H1438) -> KAAP AGRI | L95: HARDWARE | M95: =UPPER('route plans'!N1438) -> 30DAYS | N95: =UPPER('route plans'!O1438) -> NO | S95: =UPPER('route plans'!T1438) -> LOUWELLEN | T95: ='route plans'!U1438 -> #N/A | W95: ='route plans'!X1438 -> 0 | X95: ='route plans'!Y1438 -> 0 | Y95: =UPPER('route plans'!Z1438) | Z95: =UPPER('route plans'!AA1438) -> MICHELLE@SWVH.CO.ZA | AB95: ='route plans'!AC1438 -> #VALUE!
A96: =UPPER('route plans'!A1710) -> AGRIMARK STELLENBOCH | B96: =UPPER('route plans'!B1710) -> STELLENBOSCH CENTRAL | C96: =UPPER('route plans'!C1710) -> STELLENBOSCH CENTRAL | D96: =UPPER('route plans'!D1710) -> WESTERN CAPE | E96: =UPPER('route plans'!E1710) -> ADAM TAS RD | F96: =UPPER('route plans'!G1710) -> NO | G96: =UPPER('route plans'!H1710) -> KAAP AGRI | L96: HARDWARE | M96: =UPPER('route plans'!N1710) -> 30DAYS | N96: =UPPER('route plans'!O1710) -> NO | S96: =UPPER('route plans'!T1710) -> WESTLEY | T96: ='route plans'!U1710 -> #N/A | W96: ='route plans'!X1710 -> 0 | X96: ='route plans'!Y1710 -> 0 | Y96: =UPPER('route plans'!Z1710) | Z96: =UPPER('route plans'!AA1710) -> SALES@ONESTOPPLUMBERSSHOP.CO.ZA; ACCOUNTS@ONESTOPPLUMBERSSHOP.CO.ZA | AB96: ='route plans'!AC1710 -> #VALUE!
A97: =UPPER('route plans'!A1540) -> AH MARAIS SEUNS ROBERTSON (HEAD OFFICE) | B97: =UPPER('route plans'!B1540) -> ROBERTSON | C97: =UPPER('route plans'!C1540) -> ROBERTSON | D97: =UPPER('route plans'!D1540) -> WESTERN CAPE | E97: =UPPER('route plans'!E1540) -> 79 KERK STR ROBERTSON 6705 | F97: =UPPER('route plans'!G1540) -> NO | G97: =UPPER('route plans'!H1540) -> EST | L97: HARDWARE | M97: =UPPER('route plans'!N1540) -> N/A | N97: =UPPER('route plans'!O1540) -> NO | S97: =UPPER('route plans'!T1540) -> HEINDRIE MARAIS | T97: ='route plans'!U1540 -> 023 626 3071 | W97: ='route plans'!X1540 -> 0 | X97: ='route plans'!Y1540 -> 0 | Y97: =UPPER('route plans'!Z1540) | Z97: =UPPER('route plans'!AA1540) -> ANDRE@WATERSTONE.CO.ZA | AB97: ='route plans'!AC1540 -> #VALUE!
A98: AH Marais Seuns Robertson (Head Office) | B98: Robertson | C98: Robertson | D98: Western Cape | E98: 79 Kerk str Robertson 6705 | G98: EST | L98: HARDWARE | S98: Heindrie Marais | T98: 023 626 3071 | Z98: heindrie@ahm.co.za
A99: =UPPER('route plans'!A1554) -> AH MARAIS SEUNS ROBERTSON (HEAD OFFICE) | B99: =UPPER('route plans'!B1554) -> ROBERTSON | C99: =UPPER('route plans'!C1554) -> ROBERTSON | D99: =UPPER('route plans'!D1554) -> WESTERN CAPE | E99: =UPPER('route plans'!E1554) -> 79 KERK STR ROBERTSON 6705 | F99: =UPPER('route plans'!G1554) -> NO | G99: =UPPER('route plans'!H1554) -> BUILD IT | L99: HARDWARE | M99: =UPPER('route plans'!N1554) -> N/A | N99: =UPPER('route plans'!O1554) -> N | S99: =UPPER('route plans'!T1554) -> HEINDRIE MARAIS | T99: ='route plans'!U1554 -> 023 626 3071 | W99: ='route plans'!X1554 -> 0 | X99: ='route plans'!Y1554 -> 0 | Y99: =UPPER('route plans'!Z1554) | Z99: =UPPER('route plans'!AA1554) -> LIZAMCGREGOR@MWEB.CO.ZA; LIZA@JOCKSHARDWARE.CO.ZA | AB99: ='route plans'!AC1554 -> #VALUE!
A100: =UPPER('route plans'!A1546) -> AH MARAIS SEUNS WORCESTER (BRANCH) | B100: =UPPER('route plans'!B1546) -> ROBERTSON | C100: =UPPER('route plans'!C1546) -> WORCESTER | D100: =UPPER('route plans'!D1546) -> WESTERN CAPE | E100: =UPPER('route plans'!E1546) -> 12 FIELD STR WORCESTER 6705 | F100: =UPPER('route plans'!G1546) -> NO | G100: =UPPER('route plans'!H1546) -> EST | L100: HARDWARE | M100: =UPPER('route plans'!N1546) -> N/A | N100: =UPPER('route plans'!O1546) -> NO | S100: =UPPER('route plans'!T1546) -> HEINDRIE MARAIS | T100: ='route plans'!U1546 -> 023 342 2540 | W100: ='route plans'!X1546 -> 0 | X100: ='route plans'!Y1546 -> 0 | Y100: =UPPER('route plans'!Z1546) | Z100: =UPPER('route plans'!AA1546) -> SADICK@SOPATRADING.CO.ZA | AB100: ='route plans'!AC1546 -> #VALUE!
...

Sheet Sheet2
A1: BEST HARDWARE | B1: KWAMHLANGA | C1: KWAMHLANGA | D1: MPUMALANGA | E1: SHELDON ROAD, KWAMHALANGA | F1: BEST HARDWARE | G1: KWAMHLANGA | H1: KWAMHLANGA | I1: MPUMALANGA | J1: SHELDON ROAD, KWAMHALANGA
A2: RAJA HARDWARE KWAMHLANGA | B2: KWAMHLANGA | C2: KWAMHLANGA | D2: MPUMALANGA | E2: 1891/2, KWAMHLANGA, 1022 | F2: RAJA HARDWARE KWAMHLANGA | G2: KWAMHLANGA | H2: KWAMHLANGA | I2: MPUMALANGA | J2: 1891/2, KWAMHLANGA, 1022
A3: SA HARDWARE | B3: KWAMHLANGA | C3: KWAMHLANGA | D3: MPUMALANGA | E3: KWAMHLANGA | F3: SA HARDWARE | G3: KWAMHLANGA | H3: KWAMHLANGA | I3: MPUMALANGA | J3: KWAMHLANGA
A4: SUNNY'S HARDWARE KWAMHLANGA | B4: KWAMHLANGA | C4: KWAMHLANGA | D4: MPUMALANGA | E4: 7777 MOLOTO ROAD, KWAMHLANGA | F4: SUNNY'S HARDWARE KWAMHLANGA | G4: KWAMHLANGA | H4: KWAMHLANGA | I4: MPUMALANGA | J4: 7777 MOLOTO ROAD, KWAMHLANGA
A5: SUNNYS HARDWARE SHOP 2 | B5: KWAMHLANGA | C5: KWAMHLANGA | D5: MPUMALANGA | E5: TWEEFONTEIN G R573 KWAMHLANGA | F5: SUNNYS HARDWARE SHOP 2 | G5: KWAMHLANGA | H5: KWAMHLANGA | I5: MPUMALANGA | J5: TWEEFONTEIN G R573 KWAMHLANGA
A6: SHIDY'S HARWARE | B6: KWAMHLANGA | C6: KWAMHLANGA | D6: MPUMALANGA | E6: KWAMHLANGA | F6: SHIDY'S HARWARE | G6: KWAMHLANGA | H6: KWAMHLANGA | I6: MPUMALANGA | J6: KWAMHLANGA
A7: PHOLA HARDWARE & TILE | B7: KWAMHLANGA | C7: KWAMHLANGA | D7: MPUMALANGA | E7: 3,4,5 PHOLA PARK, KWAMHLANGA CROSS ROAD, KWAMHLANGA | F7: PHOLA HARDWARE & TILE | G7: KWAMHLANGA | H7: KWAMHLANGA | I7: MPUMALANGA | J7: 3,4,5 PHOLA PARK, KWAMHLANGA CROSS ROAD, KWAMHLANGA
A8: PHOOL HARDWARE | B8: KWAMHLANGA | C8: KWAMHLANGA | D8: MPUMALANGA | E8: 7936 LETHULI SECTION | F8: PHOOL HARDWARE | G8: KWAMHLANGA | H8: KWAMHLANGA | I8: MPUMALANGA | J8: 7936 LETHULI SECTION
A9: QISMAT HARDWARE | B9: KWAMHLANGA | C9: KWAMHLANGA | D9: MPUMALANGA | E9: SHELDON ROAD, KHAYALISHA | F9: QISMAT HARDWARE | G9: KWAMHLANGA | H9: KWAMHLANGA | I9: MPUMALANGA | J9: SHELDON ROAD, KHAYALISHA
A10: MJ HARDWARE | B10: KWAMHLANGA | C10: KWAMHLANGA | D10: MPUMALANGA | E10: 1891 TWEEFONTEIN, KWAMHLANGA | F10: MJ HARDWARE | G10: KWAMHLANGA | H10: KWAMHLANGA | I10: MPUMALANGA | J10: 1891 TWEEFONTEIN, KWAMHLANGA

Sheet Sheet3
A1: PWR BUILD (PTY) LTD MONTHLY SALES TRACKER - SUPPLIER FIGURES 2022
A2: SUPPLIER NAME: INSERT NAME HERE | F2: Ver 36- 1 June 22 | U2: 2022
A3: POWER BUILD MEMBERS
A4: Region | B4: Account Number | C4: Legal Entity | D4: Trading Name | E4: Physical Address | F4: Vat Number | G4: Date Joined | H4: Supp Member account no | I4: 44562 | J4: 44593 | K4: 44621 | L4: 44652 | M4: 44682 | N4: 44713 | O4: 44743 | P4: 44774 | Q4: 44805 | R4: 44835 | S4: 44866 | T4: 44896 | U4: TOTAL 2019/2020
A5: Botswana | B5: MAXIS0003 | C5: Maxi Save Botswana (Pty) Ltd | D5: Maxi Save | E5: Plot 22015, Gaborone West, Gaborone | F5: C00771501112 | G5: 1 Feb 20 | U5: =SUM(I5:T5) -> 0
A6: Eastern Cape | B6: AHMAQECRB3 | C6: A.H. Mart (Pty) Ltd | D6: A.H Mart | E6: 146 Old Main Road / Street, Qumbu, Eastern Cape,5180 | F6: 4300286764 | G6: 4-Aug-20 | U6: =SUM(I6:T6) -> 0
A7: Eastern Cape | B7: AHMAMECRB3 | C7: A.H. Mart (Pty) Ltd | D7: A.H Mart (Additional Delivery Address Mdantsane) | E7: Shop No.8, Shoprite Mall, NU2 Highway, Mdantsane, 5419 | F7: 4300286764 | G7: 4-Aug-20 | U7: =SUM(I7:T7) -> 0
A8: Eastern Cape | B8: AHMA2ECUB3 | C8: A.H. Mart (Pty) Ltd | D8: A.H Mart (Additional Delivery Address Queenstown) | E8: 6 Shepstone Street, Queenstown, Eastern Cape, 5320 | F8: 4300286764 | G8: 44328 | U8: =SUM(I8:T8) -> 0
A9: Eastern Cape | B9: MASAKECRB6 | C9: Ali Vision Trading (Pty) Ltd | D9: Masakhane Hardware | E9: Shop No 2, Maint Street, Viedgesville | F9: TBA | G9: 44317 | U9: =SUM(I9:T9) -> 0
A10: Eastern Cape | B10: BUMK1ECSD5 | C10: Build Mart Holdings (Pty) Ltd | D10: Build Mart | E10: 21 Groom Street, Kokstad, 4700 | F10: Pending | G10: 43770 | U10: =SUM(I10:T10) -> 0
A11: Eastern Cape | B11: CITYMECRB6 | C11: City Hardware Matatiele (Pty) Ltd | D11: City Hardware Matatiele | E11: 17 Long Street, Matatiele, eastern Cape, 4730 | F11: 4950280547 | G11: 44440 | U11: =SUM(I11:T11) -> 0
A12: Eastern Cape | B12: HOMEDECUB4 | C12: Come To Trade Hardware (Pty) Ltd | D12: Home Depo | E12: No 2 Blyth Street, Butterworth, 4960 | F12: Pending | G12: 43678 | U12: =SUM(I12:T12) -> 0
A13: Eastern Cape | B13: AFRIAECRB5 | C13: Frands Tranding and Projects 4 CC | D13: Africa Hardware | E13: Erf 21, Main Street, Mqanduli, 5080 | F13: 4220253084 | G13: 43990 | U13: =SUM(I13:T13) -> 0
A14: Eastern Cape | B14: ENKIHECRB5 | C14: Frands Tranding and Projects 4 CC | D14: Enkosi Hardware | E14: Erf 24, Main Street, Mqanduli, 5080 | F14: 4220253084 | G14: 43990 | U14: =SUM(I14:T14) -> 0
A15: Eastern Cape | B15: GAZI2ECUB5 | C15: Good Luck Hardware (Pty) Ltd | D15: Gazi Hardware | E15: 55 Main Street, Dordrect, Eastern Cape, 5470 | F15: TBA | G15: 44334 | U15: =SUM(I15:T15) -> 0
A16: Eastern Cape | B16: GOOD1ECUB5 | C16: Good Luck Hardware (Pty) Ltd | D16: Good Luck Hardware Ugie | E16: 12 Plein Street, Ugie, Eastern Cape, 5470 | F16: TBA | G16: 44334 | U16: =SUM(I16:T16) -> 0
A17: Eastern Cape | B17: EHDI1ECUD6 | C17: Happy Home Investments (Pty) Ltd | D17: Eyethu Hardware DIY Fort Beaufort | E17: 60 Campbell Street, Fort Beaufort, Eastern Cape, 5720 | F17: Pending | G17: 44470 | U17: =SUM(I17:T17) -> 0
A18: Eastern Cape | B18: ENDI2ECUD6 | C18: Happy Home Investments (Pty) Ltd | D18: Eyethu Hardware DIY Fort Beaufort (Barrack Street) | E18: 42 Barrack Street, Fort Beaufort, 5720 | F18: Pending | G18: 44470 | U18: =SUM(I18:T18) -> 0
A19: Eastern Cape | B19: ENDI3ECUD6 | C19: Happy Home Investments (Pty) Ltd | D19: Eyethu Hardware DIY Fort Beaufort (StringFellow Street) | E19: 17 Stringfellow Street, Adelaide, 5760 | F19: Pending | G19: 44470 | U19: =SUM(I19:T19) -> 0
A20: Eastern Cape | B20: BLOCCECRB6 | C20: High Class Trading and Construction (Pty) Ltd | D20: Block City | E20: 1069 Braodsword Road, Zitulele Industrial Butterworth, Eastern Cape, 4960 | F20: Pending | G20: 44470 | U20: =SUM(I20:T20) -> 0
A21: Eastern Cape | B21: AKHDWECRD6 | C21: Inter Kei Investments | D21: AK Hardwrae | E21: 82 Thurston Street, Tsolo, South Africa, 5170 | F21: 4810288623 | G21: 44448 | U21: =SUM(I21:T21) -> 0
A22: Eastern Cape | B22: BCSHHECRB6 | C22: Izam Trading (Pty) Ltd | D22: Build Cash Hardware | E22: N2 Ultra City, East London Road, Umtata, 5100 | F22: Pending | G22: 43990 | U22: =SUM(I22:T22) -> 0
A23: Eastern Cape | B23: KHAWHECRB3 | C23: Khawer (Pty) Ltd | D23: Khawer Hardware | E23: 62 North Street, Qumbu, 5180 | F23: 4430290702 | G23: 11 Nov 20 | U23: =SUM(I23:T23) -> 0
A24: Eastern Cape | B24: BUFFMECRB6 | C24: Lala Hardware (Pty) Ltd | D24: Buffalo Hardware | E24: Shop 1, Albert Street, Peddie, Eastern Cape, 5640 | F24: 9092299230 | G24: 44621 | U24: =SUM(I24:T24) -> 0
A25: Eastern Cape | B25: LALAHECRB6 | C25: Lala Hardware (Pty) Ltd | D25: Lala Hardware | E25: Shop 3, Albert Street, Peddie, Eastern Cape, 5640 | F25: 9092299230 | G25: 44621 | U25: =SUM(I25:T25) -> 0
A26: Eastern Cape | B26: INDALECSB4 | C26: Major Asjad Traders (Pty) Ltd | D26: Allied Build (Additional Delivery Address for Indali) | E26: 15 Errol Spring Avenue, Vulindlela Heights, Mthatha, 5099 | F26: 4240263055 | G26: 43850 | U26: =SUM(I26:T26) -> 0
A27: Eastern Cape | B27: IDDBSECUB4 | C27: Major Asjad Traders (Pty) Ltd | D27: Indali Building Supplier | E27: R61, Port St Johns Road, Coana ,Mthatha ,5099 | F27: 4240263055 | G27: 43850 | U27: =SUM(I27:T27) -> 0
A28: Eastern Cape | B28: LURHHECUB4 | C28: Major Asjad Traders (Pty) Ltd | D28: Lurhasini Hardware (Additional Delivery Address for Indali) | E28: N2 Road Lurhasini, Mthatha, 5116 | F28: 4240263055 | G28: 43850 | U28: =SUM(I28:T28) -> 0
A29: Eastern Cape | B29: MHENGECRB6 | C29: Mfundisi Bricks & Hardware (Pty) Ltd | D29: Mfundisi Hardware Engcobo | E29: 205 Main Street, Ngcobo, Eastern Cape, 5050 | F29: 4370283386 | G29: 44470 | U29: =SUM(I29:T29) -> 0
A30: Eastern Cape | B30: BFALIECSB5 | C30: Modern Time Trading CC | D30: Ali's Hardware (Additional Delivery Address for Buildfast) | E30: 6 Ntsizwa Street, Mt Ayliff, Eastern Cape, 4735 | F30: 40702585555 | G30: 43739 | U30: =SUM(I30:T30) -> 0
A31: Eastern Cape | B31: BUFT1ECSB5 | C31: Modern Time Trading CC | D31: Buildfast Warehouse | E31: Shop 15 to 20, Ntsizwa Street, Mt Ayliff, Eastern Cape, 4735 | F31: 40702585555 | G31: 43739 | U31: =SUM(I31:T31) -> 0
A32: Eastern Cape | B32: KINGNECRB3 | C32: Namul Trading (Pty) Ltd | D32: Kings Hardware (Maclear) | E32: Shop No 2, Fourie Street, Maclear, 5480 | F32: 4380286833 | G32: 44146 | U32: =SUM(I32:T32) -> 0
A33: Eastern Cape | B33: HARDWECRB5 | C33: Nedtex 4 CC | D33: Hardware Citi Sterkspruit | E33: 1 Van Tonder Street, Sterkspruit, Eastern Cape | F33: 4650257407 | G33: 44385 | U33: =SUM(I33:T33) -> 0
A34: Eastern Cape | B34: WELCOECRB5 | C34: Phindabantu Services (Pty) Ltd | D34: Welcome Hardware | E34: R61 Main Engcobo Road, Coghlan, Eastern Cape, 5054 | F34: 4270292693 | G34: 44334 | U34: =SUM(I34:T34) -> 0
A35: Eastern Cape | B35: RAJA1ECUB5 | C35: Raja Electronic Shop CC | D35: Raja Hardware Shop 1 | E35: 9 Gilwell Street, East London, 5209 | F35: 42302550238 | G35: 44105 | U35: =SUM(I35:T35) -> 0
A36: Eastern Cape | B36: RAJA2ECUB5 | C36: Raja Electronic Shop CC | D36: Raja Hardware Shop 2 | E36: Shop 1, Main Street N2, Opposite KFC Idutywa | F36: 42302550238 | G36: 44105 | U36: =SUM(I36:T36) -> 0
A37: Eastern Cape | B37: OSSKWECRB6 | C37: S.H. Rizvi T/A Ossher Bros | D37: Ossher Bros | E37: No. 2341 Main Dimbaza Road, Thembisa Ext, Near King Williams Town, 5671 | F37: Pending | G37: 44470 | U37: =SUM(I37:T37) -> 0
A38: Eastern Cape | B38: OSSGTECRB6 | C38: S.H. Rizvi T/A Ossher Bros | D38: Ossher Bros (Grahamstown) | E38: 20 Beaufort Street, Grahamstown, 6139 | F38: Pending | G38: 44470 | U38: =SUM(I38:T38) -> 0
A39: Eastern Cape | B39: BAFA1ECUB5 | C39: Safi Traders CC | D39: Bafana Bafana Hardware Cala | E39: Erf No 304 Main Street Cala, Eastern Cape, 5470 | F39: 439025596 | G39: 44348 | U39: =SUM(I39:T39) -> 0
A40: Eastern Cape | B40: DIAM2ECUB5 | C40: Safi Traders CC | D40: Diamond Hardware | E40: Shop 2 Rugby Street, Maclear, Eastern Cape, 5470 | F40: 439025596 | G40: 44348 | U40: =SUM(I40:T40) -> 0
A41: Eastern Cape | B41: SAMANECRB4 | C41: Samander Trading Enterprice (Pty) Ltd | D41: Samander Hardware | E41: Shop No 5 , Maholweni Park , Slovo Park (Opposite JJ) Mthatha,5099 | F41: 4560275309 | G41: 43819 | U41: =SUM(I41:T41) -> 0
A42: Eastern Cape | B42: AFRI1ECUB5 | C42: Sher 786 (Pty) Ltd | D42: African Hardware Berlin | E42: 1800 Legion Street, Berlin, East London, Eastern Cape | F42: TBA | G42: 44317 | U42: =SUM(I42:T42) -> 0
A43: Eastern Cape | B43: AFRI3ECUB5 | C43: Sher 786 (Pty) Ltd | D43: African Hardware Store King Williams Town | E43: 168 Buffalo Street, King Williams Town, Eastern Cape | F43: TBA | G43: 44317 | U43: =SUM(I43:T43) -> 0
A44: Eastern Cape | B44: HOME2ECUB5 | C44: Sher 786 (Pty) Ltd | D44: Home Choice Hardware | E44: Opposite Shoprite, Mdanstane Highway, Mdantsane, East London | F44: TBA | G44: 44317 | U44: =SUM(I44:T44) -> 0
A45: Eastern Cape | B45: RAHDKECRB5 | C45: Shiaad Trading CC | D45: Raja Hardware Kentani | E45: Shop 1, Main Street, Kentani, 4980 | F45: 4150287619 | G45: 44256 | U45: =SUM(I45:T45) -> 0
A46: Eastern Cape | B46: RRHARECUB6 | C46: Tip Top Cell and Technology | D46: R & R hardware | E46: Shop No 4, Arches Building Taylor, King Williamstown, 5600 | F46: 4300301902 | G46: 44531 | U46: =SUM(I46:T46) -> 0
A47: Eastern Cape | B47: KINGHECRB6 | C47: Willowvale Hardware And Builders (Pty) Ltd | D47: King Hardware | E47: 31 Umga Street, Ugie, Eastern Cape, 5470 | F47: 4470275571 | G47: 44470 | U47: =SUM(I47:T47) -> 0
A48: Eastern Cape | B48: ZIYAHECRB6 | C48: Ziyabuya Hardware (Pty) Ltd | D48: Ziyabuya Hardware | E48: Shop 5, Ziyabuya Centre, Kwadwesi, Next to KFC, Port Elizabeth, 6201 | F48: 4270290499 | G48: 44682 | U48: =SUM(I48:T48) -> 0
A49: Free State | B49: HRDHBFSUB6 | C49: Al-Kauthar Investments CC | D49: Hardware Hub | E49: 557 Main Road, Clubview, Qwa Qwa, 9866 | F49: 4900277924 | G49: 43770 | U49: =SUM(I49:T49) -> 0
A50: Free State | B50: KWIKVFSRH5 | C50: Areemaz Investments (Pty) Ltd | D50: Kwikbuild Vrede | E50: 57 Church Street, Vrede, 9835 | F50: 4080262530 | G50: 43795 | U50: =SUM(I50:T50) -> 0
A51: Free State | B51: PAINTFSUD6 | C51: Nkosana Trust | D51: Paints Direct | E51: 3 Oranje Strret, Hilton, Bloemfontein, 9300 | F51: 4160251965 | G51: 1 Jun-19 | U51: =SUM(I51:T51) -> 0
A52: Free State | B52: BARGAFSUB5 | C52: Probrick Pty Ltd | D52: Bargain Build BFN | E52: Shop 7 Mega Park , Curie avenue , Bloemfontein,9301 | F52: 4260292216 | G52: 44378 | U52: =SUM(I52:T52) -> 0
A53: Gauteng | B53: BKWIKGPUD6 | C53: Ascension Consulting (Pty) Ltd | D53: Build Kwik | E53: 110 Linksfield Road &, Club Street, Linksfield, Johannesburg, 2192 | F53: 4390289207 | G53: 44652 | U53: =SUM(I53:T53) -> 0
A54: Gauteng | B54: GARSHGPUD3 | C54: Class A Trading 64 (Pty) Ltd | D54: Garsfontein PowerBuild | E54: Units 1,2,3,4 Sunbird Centre c/o Sunbird & Delft Avenue, Garsfonein, 0042 | F54: 4910191230 | G54: 43344 | U54: =SUM(I54:T54) -> 0
A55: Gauteng | B55: COSAVGPUB2 | C55: Cosave Retail (Pty) Ltd | D55: Cosave PowerBuild | E55: 560 Alfred Boyes Ave, Kirkney Ext 5, Pretoria, 0182 | F55: 4720284191 | G55: 43770 | U55: =SUM(I55:T55) -> 0
A56: Gauteng | B56: PBSILGPUB6 | C56: DENENPINE (PTY) LTD | D56: Powerbuild Silverton | E56: 250 Waltloo Road, C/O Pretoria & Waltloo Road, Silverton, 0184 | F56: Pending | G56: 44593 | U56: =SUM(I56:T56) -> 0
A57: Gauteng | B57: DIYHCGPUD6 | C57: DIY Hardware and Crafts Doornpoort (Pty) Ltd | D57: DIY Hardware and Crafts Doornpoort | E57: Shop 17, 487 Airport Road, Doornpoort, Pretoria | F57: 4660221716 | G57: 44621 | U57: =SUM(I57:T57) -> 0
A58: Gauteng | B58: EIKENGPUH4 | C58: Eikenhof Electrical and Hardware (Pty) ltd | D58: Eikenhof Electrical and Hardware (Pty) ltd | E58: 161 Klipriver Road, Eikenhof | F58: 4330282536 | G58: 44347 | U58: =SUM(I58:T58) -> 0
A59: Gauteng | B59: GLOBWGPUB6 | C59: Global Builders Warehouse (Pty) Ltd | D59: Global Builders Warehouse | E59: 40 Bowling Avenue, Wendywood, Sandton, Johannesburg, 2146 | F59: 4400303154 | G59: 44621 | U59: =SUM(I59:T59) -> 0
A60: Gauteng | B60: JCCDRGPUD6 | C60: JC'S Cornice & Décor (Pty) Ltd | D60: JC'S Cornice & Décor | E60: Karen Park Crossing Shopping Centre, Cnr Heinrich& Doreg Avenue, Pretoria North, 0182 | F60: 4710266133 | G60: 43860 | U60: =SUM(I60:T60) -> 0
A61: Gauteng | B61: K43BSGPRB6 | C61: K43 Building Supplies (Pty) Ltd | D61: K43 Powerbuild | E61: 8586 Corner of K43 and Vaal Road, Lenasia, 1820 | F61: Pending | G61: 44501 | U61: =SUM(I61:T61) -> 0
A62: Gauteng | B62: POWERGPUH4 | C62: Kagiso D.I.Y Centre CC | D62: PowerBuild Krugersdorp | E62: 21 Adolf Schneider Ave, Krugersdorp North | F62: 4430211708 | G62: 44317 | U62: =SUM(I62:T62) -> 0
A63: Gauteng | B63: NIGELGPUH3 | C63: Labyrinth Trading 6 (Pty) LTd | D63: Nigel Power Build | E63: The Angelo Mall, Cnr Rhodes and Nigel - Springs Rd, Nigel, 1491 | F63: 4900252653 | G63: 43344 | U63: =SUM(I63:T63) -> 0
A64: Gauteng | B64: LENZHGPD56 | C64: lenz Hardware (Pty) Ltd | D64: Lenz Hardware | E64: Plot 29, Nirvana Drive, Ext 9, Lenasia, 1827 | F64: 9350822202 | G64: 44440 | U64: =SUM(I64:T64) -> 0
A65: Gauteng | B65: LISBSGPUB6 | C65: Lisel Building Supplies (Pty) Ltd | D65: Lisel Building Supplies | E65: 89 Kemston Avenue, Benoni, 1500 | F65: 4160294213 | G65: 44593 | U65: =SUM(I65:T65) -> 0
A66: Gauteng | B66: MAPH1GPUD2 | C66: Malik's Paint & Hardware CC | D66: Powerbuild Azaadville | E66: 6 Taj Mahal Street, Azaadville | F66: 4660220122 | G66: 43860 | U66: =SUM(I66:T66) -> 0
A67: Gauteng | B67: MAPH2GPUD2 | C67: Malik's Paint & Hardware CC | D67: Powerbuild Chamdor | E67: 16 Jacobs Street , Chamdor , Gauteng, 1754 | F67: 4660220122 | G67: 43860 | U67: =SUM(I67:T67) -> 0
A68: Gauteng | B68: MAPH4GPUD2 | C68: Malik's Paint & Hardware CC | D68: Powerbuild Kagiso Mall | E68: Shop 22 , Kagiso Mall, Kagiso | F68: 4660220122 | G68: 43860 | U68: =SUM(I68:T68) -> 0
A69: Gauteng | B69: MAPH8GPUD2 | C69: Malik's Paint & Hardware CC | D69: Powerbuild Midway | E69: Chris Hani Road, Midway, Soweto | F69: 4660220122 | G69: 44562 | U69: =SUM(I69:T69) -> 0
A70: Gauteng | B70: MAPH5GPUD2 | C70: Malik's Paint & Hardware cc | D70: Powerbuild Mohlakeng | E70: 2483 Ntuli Street , Mohlakeng, Randfontein | F70: 4660220122 | G70: 43617 | U70: =SUM(I70:T70) -> 0
A71: Gauteng | B71: MAPH6GPUD2 | C71: Malik's Paint & Hardware cc | D71: Powerbuild Munsieville | E71: 1596 Monala Street, Munsieville, Krugersdorp | F71: 4660220122 | G71: 43344 | U71: =SUM(I71:T71) -> 0
A72: Gauteng | B72: PBRANGPRD6 | C72: Malik's Paint & Hardware cc | D72: Powerbuild Randfontein | E72: 97 Main Reef Road, West Porges, Randfontein, 1759 | F72: 4660220122 | G72: 43374 | U72: =SUM(I72:T72) -> 0
A73: Gauteng | B73: MAPH7GPUD2 | C73: Malik's Paint & Hardware cc | D73: Powerbuild Roodepoort | E73: No 1 Station street , Roodepoort | F73: 4660220122 | G73: 43374 | U73: =SUM(I73:T73) -> 0
... A79: Gauteng | B79: BBHVBGPRB2 | C79: Silver Solutions 1399 CC | D79: Best Build Hardware Vanderbijlpark | E79: 38 Hans Strijdom Street, Vanderbilpark | F79: 4880285723 | G79: 43282 | U79: =SUM(I79:T79) -> 0
A80: Gauteng | B80: PBMODLPH6 | C80: Sincere Earth (Pty) Ltd | D80: Powerbuild Modimolle | E80: Corner of Nelson Mandela and Allan Street, Modimolle, 0150 | F80: Pending | G80: 44470 | U80: =SUM(I80:T80) -> 0
A81: Gauteng | B81: CEMMKGPRB1 | C81: The Cement Market (Pty) Ltd | D81: The Cement Market | E81: 259 Tungsten Road, Ekandustria, Bronkhorspruit, 1028 | F81: 4850263270 | G81: 44112 | U81: =SUM(I81:T81) -> 0
A82: Gauteng | B82: TJHBSGPUH3 | C82: TJ Hardware & Building Supplies CC | D82: TJ Hardware & Building Supplies | E82: 56 Merz Street, Heidelberg,1438 | F82: 4090273287 | G82: 43601 | U82: =SUM(I82:T82) -> 0
A83: Gauteng | B83: PBS0SGPRB6 | C83: TPS Hardware Group (Pty) Ltd | D83: Powerbuild Soshanguve | E83: M21 Lucas Mangope Street, New Eesertus, Soshanguve | F83: Pending | G83: 44621 | U83: =SUM(I83:T83) -> 0
A84: Gauteng | B84: PHOLAGPRB6 | C84: Virashield (Pty) Ltd | D84: Phola Powerbuild | E84: Plot 40, R573, Molot Road, Roodeplaat., 0035 | F84: TBA | G84: 44383 | U84: =SUM(I84:T84) -> 0
A85: Gauteng | B85: PBCO2GP5B6 | C85: We Build 4 U (Pty) Ltd | D85: Powerbuild Cosmo City Ext 3 | E85: Corner of Boundry and Solvenia Street, Cosmo City | F85: 4910290255 | G85: 44470 | U85: =SUM(I85:T85) -> 0
A86: Gauteng | B86: PBCO1GP5B6 | C86: We Build 4 U (Pty) Ltd | D86: Powerbuild Cosmo City Ext 6 | E86: Shop 28 , Cosmo City Shopping Centre , Cosmo City | F86: 4910290255 | G86: 44470 | U86: =SUM(I86:T86) -> 0
A87: KZN | B87: FHBBSKNRB6 | C87: A.F. Assi Trading | D87: Bhamshela Builder Supply | E87: R614 Tongaat Road, Bhamshela | F87: 9223523243 | G87: 44470 | U87: =SUM(I87:T87) -> 0
A88: KZN | B88: FHESHKNRB6 | C88: A.F. Assi Trading | D88: Escourt Hardware | E88: 135 Albert Street, Escourt | F88: 9223523243 | G88: 44470 | U88: =SUM(I88:T88) -> 0
A89: KZN | B89: FHPONKNRB6 | C89: A.F. Assi Trading | D89: Friends Hardware | E89: 238 Pietretief Road, Pongola, 3068 | F89: 9223523243 | G89: 44470 | U89: =SUM(I89:T89) -> 0
A90: KZN | B90: FHKHUKNRB6 | C90: A.F. Assi Trading | D90: KZN Hardware Ulundi | E90: Opposite Shell Garage, 3838 | F90: 9223523243 | G90: 44470 | U90: =SUM(I90:T90) -> 0
A91: KZN | B91: FHMKHKNRB6 | C91: A.F. Assi Trading | D91: Mkhondo Hardware | E91: 14 Church Street, Pietretief | F91: 9223523243 | G91: 44470 | U91: =SUM(I91:T91) -> 0
A92: KZN | B92: FHSHEKNRB6 | C92: A.F. Assi Trading | D92: Sonera Hardware Eshowe | E92: 105 Osborne Road, Eshowe, 3815 | F92: 9223523243 | G92: 44470 | U92: =SUM(I92:T92) -> 0
A93: KZN | B93: ENABHKNSH4 | C93: A.K Haffejee Family Trust & E.A Haffejee Family Trust | D93: Enanda Builders Hardware | E93: 5583 Curnic Ndlovu, Highway, Inanda, KZN | F93: 4070170693 | G93: 43388 | U93: =SUM(I93:T93) -> 0
A94: KZN | B94: ENACCKN5H4 | C94: A.K Haffejee Family Trust & E.A Haffejee Family Trust | D94: Inanda City Centre (Additional delivery address for Enanda) | E94: Shop 1, 93 Main Road, Inanda, KZN | F94: 4070170693 | G94: 43891 | U94: =SUM(I94:T94) -> 0
A95: KZN | B95: ABBAMKNUD6 | C95: Abba Moosa Hardware CC | D95: Abba Moosa Hardware | E95: 189 Moses Kotane Road, Overport, 4091 | F95: 4010191163 | G95: 43374 | U95: =SUM(I95:T95) -> 0
A96: KZN | B96: BUUP1KNRB6 | C96: Adams Close Investments (Pty) Ltd | D96: Build Up Hardware | E96: D994 Lot 2, Umbumbulu, Off R603, Kzn | F96: 4440300459 | G96: 44470 | U96: =SUM(I96:T96) -> 0
A97: KZN | B97: BUUP2KNRB6 | C97: Adams Close Investments (Pty) Ltd | D97: Build Up Hardware | E97: 228 Quarry Road East, Springfield Park Durban | F97: 4440300459 | G97: 44470 | U97: =SUM(I97:T97) -> 0
A98: KZN | B98: PREMHKNURD6 | C98: AL Naqeeb Traders (PTY) Ltd | D98: Prime Hardware | E98: Shop 2, 44 Old Main Road, Pine Town, 3610 | F98: Pending | G98: 44621 | U98: =SUM(I98:T98) -> 0
A99: KZN | B99: SMARTKNUB5 | C99: Asad Hardware CC | D99: Smart Build | E99: Shop No.3 John Ross Centre, John Ross Highway, Mtubatuba, 3635 | F99: 4150256552 | G99: 43728 | U99: =SUM(I99:T99) -> 0
A100: KZN | B100: KINGSKNUH5 | C100: Bassas Brick & Block CC | D100: Kings Hardware Scottsburgh | E100: 110 Scott Street, Scottsburgh, Durban | F100: 4540227610 | G100: 43374 | U100: =SUM(I100:T100) -> 0
A101: KZN | B101: BCINDKNUD5 | C101: BC Industrial and Engineering Supplies CC | D101: BC Industrial and Engineering Supplies CC | E101: 38 Beechfield Cresent, Springfield Park, Durban, 4051 | F101: 4270159801 | G101: 44076 | U101: =SUM(I101:T101) -> 0
A102: KZN | B102: JABMYKNUH3 | C102: Brackley Investments CC | D102: Jabula Hardware Mayville | E102: 2 Carlow Road, Mayville, Durban, 4091 | F102: 4430211336 | G102: 43313 | U102: =SUM(I102:T102) -> 0
A103: KZN | B103: JABMUKNUH3 | C103: Brackley Investments CC | D103: Jabula Hardware Mayville (Additonal Delivery Address) | E103: Umgababa, Old Main Road , Danganya | F103: 4220265054 | G103: 43313 | U103: =SUM(I103:T103) -> 0
A104: KZN | B104: BASN1KNUH2 | C104: Branberry Investments CC | D104: Bassas Hardware Newlands | E104: 920 Inanda Road, Newlands, Durban, 4037 | F104: 4180161511 | G104: 43313 | U104: =SUM(I104:T104) -> 0
A105: KZN | B105: BASN2KNUH2 | C105: Branberry Investments CC | D105: Bassas Hardware Newlands | E105: 768 Inanda Road, Newlands, Durban, 4037 | F105: 4180161511 | G105: 43728 | U105: =SUM(I105:T105) -> 0
...
